Workbook

Sheet How to Use
A1: How to Use
A3: 1. Fill the cream cells (blue text) on Application Inventory, one row per application. Grey cells are formulas.
A4: 2. Usage Status: Active Users = 0 or not used for 6+ months → 'Not in use'.
A5: 3. Retirement drivers (0–4): low / no use · replacement named · out of support · low business value.
A6: Drivers are indicative only. Decision is chosen from the dropdown: Decommission · Retire · Retire + Archive · Retain · Pending.
A7: 4. Complexity: Data Archival Required = N → Easy · else High if many interfaces, large data or critical · else Medium.
A8: 5. Record what must remain after shutdown in Post-Retirement Requirement (archive, read-only, legal hold).
A9: 6. Decision is an input (cream cell). Record any exception or rationale in Comments / Questions.
A10: 7. TBD = information still to be confirmed with the owner.
A11: 8. Thresholds and the as-of date (01-May-2021) are on the Scoring Settings tab.
A12: 9. Status: Completed = switched off · In progress = executing now · Approved = funded and scheduled · Under Review = awaiting decision · On hold = paused · Rejected = retained.

Sheet Application Inventory
A1: Application Inventory
A2: Cream cells = inputs (blue text). Grey cells = formulas. TBD = to be confirmed. Rules and thresholds on the 'Scoring Settings' tab.
A3: Identity | F3: Ownership | I3: Usage & Value | O3: Infrastructure | V3: Data & Archival | AB3: Dependencies | AC3: Documentation | AF3: Cost & Contract | AK3: Decision | AN3: Plan
A4: App ID | B4: App Name | C4: Business Capability | D4: Line of Business | E4: Exposure (Internal / External / Partner) | F4: Business Owner | G4: IT Owner | H4: Infra Owner | I4: Active Users (last 90d) | J4: Last Used Date | K4: Usage Status | L4: Business Value (1-5) | M4: Criticality Tier (1-4) | N4: Replacement / Target App | O4: Hosting | P4: Server Hostname(s) | Q4: # Servers | R4: OS / Version | S4: Database / Version | T4: Data Centre / Cloud Region | U4: End-of-Support Date | V4: Data Type | W4: Data Volume (GB) | X4: PII / Regulated (Y/N) | Y4: Retention (yrs) | Z4: Data Archival Required (Y/N) | AA4: Post-Retirement Requirement | AB4: Interfaces (#) | AC4: User / Functional Docs | AD4: Technical Design Docs | AE4: Architecture Diagram | AF4: Annual Run Cost ($) | AG4: Contract End Date | AH4: Est. Decom Cost ($) | AI4: Annual Savings ($) | AJ4: Payback (months) | AK4: Retirement Drivers (0-4) | AL4: Decision | AM4: Complexity | AN4: Wave | AO4: Target Retirement Date | AP4: Status | AQ4: Comments / Questions
A5: 195761 | B5: Global Cash Position Reporter (Nordics) | C5: Treasury | D5: Finance | E5: Internal | I5: 145 | J5: 44297 | K5: =IF(B5="","",IF(AND(I5="",J5=""),"Unknown",IF(OR(AND(ISNUMBER(I5),I5=0),AND(ISNUMBER(J5),J5<=EDATE('Scoring Settings'!$B$4,-'Scoring Settings'!$B$5))),"Not in use",IF(AND(ISNUMBER(I5),I5<'Scoring Settings'!$B$6),"Low use","Active")))) -> Active | L5: 4 | M5: 2 | N5: SAP Concur | O5: PaaS | P5: Azure App Service (PaaS) | Q5: 0 | R5: N/A (PaaS) | S5: Cosmos DB | T5: Azure West Europe | U5: 44742 | V5: Structured | W5: 230 | X5: Y | Y5: 10 | Z5: Y | AA5: Reporting extract | AB5: 15 | AC5: Y | AD5: Y | AE5: N | AF5: 7000 | AG5: 48548 | AH5: 6500 | AI5: 5500 | AJ5: =IF(AND(ISNUMBER(AH5),ISNUMBER(AI5),N(AI5)>0),AH5/AI5*12,"") -> 14.181818 | AK5: =IF(B5="","",OR(K5="Not in use",K5="Low use")+AND(N5<>"",N5<>"TBD")+AND(ISNUMBER(U5),U5<=EDATE('Scoring Settings'!$B$4,'Scoring Settings'!$B$8))+AND(ISNUMBER(L5),L5<='Scoring Settings'!$B$7)) -> 1 | AL5: Migrate | AM5: =IF(B5="","",IF(Z5="N","Easy",IF(OR(AND(ISNUMBER(AB5),AB5>'Scoring Settings'!$B$11),AND(ISNUMBER(W5),W5>'Scoring Settings'!$B$12),AND(ISNUMBER(M5),M5<='Scoring Settings'!$B$13)),"High","Medium"))) -> High | AN5: Wave 1 | AO5: 44377 | AP5: In progress | AQ5: Funding approved; migration to SAP Concur scheduled
A6: 38051 | B6: Corporate Asset Register v2 | C6: Fixed Assets | D6: Finance | E6: Internal | I6: 0 | J6: 44003 | K6: =IF(B6="","",IF(AND(I6="",J6=""),"Unknown",IF(OR(AND(ISNUMBER(I6),I6=0),AND(ISNUMBER(J6),J6<=EDATE('Scoring Settings'!$B$4,-'Scoring Settings'!$B$5))),"Not in use",IF(AND(ISNUMBER(I6),I6<'Scoring Settings'!$B$6),"Low use","Active")))) -> Not in use | L6: 2 | M6: 4 | O6: IaaS | P6: carapp01, cardb01, carweb01, carfs01 | Q6: 4 | R6: Solaris 10 | S6: Oracle 11g | T6: Azure West Europe | U6: 44227 | V6: Structured | W6: 230 | X6: Y | Y6: 7 | Z6: Y | AA6: Archive + read-only | AB6: 3 | AC6: Partial | AD6: N | AE6: N | AF6: 55000 | AG6: 46599 | AH6: 42000 | AI6: 39500 | AJ6: =IF(AND(ISNUMBER(AH6),ISNUMBER(AI6),N(AI6)>0),AH6/AI6*12,"") -> 12.759494 | AK6: =IF(B6="","",OR(K6="Not in use",K6="Low use")+AND(N6<>"",N6<>"TBD")+AND(ISNUMBER(U6),U6<=EDATE('Scoring Settings'!$B$4,'Scoring Settings'!$B$8))+AND(ISNUMBER(L6),L6<='Scoring Settings'!$B$7)) -> 3 | AL6: Retire + Archive | AM6: =IF(B6="","",IF(Z6="N","Easy",IF(OR(AND(ISNUMBER(AB6),AB6>'Scoring Settings'!$B$11),AND(ISNUMBER(W6),W6>'Scoring Settings'!$B$12),AND(ISNUMBER(M6),M6<='Scoring Settings'!$B$13)),"High","Medium"))) -> Medium | AN6: Wave 1 | AO6: 44561 | AP6: Approved | AQ6: Read-only access needed for audit
A7: 126849 | B7: Benefits Enrolment Lite | C7: Benefits | D7: HR | E7: Internal | I7: 19 | J7: 44182 | K7: =IF(B7="","",IF(AND(I7="",J7=""),"Unknown",IF(OR(AND(ISNUMBER(I7),I7=0),AND(ISNUMBER(J7),J7<=EDATE('Scoring Settings'!$B$4,-'Scoring Settings'!$B$5))),"Not in use",IF(AND(ISNUMBER(I7),I7<'Scoring Settings'!$B$6),"Low use","Active")))) -> Low use | L7: 4 | M7: 1 | N7: Workday Recruiting | O7: On-prem DC | P7: fs-bel02 (file share) | Q7: 1 | R7: TBD | S7: MS Access 2010 | T7: TBD | U7: 45209 | V7: Both | W7: 540 | X7: Y | Y7: 7 | Z7: N | AA7: None | AB7: 18 | AC7: Partial | AD7: Partial | AE7: N | AF7: 49500 | AG7: 48426 | AH7: 82500 | AI7: 39500 | AJ7: =IF(AND(ISNUMBER(AH7),ISNUMBER(AI7),N(AI7)>0),AH7/AI7*12,"") -> 25.063291 | AK7: =IF(B7="","",OR(K7="Not in use",K7="Low use")+AND(N7<>"",N7<>"TBD")+AND(ISNUMBER(U7),U7<=EDATE('Scoring Settings'!$B$4,'Scoring Settings'!$B$8))+AND(ISNUMBER(L7),L7<='Scoring Settings'!$B$7)) -> 2 | AL7: Migrate | AM7: =IF(B7="","",IF(Z7="N","Easy",IF(OR(AND(ISNUMBER(AB7),AB7>'Scoring Settings'!$B$11),AND(ISNUMBER(W7),W7>'Scoring Settings'!$B$12),AND(ISNUMBER(M7),M7<='Scoring Settings'!$B$13)),"High","Medium"))) -> Easy | AN7: Wave 1 | AO7: 44500 | AP7: In progress | AQ7: Cut-over planned for Oct-21; parallel run scheduled Blocker: Archive platform capacity not confirmed Q: Can the enterprise archive take this volume this year?
A8: 87175 | B8: Warehouse Mgmt System (Nordics) | C8: Warehouse Mgmt | D8: Supply Chain | E8: Internal | I8: 122 | J8: 44270 | K8: =IF(B8="","",IF(AND(I8="",J8=""),"Unknown",IF(OR(AND(ISNUMBER(I8),I8=0),AND(ISNUMBER(J8),J8<=EDATE('Scoring Settings'!$B$4,-'Scoring Settings'!$B$5))),"Not in use",IF(AND(ISNUMBER(I8),I8<'Scoring Settings'!$B$6),"Low use","Active")))) -> Active | L8: 2 | M8: 4 | N8: Ariba | O8: IaaS | P8: wmsapp01, wmsdb01, wmsweb01, wmsfs01 | Q8: 4 | R8: Ubuntu 16.04 | S8: MySQL 5.7 | T8: AWS us-east-1 | U8: 44316 | V8: Both | W8: 22 | X8: Y | Y8: 10 | Z8: N | AA8: None | AB8: 3 | AC8: Y | AD8: N | AE8: Y | AF8: 38500 | AG8: 47542 | AH8: 40500 | AI8: 33500 | AJ8: =IF(AND(ISNUMBER(AH8),ISNUMBER(AI8),N(AI8)>0),AH8/AI8*12,"") -> 14.507463 | AK8: =IF(B8="","",OR(K8="Not in use",K8="Low use")+AND(N8<>"",N8<>"TBD")+AND(ISNUMBER(U8),U8<=EDATE('Scoring Settings'!$B$4,'Scoring Settings'!$B$8))+AND(ISNUMBER(L8),L8<='Scoring Settings'!$B$7)) -> 3 | AL8: Retire | AM8: =IF(B8="","",IF(Z8="N","Easy",IF(OR(AND(ISNUMBER(AB8),AB8>'Scoring Settings'!$B$11),AND(ISNUMBER(W8),W8>'Scoring Settings'!$B$12),AND(ISNUMBER(M8),M8<='Scoring Settings'!$B$13)),"High","Medium"))) -> Easy | AN8: Wave 1 | AO8: 44347 | AP8: On hold | AQ8: On hold - audit request needs system access until Q3
A9: 57496 | B9: Shared Licence Manager v3 | C9: Licence Mgmt | D9: IT | E9: Internal | I9: 449 | J9: 44309 | K9: =IF(B9="","",IF(AND(I9="",J9=""),"Unknown",IF(OR(AND(ISNUMBER(I9),I9=0),AND(ISNUMBER(J9),J9<=EDATE('Scoring Settings'!$B$4,-'Scoring Settings'!$B$5))),"Not in use",IF(AND(ISNUMBER(I9),I9<'Scoring Settings'!$B$6),"Low use","Active")))) -> Active | L9: 3 | M9: 4 | N9: Microsoft 365 | O9: On-prem DC | P9: slmapp01, slmdb01 | Q9: 2 | R9: SUSE Linux 11 | S9: Oracle 11g | T9: TBD | U9: 43555 | V9: Both | W9: 21 | X9: N | Y9: 2 | Z9: Y | AA9: Read-only access | AB9: 2 | AC9: N | AD9: Partial | AE9: Y | AF9: 24500 | AG9: 49460 | AH9: 25000 | AI9: 18500 | AJ9: =IF(AND(ISNUMBER(AH9),ISNUMBER(AI9),N(AI9)>0),AH9/AI9*12,"") -> 16.216216 | AK9: =IF(B9="","",OR(K9="Not in use",K9="Low use")+AND(N9<>"",N9<>"TBD")+AND(ISNUMBER(U9),U9<=EDATE('Scoring Settings'!$B$4,'Scoring Settings'!$B$8))+AND(ISNUMBER(L9),L9<='Scoring Settings'!$B$7)) -> 2 | AL9: Migrate | AM9: =IF(B9="","",IF(Z9="N","Easy",IF(OR(AND(ISNUMBER(AB9),AB9>'Scoring Settings'!$B$11),AND(ISNUMBER(W9),W9>'Scoring Settings'!$B$12),AND(ISNUMBER(M9),M9<='Scoring Settings'!$B$13)),"High","Medium"))) -> Medium | AN9: Wave 1 | AO9: 44377 | AP9: In progress | AQ9: Migration to Microsoft 365 70% complete; cut-over by end of May
A10: 151951 | B10: Intranet (SharePoint) (US) | C10: Collaboration | D10: IT | E10: Internal | I10: 0 | J10: 44305 | K10: =IF(B10="","",IF(AND(I10="",J10=""),"Unknown",IF(OR(AND(ISNUMBER(I10),I10=0),AND(ISNUMBER(J10),J10<=EDATE('Scoring Settings'!$B$4,-'Scoring Settings'!$B$5))),"Not in use",IF(AND(ISNUMBER(I10),I10<'Scoring Settings'!$B$6),"Low use","Active")))) -> Not in use | L10: 3 | M10: 4 | N10: Microsoft 365 | O10: SaaS | P10: N/A (SaaS) | Q10: 0 | R10: N/A | S10: N/A | T10: Vendor cloud (EU) | U10: 45777 | V10: Unstructured | W10: 220 | X10: N | Y10: 3 | Z10: Y | AA10: Legal hold | AB10: 0 | AC10: Y | AD10: Partial | AE10: Y | AF10: 37000 | AG10: 48548 | AH10: 59000 | AI10: 14500 | AJ10: =IF(AND(ISNUMBER(AH10),ISNUMBER(AI10),N(AI10)>0),AH10/AI10*12,"") -> 48.827586 | AK10: =IF(B10="","",OR(K10="Not in use",K10="Low use")+AND(N10<>"",N10<>"TBD")+AND(ISNUMBER(U10),U10<=EDATE('Scoring Settings'!$B$4,'Scoring Settings'!$B$8))+AND(ISNUMBER(L10),L10<='Scoring Settings'!$B$7)) -> 2 | AL10: Retire + Archive | AM10: =IF(B10="","",IF(Z10="N","Easy",IF(OR(AND(ISNUMBER(AB10),AB10>'Scoring Settings'!$B$11),AND(ISNUMBER(W10),W10>'Scoring Settings'!$B$12),AND(ISNUMBER(M10),M10<='Scoring Settings'!$B$13)),"High","Medium"))) -> Medium | AN10: Wave 1 | AO10: 44316 | AP10: Completed | AQ10: Data archived and validated; switched off Apr-21
A11: 105155 | B11: Shared Inventory Control (APAC) | C11: Inventory | D11: Supply Chain | E11: Partner | I11: 0 | J11: 44271 | K11: =IF(B11="","",IF(AND(I11="",J11=""),"Unknown",IF(OR(AND(ISNUMBER(I11),I11=0),AND(ISNUMBER(J11),J11<=EDATE('Scoring Settings'!$B$4,-'Scoring Settings'!$B$5))),"Not in use",IF(AND(ISNUMBER(I11),I11<'Scoring Settings'!$B$6),"Low use","Active")))) -> Not in use | L11: 1 | M11: 4 | O11: PaaS | P11: Azure App Service (PaaS) | Q11: 0 | R11: N/A (PaaS) | S11: Azure SQL | T11: Azure West Europe | V11: Structured | W11: 100 | X11: N | Y11: 1 | Z11: N | AA11: None | AB11: 2 | AC11: N | AD11: Y | AE11: N | AF11: 170000 | AG11: 46234 | AH11: 20000 | AI11: 97000 | AJ11: =IF(AND(ISNUMBER(AH11),ISNUMBER(AI11),N(AI11)>0),AH11/AI11*12,"") -> 2.4742268 | AK11: =IF(B11="","",OR(K11="Not in use",K11="Low use")+AND(N11<>"",N11<>"TBD")+AND(ISNUMBER(U11),U11<=EDATE('Scoring Settings'!$B$4,'Scoring Settings'!$B$8))+AND(ISNUMBER(L11),L11<='Scoring Settings'!$B$7)) -> 2 | AL11: Retire | AM11: =IF(B11="","",IF(Z11="N","Easy",IF(OR(AND(ISNUMBER(AB11),AB11>'Scoring Settings'!$B$11),AND(ISNUMBER(W11),W11>'Scoring Settings'!$B$12),AND(ISNUMBER(M11),M11<='Scoring Settings'!$B$13)),"High","Medium"))) -> Easy | AN11: Wave 1 | AO11: 44286 | AP11: Completed | AQ11: Switched off Mar-21; licence terminated
A12: 32005 | B12: Global Shipment Tracker | C12: Logistics | D12: Supply Chain | E12: Internal | I12: 0 | J12: 44245 | K12: =IF(B12="","",IF(AND(I12="",J12=""),"Unknown",IF(OR(AND(ISNUMBER(I12),I12=0),AND(ISNUMBER(J12),J12<=EDATE('Scoring Settings'!$B$4,-'Scoring Settings'!$B$5))),"Not in use",IF(AND(ISNUMBER(I12),I12<'Scoring Settings'!$B$6),"Low use","Active")))) -> Not in use | L12: 3 | M12: 3 | N12: Oracle SCM Cloud | O12: SaaS | P12: N/A (SaaS) | Q12: 0 | R12: N/A | S12: N/A | T12: Vendor cloud (EU) | V12: Structured | W12: 170 | X12: N | Y12: 2 | Z12: N | AA12: None | AB12: 8 | AC12: Partial | AD12: Partial | AE12: N | AF12: 234500 | AG12: 46203 | AH12: 54000 | AI12: 246500 | AJ12: =IF(AND(ISNUMBER(AH12),ISNUMBER(AI12),N(AI12)>0),AH12/AI12*12,"") -> 2.6288032 | AK12: =IF(B12="","",OR(K12="Not in use",K12="Low use")+AND(N12<>"",N12<>"TBD")+AND(ISNUMBER(U12),U12<=EDATE('Scoring Settings'!$B$4,'Scoring Settings'!$B$8))+AND(ISNUMBER(L12),L12<='Scoring Settings'!$B$7)) -> 2 | AL12: Migrate | AM12: =IF(B12="","",IF(Z12="N","Easy",IF(OR(AND(ISNUMBER(AB12),AB12>'Scoring Settings'!$B$11),AND(ISNUMBER(W12),W12>'Scoring Settings'!$B$12),AND(ISNUMBER(M12),M12<='Scoring Settings'!$B$13)),"High","Medium"))) -> Easy | AN12: Wave 1 | AO12: 44255 | AP12: Completed | AQ12: Migrated to Oracle SCM Cloud; legacy switched off Feb-21
A13: 187888 | B13: Customer Contact Manager (DE) | C13: CRM | D13: Sales | E13: Partner | I13: 0 | J13: 44310 | K13: =IF(B13="","",IF(AND(I13="",J13=""),"Unknown",IF(OR(AND(ISNUMBER(I13),I13=0),AND(ISNUMBER(J13),J13<=EDATE('Scoring Settings'!$B$4,-'Scoring Settings'!$B$5))),"Not in use",IF(AND(ISNUMBER(I13),I13<'Scoring Settings'!$B$6),"Low use","Active")))) -> Not in use | L13: 3 | M13: 3 | N13: Salesforce | O13: On-prem DC | P13: ccmapp01 | Q13: 1 | R13: Solaris 10 | S13: Oracle 11g | T13: EU DC-2 | U13: 44227 | V13: Structured | W13: 230 | X13: Y | Y13: 10 | Z13: N | AA13: None | AB13: 8 | AC13: N | AD13: Partial | AE13: Partial | AF13: 123000 | AG13: 45777 | AH13: 12000 | AI13: 161000 | AJ13: =IF(AND(ISNUMBER(AH13),ISNUMBER(AI13),N(AI13)>0),AH13/AI13*12,"") -> 0.89440994 | AK13: =IF(B13="","",OR(K13="Not in use",K13="Low use")+AND(N13<>"",N13<>"TBD")+AND(ISNUMBER(U13),U13<=EDATE('Scoring Settings'!$B$4,'Scoring Settings'!$B$8))+AND(ISNUMBER(L13),L13<='Scoring Settings'!$B$7)) -> 3 | AL13: Retire | AM13: =IF(B13="","",IF(Z13="N","Easy",IF(OR(AND(ISNUMBER(AB13),AB13>'Scoring Settings'!$B$11),AND(ISNUMBER(W13),W13>'Scoring Settings'!$B$12),AND(ISNUMBER(M13),M13<='Scoring Settings'!$B$13)),"High","Medium"))) -> Easy | AN13: Wave 1 | AO13: 44316 | AP13: Completed | AQ13: Switched off Apr-21; licence terminated
A14: 80130 | B14: Price List Manager | C14: Pricing | D14: Sales | E14: Internal | I14: 0 | J14: 44115 | K14: =IF(B14="","",IF(AND(I14="",J14=""),"Unknown",IF(OR(AND(ISNUMBER(I14),I14=0),AND(ISNUMBER(J14),J14<=EDATE('Scoring Settings'!$B$4,-'Scoring Settings'!$B$5))),"Not in use",IF(AND(ISNUMBER(I14),I14<'Scoring Settings'!$B$6),"Low use","Active")))) -> Not in use | L14: 1 | M14: 3 | N14: TBD | O14: On-prem DC | P14: plmapp01, plmdb01, plmweb01, plmfs01 | Q14: 4 | R14: Windows Server 2016 | S14: SQL Server 2017 | T14: TBD | U14: 46399 | V14: Structured | W14: 990 | X14: Y | Y14: 7 | Z14: Y | AA14: Reporting extract | AB14: 4 | AC14: Partial | AD14: Partial | AE14: N | AF14: 65000 | AG14: 46965 | AH14: 94500 | AI14: 53500 | AJ14: =IF(AND(ISNUMBER(AH14),ISNUMBER(AI14),N(AI14)>0),AH14/AI14*12,"") -> 21.196262 | AK14: =IF(B14="","",OR(K14="Not in use",K14="Low use")+AND(N14<>"",N14<>"TBD")+AND(ISNUMBER(U14),U14<=EDATE('Scoring Settings'!$B$4,'Scoring Settings'!$B$8))+AND(ISNUMBER(L14),L14<='Scoring Settings'!$B$7)) -> 2 | AL14: Retire + Archive | AM14: =IF(B14="","",IF(Z14="N","Easy",IF(OR(AND(ISNUMBER(AB14),AB14>'Scoring Settings'!$B$11),AND(ISNUMBER(W14),W14>'Scoring Settings'!$B$12),AND(ISNUMBER(M14),M14<='Scoring Settings'!$B$13)),"High","Medium"))) -> Medium | AN14: Wave 1 | AO14: 44408 | AP14: In progress | AQ14: Archive format agreed; load scheduled before switch-off
A15: 37239 | B15: Corporate Ticket Desk | C15: Service Desk | D15: IT | E15: Partner | I15: 1202 | J15: 44304 | K15: =IF(B15="","",IF(AND(I15="",J15=""),"Unknown",IF(OR(AND(ISNUMBER(I15),I15=0),AND(ISNUMBER(J15),J15<=EDATE('Scoring Settings'!$B$4,-'Scoring Settings'!$B$5))),"Not in use",IF(AND(ISNUMBER(I15),I15<'Scoring Settings'!$B$6),"Low use","Active")))) -> Active | L15: 1 | M15: 4 | N15: Splunk | O15: On-prem DC | P15: ctdapp01, ctddb01, ctdweb01 | Q15: 3 | R15: SUSE Linux 11 | S15: TBD | T15: EU DC-1 | U15: TBD | V15: Structured | W15: 100 | X15: N | Y15: 1 | Z15: N | AA15: None | AB15: 0 | AC15: N | AD15: Partial | AE15: Partial | AF15: 55000 | AG15: 47330 | AH15: 47500 | AI15: 51000 | AJ15: =IF(AND(ISNUMBER(AH15),ISNUMBER(AI15),N(AI15)>0),AH15/AI15*12,"") -> 11.176471 | AK15: =IF(B15="","",OR(K15="Not in use",K15="Low use")+AND(N15<>"",N15<>"TBD")+AND(ISNUMBER(U15),U15<=EDATE('Scoring Settings'!$B$4,'Scoring Settings'!$B$8))+AND(ISNUMBER(L15),L15<='Scoring Settings'!$B$7)) -> 2 | AL15: Retire | AM15: =IF(B15="","",IF(Z15="N","Easy",IF(OR(AND(ISNUMBER(AB15),AB15>'Scoring Settings'!$B$11),AND(ISNUMBER(W15),W15>'Scoring Settings'!$B$12),AND(ISNUMBER(M15),M15<='Scoring Settings'!$B$13)),"High","Medium"))) -> Easy | AN15: Wave 1 | AO15: 44439 | AP15: In progress | AQ15: Functionality covered by existing tools
A16: 43206 | B16: Custom Batch Scheduler (APAC) | C16: Batch Scheduling | D16: IT | E16: Internal | I16: 22 | J16: 44204 | K16: =IF(B16="","",IF(AND(I16="",J16=""),"Unknown",IF(OR(AND(ISNUMBER(I16),I16=0),AND(ISNUMBER(J16),J16<=EDATE('Scoring Settings'!$B$4,-'Scoring Settings'!$B$5))),"Not in use",IF(AND(ISNUMBER(I16),I16<'Scoring Settings'!$B$6),"Low use","Active")))) -> Low use | L16: 4 | M16: 2 | N16: ServiceNow | O16: On-prem DC | P16: cbs-app01–05, cbs-db01 | Q16: 6 | R16: AIX 7.1 | S16: DB2 10.5 | T16: Plant DC | U16: 45046 | V16: Structured | W16: 67 | X16: Y | Y16: 7 | Z16: N | AA16: None | AB16: 26 | AC16: N | AD16: Partial | AE16: Partial | AF16: 95000 | AG16: 47026 | AH16: 87500 | AI16: 71500 | AJ16: =IF(AND(ISNUMBER(AH16),ISNUMBER(AI16),N(AI16)>0),AH16/AI16*12,"") -> 14.685315 | AK16: =IF(B16="","",OR(K16="Not in use",K16="Low use")+AND(N16<>"",N16<>"TBD")+AND(ISNUMBER(U16),U16<=EDATE('Scoring Settings'!$B$4,'Scoring Settings'!$B$8))+AND(ISNUMBER(L16),L16<='Scoring Settings'!$B$7)) -> 2 | AL16: Migrate | AM16: =IF(B16="","",IF(Z16="N","Easy",IF(OR(AND(ISNUMBER(AB16),AB16>'Scoring Settings'!$B$11),AND(ISNUMBER(W16),W16>'Scoring Settings'!$B$12),AND(ISNUMBER(M16),M16<='Scoring Settings'!$B$13)),"High","Medium"))) -> Easy | AN16: Wave 1 | AO16: 44408 | AP16: In progress | AQ16: Cut-over planned for Jul-21; parallel run scheduled
A17: 93717 | B17: Regional Facilities Request Portal (Nordics) | C17: Facilities | D17: Operations | E17: Internal | I17: 5 | J17: 43952 | K17: =IF(B17="","",IF(AND(I17="",J17=""),"Unknown",IF(OR(AND(ISNUMBER(I17),I17=0),AND(ISNUMBER(J17),J17<=EDATE('Scoring Settings'!$B$4,-'Scoring Settings'!$B$5))),"Not in use",IF(AND(ISNUMBER(I17),I17<'Scoring Settings'!$B$6),"Low use","Active")))) -> Not in use | L17: 2 | M17: 3 | N17: IBM Maximo | O17: On-prem DC | P17: rfrapp01, rfrdb01, rfrweb01, rfrfs01 | Q17: 4 | R17: RHEL 6 | S17: Oracle 11g | T17: Plant DC | U17: 44165 | V17: Both | W17: 260 | X17: N | Y17: 3 | Z17: Y | AA17: Archive + read-only | AB17: 4 | AC17: Partial | AD17: Partial | AE17: N | AF17: 50000 | AG17: 45747 | AH17: 25000 | AI17: 28500 | AJ17: =IF(AND(ISNUMBER(AH17),ISNUMBER(AI17),N(AI17)>0),AH17/AI17*12,"") -> 10.526316 | AK17: =IF(B17="","",OR(K17="Not in use",K17="Low use")+AND(N17<>"",N17<>"TBD")+AND(ISNUMBER(U17),U17<=EDATE('Scoring Settings'!$B$4,'Scoring Settings'!$B$8))+AND(ISNUMBER(L17),L17<='Scoring Settings'!$B$7)) -> 4 | AL17: Retire + Archive | AM17: =IF(B17="","",IF(Z17="N","Easy",IF(OR(AND(ISNUMBER(AB17),AB17>'Scoring Settings'!$B$11),AND(ISNUMBER(W17),W17>'Scoring Settings'!$B$12),AND(ISNUMBER(M17),M17<='Scoring Settings'!$B$13)),"High","Medium"))) -> Medium | AN17: Wave 1 | AO17: 44530 | AP17: In progress | AQ17: Read-only access needed for audit
A18: 45114 | B18: Regional Timesheet Portal 2012 | C18: Time & Attendance | D18: HR | E18: Internal | I18: 11 | J18: 44298 | K18: =IF(B18="","",IF(AND(I18="",J18=""),"Unknown",IF(OR(AND(ISNUMBER(I18),I18=0),AND(ISNUMBER(J18),J18<=EDATE('Scoring Settings'!$B$4,-'Scoring Settings'!$B$5))),"Not in use",IF(AND(ISNUMBER(I18),I18<'Scoring Settings'!$B$6),"Low use","Active")))) -> Low use | L18: 2 | M18: 3 | O18: PaaS | P18: Azure App Service (PaaS) | Q18: 0 | R18: N/A (PaaS) | S18: Azure SQL | T18: Azure West Europe | U18: 44742 | V18: Both | W18: 140 | X18: Y | Y18: 10 | Z18: N | AA18: None | AB18: 3 | AC18: Partial | AD18: N | AE18: Y | AF18: 8500 | AG18: 46783 | AH18: 9000 | AI18: 77500 | AJ18: =IF(AND(ISNUMBER(AH18),ISNUMBER(AI18),N(AI18)>0),AH18/AI18*12,"") -> 1.3935484 | AK18: =IF(B18="","",OR(K18="Not in use",K18="Low use")+AND(N18<>"",N18<>"TBD")+AND(ISNUMBER(U18),U18<=EDATE('Scoring Settings'!$B$4,'Scoring Settings'!$B$8))+AND(ISNUMBER(L18),L18<='Scoring Settings'!$B$7)) -> 2 | AL18: Retire | AM18: =IF(B18="","",IF(Z18="N","Easy",IF(OR(AND(ISNUMBER(AB18),AB18>'Scoring Settings'!$B$11),AND(ISNUMBER(W18),W18>'Scoring Settings'!$B$12),AND(ISNUMBER(M18),M18<='Scoring Settings'!$B$13)),"High","Medium"))) -> Easy | AN18: Wave 1 | AO18: 44347 | AP18: On hold | AQ18: On hold - audit request needs system access until Q3
A19: 99137 | B19: Global Newsletter Mailer (DE) | C19: Email | D19: Marketing | E19: Internal | I19: 0 | J19: 44279 | K19: =IF(B19="","",IF(AND(I19="",J19=""),"Unknown",IF(OR(AND(ISNUMBER(I19),I19=0),AND(ISNUMBER(J19),J19<=EDATE('Scoring Settings'!$B$4,-'Scoring Settings'!$B$5))),"Not in use",IF(AND(ISNUMBER(I19),I19<'Scoring Settings'!$B$6),"Low use","Active")))) -> Not in use | L19: 1 | M19: 3 | N19: TBD | O19: On-prem DC | P19: gnmapp01, gnmdb01, gnmweb01, gnmfs01 | Q19: 4 | R19: Windows Server 2012 R2 | S19: SQL Server 2014 | T19: US DC-1 | U19: 45482 | V19: Both | W19: 55 | X19: Y | Y19: 10 | Z19: N | AA19: None | AB19: 2 | AC19: Partial | AD19: N | AE19: Partial | AF19: 55000 | AG19: 47938 | AH19: 53000 | AI19: 95500 | AJ19: =IF(AND(ISNUMBER(AH19),ISNUMBER(AI19),N(AI19)>0),AH19/AI19*12,"") -> 6.6596859 | AK19: =IF(B19="","",OR(K19="Not in use",K19="Low use")+AND(N19<>"",N19<>"TBD")+AND(ISNUMBER(U19),U19<=EDATE('Scoring Settings'!$B$4,'Scoring Settings'!$B$8))+AND(ISNUMBER(L19),L19<='Scoring Settings'!$B$7)) -> 2 | AL19: Retire | AM19: =IF(B19="","",IF(Z19="N","Easy",IF(OR(AND(ISNUMBER(AB19),AB19>'Scoring Settings'!$B$11),AND(ISNUMBER(W19),W19>'Scoring Settings'!$B$12),AND(ISNUMBER(M19),M19<='Scoring Settings'!$B$13)),"High","Medium"))) -> Easy | AN19: Wave 1 | AO19: 44286 | AP19: Completed | AQ19: Switched off Mar-21; licence terminated
A20: 85637 | B20: Core ERP (SAP ECC) | C20: Enterprise Resource Planning | D20: Finance | E20: Partner | I20: 2400 | J20: 44316 | K20: =IF(B20="","",IF(AND(I20="",J20=""),"Unknown",IF(OR(AND(ISNUMBER(I20),I20=0),AND(ISNUMBER(J20),J20<=EDATE('Scoring Settings'!$B$4,-'Scoring Settings'!$B$5))),"Not in use",IF(AND(ISNUMBER(I20),I20<'Scoring Settings'!$B$6),"Low use","Active")))) -> Active | L20: 5 | M20: 1 | N20: SAP S/4HANA | O20: On-prem DC | P20: ecc-app01–05, ecc-db01 | Q20: 6 | R20: SUSE Linux 11 | S20: Oracle 11g | T20: EU DC-1 | U20: 46022 | V20: Structured | W20: 4500 | X20: Y | Y20: 10 | Z20: N | AA20: None | AB20: 85 | AC20: Y | AD20: Y | AE20: Partial | AF20: 650000 | AG20: 46387 | AH20: 32200000 | AI20: 520000 | AJ20: =IF(AND(ISNUMBER(AH20),ISNUMBER(AI20),N(AI20)>0),AH20/AI20*12,"") -> 743.07692 | AK20: =IF(B20="","",OR(K20="Not in use",K20="Low use")+AND(N20<>"",N20<>"TBD")+AND(ISNUMBER(U20),U20<=EDATE('Scoring Settings'!$B$4,'Scoring Settings'!$B$8))+AND(ISNUMBER(L20),L20<='Scoring Settings'!$B$7)) -> 1 | AL20: Retire | AM20: =IF(B20="","",IF(Z20="N","Easy",IF(OR(AND(ISNUMBER(AB20),AB20>'Scoring Settings'!$B$11),AND(ISNUMBER(W20),W20>'Scoring Settings'!$B$12),AND(ISNUMBER(M20),M20<='Scoring Settings'!$B$13)),"High","Medium"))) -> Easy | AN20: Wave 1 | AO20: 44500 | AP20: In progress | AQ20: Retire after S/4HANA cut-over; finance history retained in S/4HANA - no separate archive
A21: 138296 | B21: Old CMDB Lite | C21: Config Mgmt | D21: IT | E21: External | I21: 8 | J21: 44168 | K21: =IF(B21="","",IF(AND(I21="",J21=""),"Unknown",IF(OR(AND(ISNUMBER(I21),I21=0),AND(ISNUMBER(J21),J21<=EDATE('Scoring Settings'!$B$4,-'Scoring Settings'!$B$5))),"Not in use",IF(AND(ISNUMBER(I21),I21<'Scoring Settings'!$B$6),"Low use","Active")))) -> Low use | L21: 5 | M21: 1 | N21: ServiceNow (planned) | O21: On-prem DC | P21: ocl-app01–04, ocl-db01 | Q21: 5 | R21: Windows Server 2008 R2 | S21: SQL Server 2008 R2 | T21: TBD | U21: 43844 | V21: Structured | W21: 19 | X21: N | Y21: 7 | Z21: Y | AA21: Archive + read-only | AB21: 35 | AC21: Partial | AD21: N | AE21: Partial | AF21: 195000 | AG21: 47999 | AH21: 245000 | AI21: 267500 | AJ21: =IF(AND(ISNUMBER(AH21),ISNUMBER(AI21),N(AI21)>0),AH21/AI21*12,"") -> 10.990654 | AK21: =IF(B21="","",OR(K21="Not in use",K21="Low use")+AND(N21<>"",N21<>"TBD")+AND(ISNUMBER(U21),U21<=EDATE('Scoring Settings'!$B$4,'Scoring Settings'!$B$8))+AND(ISNUMBER(L21),L21<='Scoring Settings'!$B$7)) -> 3 | AL21: Migrate | AM21: =IF(B21="","",IF(Z21="N","Easy",IF(OR(AND(ISNUMBER(AB21),AB21>'Scoring Settings'!$B$11),AND(ISNUMBER(W21),W21>'Scoring Settings'!$B$12),AND(ISNUMBER(M21),M21<='Scoring Settings'!$B$13)),"High","Medium"))) -> High | AN21: Wave 1 | AO21: 44469 | AP21: In progress | AQ21: 3 feeds to re-point to ServiceNow
A22: 166902 | B22: Supplier Portal | C22: Supplier Mgmt | D22: Supply Chain | E22: Internal | I22: 0 | J22: 43732 | K22: =IF(B22="","",IF(AND(I22="",J22=""),"Unknown",IF(OR(AND(ISNUMBER(I22),I22=0),AND(ISNUMBER(J22),J22<=EDATE('Scoring Settings'!$B$4,-'Scoring Settings'!$B$5))),"Not in use",IF(AND(ISNUMBER(I22),I22<'Scoring Settings'!$B$6),"Low use","Active")))) -> Not in use | L22: 2 | M22: 3 | O22: On-prem DC | P22: spxapp01, spxdb01, spxweb01, spxfs01 | Q22: 4 | R22: Windows Server 2008 R2 | S22: SQL Server 2008 R2 | T22: EU DC-1 | U22: 43844 | V22: Both | W22: 110 | X22: N | Y22: 7 | Z22: N | AA22: None | AB22: 2 | AC22: N | AD22: Partial | AE22: N | AF22: 80000 | AG22: 45777 | AH22: 39000 | AI22: 77000 | AJ22: =IF(AND(ISNUMBER(AH22),ISNUMBER(AI22),N(AI22)>0),AH22/AI22*12,"") -> 6.0779221 | AK22: =IF(B22="","",OR(K22="Not in use",K22="Low use")+AND(N22<>"",N22<>"TBD")+AND(ISNUMBER(U22),U22<=EDATE('Scoring Settings'!$B$4,'Scoring Settings'!$B$8))+AND(ISNUMBER(L22),L22<='Scoring Settings'!$B$7)) -> 3 | AL22: Retire | AM22: =IF(B22="","",IF(Z22="N","Easy",IF(OR(AND(ISNUMBER(AB22),AB22>'Scoring Settings'!$B$11),AND(ISNUMBER(W22),W22>'Scoring Settings'!$B$12),AND(ISNUMBER(M22),M22<='Scoring Settings'!$B$13)),"High","Medium"))) -> Easy | AN22: Wave 1 | AO22: 44469 | AP22: In progress | AQ22: Functionality covered by existing tools
A23: 18048 | B23: Corporate Inventory Control (UK) | C23: Inventory | D23: Supply Chain | E23: Internal | I23: 22 | J23: 44230 | K23: =IF(B23="","",IF(AND(I23="",J23=""),"Unknown",IF(OR(AND(ISNUMBER(I23),I23=0),AND(ISNUMBER(J23),J23<=EDATE('Scoring Settings'!$B$4,-'Scoring Settings'!$B$5))),"Not in use",IF(AND(ISNUMBER(I23),I23<'Scoring Settings'!$B$6),"Low use","Active")))) -> Low use | L23: 3 | M23: 3 | N23: TBD | O23: SaaS | P23: N/A (SaaS) | Q23: 0 | R23: N/A | S23: N/A | T23: Vendor cloud (EU) | V23: Unstructured | W23: 120 | X23: N | Y23: 3 | Z23: Y | AA23: Data archive | AB23: 8 | AC23: Partial | AD23: Partial | AE23: Partial | AF23: 90000 | AG23: 48487 | AH23: 52500 | AI23: 32500 | AJ23: =IF(AND(ISNUMBER(AH23),ISNUMBER(AI23),N(AI23)>0),AH23/AI23*12,"") -> 19.384615 | AK23: =IF(B23="","",OR(K23="Not in use",K23="Low use")+AND(N23<>"",N23<>"TBD")+AND(ISNUMBER(U23),U23<=EDATE('Scoring Settings'!$B$4,'Scoring Settings'!$B$8))+AND(ISNUMBER(L23),L23<='Scoring Settings'!$B$7)) -> 1 | AL23: Retire + Archive | AM23: =IF(B23="","",IF(Z23="N","Easy",IF(OR(AND(ISNUMBER(AB23),AB23>'Scoring Settings'!$B$11),AND(ISNUMBER(W23),W23>'Scoring Settings'!$B$12),AND(ISNUMBER(M23),M23<='Scoring Settings'!$B$13)),"High","Medium"))) -> High | AN23: Wave 1 | AO23: 44408 | AP23: In progress | AQ23: Retention 3 yrs - archive slot booked
A24: 161444 | B24: Corporate Access Request Tool (UK) | C24: Identity | D24: IT | E24: Internal | I24: 44 | J24: 44274 | K24: =IF(B24="","",IF(AND(I24="",J24=""),"Unknown",IF(OR(AND(ISNUMBER(I24),I24=0),AND(ISNUMBER(J24),J24<=EDATE('Scoring Settings'!$B$4,-'Scoring Settings'!$B$5))),"Not in use",IF(AND(ISNUMBER(I24),I24<'Scoring Settings'!$B$6),"Low use","Active")))) -> Active | L24: 3 | M24: 2 | N24: Azure Monitor | O24: On-prem DC | P24: car-app01–05, car-db01 | Q24: 6 | R24: SUSE Linux 11 | S24: Oracle 11g | T24: Plant DC | U24: 43555 | V24: Structured | W24: 30 | X24: N | Y24: 7 | Z24: Y | AA24: Read-only access | AB24: 12 | AC24: Partial | AD24: Partial | AE24: N | AF24: 125000 | AG24: 46265 | AH24: 256000 | AI24: 84000 | AJ24: =IF(AND(ISNUMBER(AH24),ISNUMBER(AI24),N(AI24)>0),AH24/AI24*12,"") -> 36.571429 | AK24: =IF(B24="","",OR(K24="Not in use",K24="Low use")+AND(N24<>"",N24<>"TBD")+AND(ISNUMBER(U24),U24<=EDATE('Scoring Settings'!$B$4,'Scoring Settings'!$B$8))+AND(ISNUMBER(L24),L24<='Scoring Settings'!$B$7)) -> 2 | AL24: Retire + Archive | AM24: =IF(B24="","",IF(Z24="N","Easy",IF(OR(AND(ISNUMBER(AB24),AB24>'Scoring Settings'!$B$11),AND(ISNUMBER(W24),W24>'Scoring Settings'!$B$12),AND(ISNUMBER(M24),M24<='Scoring Settings'!$B$13)),"High","Medium"))) -> High | AN24: Wave 1 | AO24: 44408 | AP24: In progress | AQ24: Read-only access needed for audit
A25: 186996 | B25: Departmental Quality Incident Log v2 | C25: Quality | D25: Operations | E25: Internal | I25: 11 | J25: 44170 | K25: =IF(B25="","",IF(AND(I25="",J25=""),"Unknown",IF(OR(AND(ISNUMBER(I25),I25=0),AND(ISNUMBER(J25),J25<=EDATE('Scoring Settings'!$B$4,-'Scoring Settings'!$B$5))),"Not in use",IF(AND(ISNUMBER(I25),I25<'Scoring Settings'!$B$6),"Low use","Active")))) -> Low use | L25: 2 | M25: 4 | N25: Fiix | O25: On-prem DC | P25: dqiapp01, dqidb01 | Q25: 2 | R25: Windows Server 2008 | S25: SQL Server 2008 | T25: TBD | U25: 43655 | V25: Structured | W25: 160 | X25: N | Y25: 2 | Z25: Y | AA25: Archive + read-only | AB25: 3 | AC25: Partial | AD25: Partial | AE25: Y | AF25: 28500 | AG25: 47542 | AH25: 16000 | AI25: 22000 | AJ25: =IF(AND(ISNUMBER(AH25),ISNUMBER(AI25),N(AI25)>0),AH25/AI25*12,"") -> 8.7272727 | AK25: =IF(B25="","",OR(K25="Not in use",K25="Low use")+AND(N25<>"",N25<>"TBD")+AND(ISNUMBER(U25),U25<=EDATE('Scoring Settings'!$B$4,'Scoring Settings'!$B$8))+AND(ISNUMBER(L25),L25<='Scoring Settings'!$B$7)) -> 4 | AL25: Migrate | AM25: =IF(B25="","",IF(Z25="N","Easy",IF(OR(AND(ISNUMBER(AB25),AB25>'Scoring Settings'!$B$11),AND(ISNUMBER(W25),W25>'Scoring Settings'!$B$12),AND(ISNUMBER(M25),M25<='Scoring Settings'!$B$13)),"High","Medium"))) -> Medium | AN25: Wave 1 | AO25: 44500 | AP25: In progress | AQ25: Funding approved; migration to Fiix scheduled
A26: 18964 | B26: Custom Billing Engine | C26: Billing | D26: Finance | E26: External | I26: 0 | J26: 44251 | K26: =IF(B26="","",IF(AND(I26="",J26=""),"Unknown",IF(OR(AND(ISNUMBER(I26),I26=0),AND(ISNUMBER(J26),J26<=EDATE('Scoring Settings'!$B$4,-'Scoring Settings'!$B$5))),"Not in use",IF(AND(ISNUMBER(I26),I26<'Scoring Settings'!$B$6),"Low use","Active")))) -> Not in use | L26: 2 | M26: 4 | O26: IaaS | P26: cbeapp01, cbedb01, cbeweb01 | Q26: 3 | R26: Ubuntu 16.04 | S26: MySQL 5.7 | T26: Azure West Europe | U26: 44316 | V26: Structured | W26: 710 | X26: Y | Y26: 7 | Z26: N | AA26: None | AB26: 2 | AC26: Y | AD26: N | AE26: Partial | AF26: 32000 | AG26: 49582 | AH26: 30000 | AI26: 91000 | AJ26: =IF(AND(ISNUMBER(AH26),ISNUMBER(AI26),N(AI26)>0),AH26/AI26*12,"") -> 3.956044 | AK26: =IF(B26="","",OR(K26="Not in use",K26="Low use")+AND(N26<>"",N26<>"TBD")+AND(ISNUMBER(U26),U26<=EDATE('Scoring Settings'!$B$4,'Scoring Settings'!$B$8))+AND(ISNUMBER(L26),L26<='Scoring Settings'!$B$7)) -> 3 | AL26: Retire | AM26: =IF(B26="","",IF(Z26="N","Easy",IF(OR(AND(ISNUMBER(AB26),AB26>'Scoring Settings'!$B$11),AND(ISNUMBER(W26),W26>'Scoring Settings'!$B$12),AND(ISNUMBER(M26),M26<='Scoring Settings'!$B$13)),"High","Medium"))) -> Easy | AN26: Wave 1 | AO26: 44377 | AP26: In progress | AQ26: User comms sent; switch-off scheduled for end of May
A27: 23920 | B27: Departmental Budget Planner (FR) | C27: Budgeting | D27: Finance | E27: Internal | I27: 0 | J27: 44234 | K27: =IF(B27="","",IF(AND(I27="",J27=""),"Unknown",IF(OR(AND(ISNUMBER(I27),I27=0),AND(ISNUMBER(J27),J27<=EDATE('Scoring Settings'!$B$4,-'Scoring Settings'!$B$5))),"Not in use",IF(AND(ISNUMBER(I27),I27<'Scoring Settings'!$B$6),"Low use","Active")))) -> Not in use | L27: 3 | M27: 4 | O27: On-prem DC | P27: dbpapp01, dbpdb01 | Q27: 2 | R27: Windows Server 2008 | S27: SQL Server 2008 | T27: EU DC-2 | U27: 43655 | V27: Both | W27: 1100 | X27: Y | Y27: 7 | Z27: N | AA27: None | AB27: 2 | AC27: N | AD27: Y | AE27: Y | AF27: 45000 | AG27: 48152 | AH27: 35000 | AI27: 38000 | AJ27: =IF(AND(ISNUMBER(AH27),ISNUMBER(AI27),N(AI27)>0),AH27/AI27*12,"") -> 11.052632 | AK27: =IF(B27="","",OR(K27="Not in use",K27="Low use")+AND(N27<>"",N27<>"TBD")+AND(ISNUMBER(U27),U27<=EDATE('Scoring Settings'!$B$4,'Scoring Settings'!$B$8))+AND(ISNUMBER(L27),L27<='Scoring Settings'!$B$7)) -> 2 | AL27: Retire | AM27: =IF(B27="","",IF(Z27="N","Easy",IF(OR(AND(ISNUMBER(AB27),AB27>'Scoring Settings'!$B$11),AND(ISNUMBER(W27),W27>'Scoring Settings'!$B$12),AND(ISNUMBER(M27),M27<='Scoring Settings'!$B$13)),"High","Medium"))) -> Easy | AN27: Wave 1 | AO27: 44255 | AP27: Completed | AQ27: Switched off Feb-21; licence terminated
A28: 136942 | B28: Legacy Timesheet Portal (FR) | C28: Time & Attendance | D28: HR | E28: Internal | I28: 83 | J28: 44296 | K28: =IF(B28="","",IF(AND(I28="",J28=""),"Unknown",IF(OR(AND(ISNUMBER(I28),I28=0),AND(ISNUMBER(J28),J28<=EDATE('Scoring Settings'!$B$4,-'Scoring Settings'!$B$5))),"Not in use",IF(AND(ISNUMBER(I28),I28<'Scoring Settings'!$B$6),"Low use","Active")))) -> Active | L28: 1 | M28: 4 | N28: SuccessFactors | O28: On-prem DC | P28: ltpapp01, ltpdb01, ltpweb01 | Q28: 3 | R28: RHEL 6 | S28: Oracle 11g | T28: EU DC-1 | U28: 44165 | V28: Structured | W28: 3 | X28: Y | Y28: 7 | Z28: Y | AA28: Data archive | AB28: 2 | AC28: Y | AD28: Y | AE28: Partial | AF28: 33000 | AG28: 45991 | AH28: 35000 | AI28: 25500 | AJ28: =IF(AND(ISNUMBER(AH28),ISNUMBER(AI28),N(AI28)>0),AH28/AI28*12,"") -> 16.470588 | AK28: =IF(B28="","",OR(K28="Not in use",K28="Low use")+AND(N28<>"",N28<>"TBD")+AND(ISNUMBER(U28),U28<=EDATE('Scoring Settings'!$B$4,'Scoring Settings'!$B$8))+AND(ISNUMBER(L28),L28<='Scoring Settings'!$B$7)) -> 3 | AL28: Migrate | AM28: =IF(B28="","",IF(Z28="N","Easy",IF(OR(AND(ISNUMBER(AB28),AB28>'Scoring Settings'!$B$11),AND(ISNUMBER(W28),W28>'Scoring Settings'!$B$12),AND(ISNUMBER(M28),M28<='Scoring Settings'!$B$13)),"High","Medium"))) -> Medium | AN28: Wave 1 | AO28: 44408 | AP28: In progress | AQ28: 6 feeds to re-point to SuccessFactors
A29: 98378 | B29: Travel Booking Tool 2012 | C29: Travel | D29: HR | E29: Internal | I29: 317 | J29: 44308 | K29: =IF(B29="","",IF(AND(I29="",J29=""),"Unknown",IF(OR(AND(ISNUMBER(I29),I29=0),AND(ISNUMBER(J29),J29<=EDATE('Scoring Settings'!$B$4,-'Scoring Settings'!$B$5))),"Not in use",IF(AND(ISNUMBER(I29),I29<'Scoring Settings'!$B$6),"Low use","Active")))) -> Active | L29: 3 | M29: 4 | N29: Workday HCM | O29: On-prem DC | P29: tbtapp01, tbtdb01 | Q29: 2 | R29: Windows Server 2008 R2 | S29: SQL Server 2008 R2 | T29: US DC-1 | U29: 43844 | V29: Structured | W29: 62 | X29: Y | Y29: 7 | Z29: Y | AA29: Read-only access | AB29: 0 | AC29: N | AD29: N | AE29: N | AF29: 47500 | AG29: 46783 | AH29: 40000 | AI29: 33500 | AJ29: =IF(AND(ISNUMBER(AH29),ISNUMBER(AI29),N(AI29)>0),AH29/AI29*12,"") -> 14.328358 | AK29: =IF(B29="","",OR(K29="Not in use",K29="Low use")+AND(N29<>"",N29<>"TBD")+AND(ISNUMBER(U29),U29<=EDATE('Scoring Settings'!$B$4,'Scoring Settings'!$B$8))+AND(ISNUMBER(L29),L29<='Scoring Settings'!$B$7)) -> 2 | AL29: Migrate | AM29: =IF(B29="","",IF(Z29="N","Easy",IF(OR(AND(ISNUMBER(AB29),AB29>'Scoring Settings'!$B$11),AND(ISNUMBER(W29),W29>'Scoring Settings'!$B$12),AND(ISNUMBER(M29),M29<='Scoring Settings'!$B$13)),"High","Medium"))) -> Medium | AN29: Wave 1 | AO29: 44469 | AP29: In progress | AQ29: Cut-over planned for Sep-21; parallel run scheduled
A30: 84815 | B30: Shared Contract Repository (FR) | C30: Contract Mgmt | D30: Finance | E30: Partner | I30: 100 | J30: 44278 | K30: =IF(B30="","",IF(AND(I30="",J30=""),"Unknown",IF(OR(AND(ISNUMBER(I30),I30=0),AND(ISNUMBER(J30),J30<=EDATE('Scoring Settings'!$B$4,-'Scoring Settings'!$B$5))),"Not in use",IF(AND(ISNUMBER(I30),I30<'Scoring Settings'!$B$6),"Low use","Active")))) -> Active | L30: 3 | M30: 3 | O30: SaaS | P30: N/A (SaaS) | Q30: 0 | R30: N/A | S30: N/A | T30: Vendor cloud (EU) | U30: 46203 | V30: Both | W30: 93 | X30: Y | Y30: 7 | Z30: Y | AA30: Read-only access | AB30: 8 | AC30: Y | AD30: Partial | AE30: Partial | AF30: 31500 | AG30: 47118 | AH30: 32500 | AI30: 73000 | AJ30: =IF(AND(ISNUMBER(AH30),ISNUMBER(AI30),N(AI30)>0),AH30/AI30*12,"") -> 5.3424658 | AK30: =IF(B30="","",OR(K30="Not in use",K30="Low use")+AND(N30<>"",N30<>"TBD")+AND(ISNUMBER(U30),U30<=EDATE('Scoring Settings'!$B$4,'Scoring Settings'!$B$8))+AND(ISNUMBER(L30),L30<='Scoring Settings'!$B$7)) -> 0 | AL30: Retire + Archive | AM30: =IF(B30="","",IF(Z30="N","Easy",IF(OR(AND(ISNUMBER(AB30),AB30>'Scoring Settings'!$B$11),AND(ISNUMBER(W30),W30>'Scoring Settings'!$B$12),AND(ISNUMBER(M30),M30<='Scoring Settings'!$B$13)),"High","Medium"))) -> High | AN30: Wave 1 | AO30: 44347 | AP30: Completed | AQ30: Retention 7 yrs - archive slot booked
A31: 164470 | B31: Old Safety Incident Tracker Lite | C31: Health & Safety | D31: Operations | E31: Internal | I31: 0 | J31: 44250 | K31: =IF(B31="","",IF(AND(I31="",J31=""),"Unknown",IF(OR(AND(ISNUMBER(I31),I31=0),AND(ISNUMBER(J31),J31<=EDATE('Scoring Settings'!$B$4,-'Scoring Settings'!$B$5))),"Not in use",IF(AND(ISNUMBER(I31),I31<'Scoring Settings'!$B$6),"Low use","Active")))) -> Not in use | L31: 3 | M31: 3 | O31: On-prem DC | P31: osiapp01, osidb01, osiweb01 | Q31: 3 | R31: Ubuntu 16.04 | S31: MySQL 5.7 | T31: Plant DC | U31: 44316 | V31: Structured | W31: 200 | X31: N | Y31: 3 | Z31: N | AA31: None | AB31: 2 | AC31: Y | AD31: Y | AE31: Partial | AF31: 55000 | AG31: 47726 | AH31: 53500 | AI31: 54000 | AJ31: =IF(AND(ISNUMBER(AH31),ISNUMBER(AI31),N(AI31)>0),AH31/AI31*12,"") -> 11.888889 | AK31: =IF(B31="","",OR(K31="Not in use",K31="Low use")+AND(N31<>"",N31<>"TBD")+AND(ISNUMBER(U31),U31<=EDATE('Scoring Settings'!$B$4,'Scoring Settings'!$B$8))+AND(ISNUMBER(L31),L31<='Scoring Settings'!$B$7)) -> 2 | AL31: Retire | AM31: =IF(B31="","",IF(Z31="N","Easy",IF(OR(AND(ISNUMBER(AB31),AB31>'Scoring Settings'!$B$11),AND(ISNUMBER(W31),W31>'Scoring Settings'!$B$12),AND(ISNUMBER(M31),M31<='Scoring Settings'!$B$13)),"High","Medium"))) -> Easy | AN31: Wave 1 | AO31: 44255 | AP31: Completed | AQ31: Switched off Feb-21; licence terminated
A32: 65070 | B32: Payroll Interface (UK) | C32: Payroll | D32: HR | E32: Internal | I32: 0 | J32: 44241 | K32: =IF(B32="","",IF(AND(I32="",J32=""),"Unknown",IF(OR(AND(ISNUMBER(I32),I32=0),AND(ISNUMBER(J32),J32<=EDATE('Scoring Settings'!$B$4,-'Scoring Settings'!$B$5))),"Not in use",IF(AND(ISNUMBER(I32),I32<'Scoring Settings'!$B$6),"Low use","Active")))) -> Not in use | L32: 1 | M32: 4 | O32: SaaS | P32: N/A (SaaS) | Q32: 0 | R32: N/A | S32: N/A | T32: Vendor cloud (EU) | V32: Structured | W32: 180 | X32: Y | Y32: 5 | Z32: Y | AA32: Archive + read-only | AB32: 1 | AC32: Partial | AD32: Y | AE32: Partial | AF32: 42500 | AG32: 49552 | AH32: 53500 | AI32: 18500 | AJ32: =IF(AND(ISNUMBER(AH32),ISNUMBER(AI32),N(AI32)>0),AH32/AI32*12,"") -> 34.702703 | AK32: =IF(B32="","",OR(K32="Not in use",K32="Low use")+AND(N32<>"",N32<>"TBD")+AND(ISNUMBER(U32),U32<=EDATE('Scoring Settings'!$B$4,'Scoring Settings'!$B$8))+AND(ISNUMBER(L32),L32<='Scoring Settings'!$B$7)) -> 2 | AL32: Retire + Archive | AM32: =IF(B32="","",IF(Z32="N","Easy",IF(OR(AND(ISNUMBER(AB32),AB32>'Scoring Settings'!$B$11),AND(ISNUMBER(W32),W32>'Scoring Settings'!$B$12),AND(ISNUMBER(M32),M32<='Scoring Settings'!$B$13)),"High","Medium"))) -> Medium | AN32: Wave 1 | AO32: 44530 | AP32: In progress | AQ32: Read-only access needed for audit
A33: 97953 | B33: Shared Safety Incident Tracker | C33: Health & Safety | D33: Operations | E33: Internal | I33: 581 | J33: 44277 | K33: =IF(B33="","",IF(AND(I33="",J33=""),"Unknown",IF(OR(AND(ISNUMBER(I33),I33=0),AND(ISNUMBER(J33),J33<=EDATE('Scoring Settings'!$B$4,-'Scoring Settings'!$B$5))),"Not in use",IF(AND(ISNUMBER(I33),I33<'Scoring Settings'!$B$6),"Low use","Active")))) -> Active | L33: 4 | M33: 1 | N33: SAP EAM | O33: PaaS | P33: Azure App Service (PaaS) | Q33: 0 | R33: N/A (PaaS) | S33: Azure SQL | T33: Azure West Europe | U33: 44742 | V33: Structured | W33: 870 | X33: N | Y33: 7 | Z33: N | AA33: None | AB33: 60 | AC33: N | AD33: Partial | AE33: Y | AF33: 80000 | AG33: 48669 | AH33: 122000 | AI33: 49500 | AJ33: =IF(AND(ISNUMBER(AH33),ISNUMBER(AI33),N(AI33)>0),AH33/AI33*12,"") -> 29.575758 | AK33: =IF(B33="","",OR(K33="Not in use",K33="Low use")+AND(N33<>"",N33<>"TBD")+AND(ISNUMBER(U33),U33<=EDATE('Scoring Settings'!$B$4,'Scoring Settings'!$B$8))+AND(ISNUMBER(L33),L33<='Scoring Settings'!$B$7)) -> 1 | AL33: Migrate | AM33: =IF(B33="","",IF(Z33="N","Easy",IF(OR(AND(ISNUMBER(AB33),AB33>'Scoring Settings'!$B$11),AND(ISNUMBER(W33),W33>'Scoring Settings'!$B$12),AND(ISNUMBER(M33),M33<='Scoring Settings'!$B$13)),"High","Medium"))) -> Easy | AN33: Wave 1 | AO33: 44500 | AP33: In progress | AQ33: Funding approved; migration to SAP EAM scheduled
A34: 143504 | B34: Corporate Travel Booking Tool | C34: Travel | D34: HR | E34: Internal | I34: 96 | J34: 44277 | K34: =IF(B34="","",IF(AND(I34="",J34=""),"Unknown",IF(OR(AND(ISNUMBER(I34),I34=0),AND(ISNUMBER(J34),J34<=EDATE('Scoring Settings'!$B$4,-'Scoring Settings'!$B$5))),"Not in use",IF(AND(ISNUMBER(I34),I34<'Scoring Settings'!$B$6),"Low use","Active")))) -> Active | L34: 3 | M34: 3 | N34: Workday HCM (planned) | O34: On-prem DC | P34: fs-ctb02 (file share) | Q34: 1 | R34: Windows Server 2012 R2 | S34: MS Access 2010 | T34: Plant DC | U34: 45209 | V34: Both | W34: 89 | X34: Y | Y34: 10 | Z34: N | AA34: None | AB34: 1 | AC34: N | AD34: Partial | AE34: Y | AF34: 26000 | AG34: 47968 | AH34: 14500 | AI34: 78500 | AJ34: =IF(AND(ISNUMBER(AH34),ISNUMBER(AI34),N(AI34)>0),AH34/AI34*12,"") -> 2.2165605 | AK34: =IF(B34="","",OR(K34="Not in use",K34="Low use")+AND(N34<>"",N34<>"TBD")+AND(ISNUMBER(U34),U34<=EDATE('Scoring Settings'!$B$4,'Scoring Settings'!$B$8))+AND(ISNUMBER(L34),L34<='Scoring Settings'!$B$7)) -> 1 | AL34: Migrate | AM34: =IF(B34="","",IF(Z34="N","Easy",IF(OR(AND(ISNUMBER(AB34),AB34>'Scoring Settings'!$B$11),AND(ISNUMBER(W34),W34>'Scoring Settings'!$B$12),AND(ISNUMBER(M34),M34<='Scoring Settings'!$B$13)),"High","Medium"))) -> Easy | AN34: Wave 1 | AO34: 44500 | AP34: In progress | AQ34: Cut-over planned for Oct-21; parallel run scheduled
A35: 88761 | B35: Monitoring Console 2008 | C35: Monitoring | D35: IT | E35: Internal | I35: 10 | J35: 44310 | K35: =IF(B35="","",IF(AND(I35="",J35=""),"Unknown",IF(OR(AND(ISNUMBER(I35),I35=0),AND(ISNUMBER(J35),J35<=EDATE('Scoring Settings'!$B$4,-'Scoring Settings'!$B$5))),"Not in use",IF(AND(ISNUMBER(I35),I35<'Scoring Settings'!$B$6),"Low use","Active")))) -> Low use | L35: 1 | M35: 3 | N35: Microsoft 365 (planned) | O35: IaaS | P35: mcxapp01, mcxdb01 | Q35: 2 | R35: HP-UX 11i v3 | S35: TBD | T35: AWS us-east-1 | U35: 44561 | V35: Both | W35: 48 | X35: N | Y35: 7 | Z35: N | AA35: None | AB35: 5 | AC35: Partial | AD35: N | AE35: N | AF35: 16000 | AG35: 46507 | AH35: 6500 | AI35: 75000 | AJ35: =IF(AND(ISNUMBER(AH35),ISNUMBER(AI35),N(AI35)>0),AH35/AI35*12,"") -> 1.04 | AK35: =IF(B35="","",OR(K35="Not in use",K35="Low use")+AND(N35<>"",N35<>"TBD")+AND(ISNUMBER(U35),U35<=EDATE('Scoring Settings'!$B$4,'Scoring Settings'!$B$8))+AND(ISNUMBER(L35),L35<='Scoring Settings'!$B$7)) -> 4 | AL35: Retire | AM35: =IF(B35="","",IF(Z35="N","Easy",IF(OR(AND(ISNUMBER(AB35),AB35>'Scoring Settings'!$B$11),AND(ISNUMBER(W35),W35>'Scoring Settings'!$B$12),AND(ISNUMBER(M35),M35<='Scoring Settings'!$B$13)),"High","Medium"))) -> Easy | AN35: Wave 1 | AO35: 44347 | AP35: Completed | AQ35: No active users; switch-off confirmed with owner
A36: 145984 | B36: Departmental Safety Incident Tracker | C36: Health & Safety | D36: Operations | E36: Internal | I36: 4 | J36: 44263 | K36: =IF(B36="","",IF(AND(I36="",J36=""),"Unknown",IF(OR(AND(ISNUMBER(I36),I36=0),AND(ISNUMBER(J36),J36<=EDATE('Scoring Settings'!$B$4,-'Scoring Settings'!$B$5))),"Not in use",IF(AND(ISNUMBER(I36),I36<'Scoring Settings'!$B$6),"Low use","Active")))) -> Low use | L36: 2 | M36: 4 | N36: TBD | O36: On-prem DC | P36: dsiapp01 | Q36: 1 | R36: RHEL 6 | S36: Oracle 11g | T36: TBD | U36: 44165 | V36: Structured | W36: 8 | X36: N | Y36: 5 | Z36: N | AA36: None | AB36: 1 | AC36: Y | AD36: N | AE36: Y | AF36: 29500 | AG36: 47726 | AH36: 32000 | AI36: 88500 | AJ36: =IF(AND(ISNUMBER(AH36),ISNUMBER(AI36),N(AI36)>0),AH36/AI36*12,"") -> 4.3389831 | AK36: =IF(B36="","",OR(K36="Not in use",K36="Low use")+AND(N36<>"",N36<>"TBD")+AND(ISNUMBER(U36),U36<=EDATE('Scoring Settings'!$B$4,'Scoring Settings'!$B$8))+AND(ISNUMBER(L36),L36<='Scoring Settings'!$B$7)) -> 3 | AL36: Retire | AM36: =IF(B36="","",IF(Z36="N","Easy",IF(OR(AND(ISNUMBER(AB36),AB36>'Scoring Settings'!$B$11),AND(ISNUMBER(W36),W36>'Scoring Settings'!$B$12),AND(ISNUMBER(M36),M36<='Scoring Settings'!$B$13)),"High","Medium"))) -> Easy | AN36: Wave 1 | AO36: 44500 | AP36: In progress | AQ36: No active users; switch-off confirmed with owner
A37: 140092 | B37: Inventory Control Plus | C37: Inventory | D37: Supply Chain | E37: Internal | I37: 19 | J37: 44311 | K37: =IF(B37="","",IF(AND(I37="",J37=""),"Unknown",IF(OR(AND(ISNUMBER(I37),I37=0),AND(ISNUMBER(J37),J37<=EDATE('Scoring Settings'!$B$4,-'Scoring Settings'!$B$5))),"Not in use",IF(AND(ISNUMBER(I37),I37<'Scoring Settings'!$B$6),"Low use","Active")))) -> Low use | L37: 2 | M37: 4 | N37: TBD | O37: On-prem DC | P37: icpapp01, icpdb01 | Q37: 2 | R37: SUSE Linux 11 | S37: Oracle 11g | T37: EU DC-1 | U37: 43555 | V37: Structured | W37: 450 | X37: Y | Y37: 10 | Z37: Y | AA37: Archive + read-only | AB37: 3 | AC37: Partial | AD37: N | AE37: Partial | AF37: 31500 | AG37: 48273 | AH37: 30500 | AI37: 89000 | AJ37: =IF(AND(ISNUMBER(AH37),ISNUMBER(AI37),N(AI37)>0),AH37/AI37*12,"") -> 4.1123596 | AK37: =IF(B37="","",OR(K37="Not in use",K37="Low use")+AND(N37<>"",N37<>"TBD")+AND(ISNUMBER(U37),U37<=EDATE('Scoring Settings'!$B$4,'Scoring Settings'!$B$8))+AND(ISNUMBER(L37),L37<='Scoring Settings'!$B$7)) -> 3 | AL37: Retire + Archive | AM37: =IF(B37="","",IF(Z37="N","Easy",IF(OR(AND(ISNUMBER(AB37),AB37>'Scoring Settings'!$B$11),AND(ISNUMBER(W37),W37>'Scoring Settings'!$B$12),AND(ISNUMBER(M37),M37<='Scoring Settings'!$B$13)),"High","Medium"))) -> Medium | AN37: Wave 1 | AO37: 44530 | AP37: In progress | AQ37: Read-only access needed for audit
A38: 180343 | B38: Tax Compliance Tool (APAC) | C38: Tax | D38: Finance | E38: Internal | I38: 0 | J38: 44243 | K38: =IF(B38="","",IF(AND(I38="",J38=""),"Unknown",IF(OR(AND(ISNUMBER(I38),I38=0),AND(ISNUMBER(J38),J38<=EDATE('Scoring Settings'!$B$4,-'Scoring Settings'!$B$5))),"Not in use",IF(AND(ISNUMBER(I38),I38<'Scoring Settings'!$B$6),"Low use","Active")))) -> Not in use | L38: 1 | M38: 4 | O38: On-prem DC | P38: tctapp01, tctdb01, tctweb01 | Q38: 3 | R38: Windows Server 2008 R2 | S38: SQL Server 2008 R2 | T38: Plant DC | U38: 43844 | V38: Structured | W38: 13050 | X38: Y | Y38: 10 | Z38: Y | AA38: Data archive | AB38: 3 | AC38: N | AD38: N | AE38: Partial | AF38: 40500 | AG38: 48730 | AH38: 306500 | AI38: 63500 | AJ38: =IF(AND(ISNUMBER(AH38),ISNUMBER(AI38),N(AI38)>0),AH38/AI38*12,"") -> 57.92126 | AK38: =IF(B38="","",OR(K38="Not in use",K38="Low use")+AND(N38<>"",N38<>"TBD")+AND(ISNUMBER(U38),U38<=EDATE('Scoring Settings'!$B$4,'Scoring Settings'!$B$8))+AND(ISNUMBER(L38),L38<='Scoring Settings'!$B$7)) -> 3 | AL38: Retire + Archive | AM38: =IF(B38="","",IF(Z38="N","Easy",IF(OR(AND(ISNUMBER(AB38),AB38>'Scoring Settings'!$B$11),AND(ISNUMBER(W38),W38>'Scoring Settings'!$B$12),AND(ISNUMBER(M38),M38<='Scoring Settings'!$B$13)),"High","Medium"))) -> High | AN38: Wave 1 | AO38: 44255 | AP38: Completed | AQ38: Data archived and validated; switched off Feb-21
A39: 34980 | B39: Custom Org Chart Publisher (APAC) | C39: Org Mgmt | D39: HR | E39: Internal | I39: 11 | J39: 44229 | K39: =IF(B39="","",IF(AND(I39="",J39=""),"Unknown",IF(OR(AND(ISNUMBER(I39),I39=0),AND(ISNUMBER(J39),J39<=EDATE('Scoring Settings'!$B$4,-'Scoring Settings'!$B$5))),"Not in use",IF(AND(ISNUMBER(I39),I39<'Scoring Settings'!$B$6),"Low use","Active")))) -> Low use | L39: 2 | M39: 4 | N39: Workday Recruiting | O39: On-prem DC | P39: cocapp01, cocdb01, cocweb01 | Q39: 3 | R39: Ubuntu 16.04 | S39: MySQL 5.7 | T39: Plant DC | U39: 44316 | V39: Structured | W39: 1 | X39: Y | Y39: 7 | Z39: N | AA39: None | AB39: 3 | AC39: N | AD39: N | AE39: Y | AF39: 45500 | AG39: 46721 | AH39: 36000 | AI39: 55000 | AJ39: =IF(AND(ISNUMBER(AH39),ISNUMBER(AI39),N(AI39)>0),AH39/AI39*12,"") -> 7.8545455 | AK39: =IF(B39="","",OR(K39="Not in use",K39="Low use")+AND(N39<>"",N39<>"TBD")+AND(ISNUMBER(U39),U39<=EDATE('Scoring Settings'!$B$4,'Scoring Settings'!$B$8))+AND(ISNUMBER(L39),L39<='Scoring Settings'!$B$7)) -> 4 | AL39: Retire | AM39: =IF(B39="","",IF(Z39="N","Easy",IF(OR(AND(ISNUMBER(AB39),AB39>'Scoring Settings'!$B$11),AND(ISNUMBER(W39),W39>'Scoring Settings'!$B$12),AND(ISNUMBER(M39),M39<='Scoring Settings'!$B$13)),"High","Medium"))) -> Easy | AN39: Wave 1 | AO39: 44469 | AP39: In progress | AQ39: Functionality covered by existing tools
A40: 23345 | B40: Shared Inventory Control Classic | C40: Inventory | D40: Supply Chain | E40: Internal | I40: 7 | J40: 44209 | K40: =IF(B40="","",IF(AND(I40="",J40=""),"Unknown",IF(OR(AND(ISNUMBER(I40),I40=0),AND(ISNUMBER(J40),J40<=EDATE('Scoring Settings'!$B$4,-'Scoring Settings'!$B$5))),"Not in use",IF(AND(ISNUMBER(I40),I40<'Scoring Settings'!$B$6),"Low use","Active")))) -> Low use | L40: 1 | M40: 4 | O40: On-prem DC | P40: sicapp01 | Q40: 1 | R40: Windows Server 2016 | S40: SQL Server 2017 | T40: US DC-1 | U40: 46399 | V40: Both | W40: 180 | X40: Y | Y40: 10 | Z40: Y | AA40: Archive + read-only | AB40: 2 | AC40: Partial | AD40: Partial | AE40: Partial | AF40: 11500 | AG40: 47603 | AH40: 14000 | AI40: 68500 | AJ40: =IF(AND(ISNUMBER(AH40),ISNUMBER(AI40),N(AI40)>0),AH40/AI40*12,"") -> 2.4525547 | AK40: =IF(B40="","",OR(K40="Not in use",K40="Low use")+AND(N40<>"",N40<>"TBD")+AND(ISNUMBER(U40),U40<=EDATE('Scoring Settings'!$B$4,'Scoring Settings'!$B$8))+AND(ISNUMBER(L40),L40<='Scoring Settings'!$B$7)) -> 2 | AL40: Retire + Archive | AM40: =IF(B40="","",IF(Z40="N","Easy",IF(OR(AND(ISNUMBER(AB40),AB40>'Scoring Settings'!$B$11),AND(ISNUMBER(W40),W40>'Scoring Settings'!$B$12),AND(ISNUMBER(M40),M40<='Scoring Settings'!$B$13)),"High","Medium"))) -> Medium | AN40: Wave 1 | AO40: 44530 | AP40: In progress | AQ40: Retention 10 yrs - archive slot booked
A41: 123490 | B41: Global Supplier Portal | C41: Supplier Mgmt | D41: Supply Chain | E41: Internal | I41: 0 | J41: 44309 | K41: =IF(B41="","",IF(AND(I41="",J41=""),"Unknown",IF(OR(AND(ISNUMBER(I41),I41=0),AND(ISNUMBER(J41),J41<=EDATE('Scoring Settings'!$B$4,-'Scoring Settings'!$B$5))),"Not in use",IF(AND(ISNUMBER(I41),I41<'Scoring Settings'!$B$6),"Low use","Active")))) -> Not in use | L41: 2 | M41: 3 | N41: SAP IBP | O41: IaaS | P41: gspapp01, gspdb01, gspweb01 | Q41: 3 | R41: Windows Server 2016 | S41: SQL Server 2017 | T41: AWS eu-west-1 | U41: 46399 | V41: Structured | W41: 390 | X41: Y | Y41: 7 | Z41: N | AA41: None | AB41: 4 | AC41: N | AD41: Partial | AE41: N | AF41: 30500 | AG41: 49248 | AH41: 34500 | AI41: 29000 | AJ41: =IF(AND(ISNUMBER(AH41),ISNUMBER(AI41),N(AI41)>0),AH41/AI41*12,"") -> 14.275862 | AK41: =IF(B41="","",OR(K41="Not in use",K41="Low use")+AND(N41<>"",N41<>"TBD")+AND(ISNUMBER(U41),U41<=EDATE('Scoring Settings'!$B$4,'Scoring Settings'!$B$8))+AND(ISNUMBER(L41),L41<='Scoring Settings'!$B$7)) -> 3 | AL41: Retire | AM41: =IF(B41="","",IF(Z41="N","Easy",IF(OR(AND(ISNUMBER(AB41),AB41>'Scoring Settings'!$B$11),AND(ISNUMBER(W41),W41>'Scoring Settings'!$B$12),AND(ISNUMBER(M41),M41<='Scoring Settings'!$B$13)),"High","Medium"))) -> Easy | AN41: Wave 1 | AO41: 44316 | AP41: Completed | AQ41: Switched off Apr-21; licence terminated
A42: 187110 | B42: Departmental Supplier Portal Plus | C42: Supplier Mgmt | D42: Supply Chain | E42: Internal | I42: 0 | J42: 44234 | K42: =IF(B42="","",IF(AND(I42="",J42=""),"Unknown",IF(OR(AND(ISNUMBER(I42),I42=0),AND(ISNUMBER(J42),J42<=EDATE('Scoring Settings'!$B$4,-'Scoring Settings'!$B$5))),"Not in use",IF(AND(ISNUMBER(I42),I42<'Scoring Settings'!$B$6),"Low use","Active")))) -> Not in use | L42: 4 | M42: 3 | N42: SAP TM | O42: On-prem DC | P42: dspapp01, dspdb01, dspweb01, dspfs01 | Q42: 4 | R42: Ubuntu 16.04 | S42: MySQL 5.7 | T42: TBD | U42: 44316 | V42: Both | W42: 310 | X42: N | Y42: 3 | Z42: N | AA42: None | AB42: 5 | AC42: Y | AD42: N | AE42: N | AF42: 43000 | AG42: 45869 | AH42: 49000 | AI42: 35000 | AJ42: =IF(AND(ISNUMBER(AH42),ISNUMBER(AI42),N(AI42)>0),AH42/AI42*12,"") -> 16.8 | AK42: =IF(B42="","",OR(K42="Not in use",K42="Low use")+AND(N42<>"",N42<>"TBD")+AND(ISNUMBER(U42),U42<=EDATE('Scoring Settings'!$B$4,'Scoring Settings'!$B$8))+AND(ISNUMBER(L42),L42<='Scoring Settings'!$B$7)) -> 3 | AL42: Migrate | AM42: =IF(B42="","",IF(Z42="N","Easy",IF(OR(AND(ISNUMBER(AB42),AB42>'Scoring Settings'!$B$11),AND(ISNUMBER(W42),W42>'Scoring Settings'!$B$12),AND(ISNUMBER(M42),M42<='Scoring Settings'!$B$13)),"High","Medium"))) -> Easy | AN42: Wave 1 | AO42: 44255 | AP42: Completed | AQ42: Migrated to SAP TM; legacy switched off Feb-21
A43: 122617 | B43: Shared Brand Asset Library Classic | C43: Digital Assets | D43: Marketing | E43: Internal | I43: 0 | J43: 44224 | K43: =IF(B43="","",IF(AND(I43="",J43=""),"Unknown",IF(OR(AND(ISNUMBER(I43),I43=0),AND(ISNUMBER(J43),J43<=EDATE('Scoring Settings'!$B$4,-'Scoring Settings'!$B$5))),"Not in use",IF(AND(ISNUMBER(I43),I43<'Scoring Settings'!$B$6),"Low use","Active")))) -> Not in use | L43: 2 | M43: 4 | N43: Marketo | O43: IaaS | P43: sbaapp01 | Q43: 1 | R43: RHEL 7 | S43: Oracle 12c | T43: AWS eu-west-1 | U43: 45473 | V43: Structured | W43: 430 | X43: Y | Y43: 5 | Z43: Y | AA43: Read-only access | AB43: 0 | AC43: Partial | AD43: Y | AE43: Y | AF43: 13000 | AG43: 48487 | AH43: 13000 | AI43: 8500 | AJ43: =IF(AND(ISNUMBER(AH43),ISNUMBER(AI43),N(AI43)>0),AH43/AI43*12,"") -> 18.352941 | AK43: =IF(B43="","",OR(K43="Not in use",K43="Low use")+AND(N43<>"",N43<>"TBD")+AND(ISNUMBER(U43),U43<=EDATE('Scoring Settings'!$B$4,'Scoring Settings'!$B$8))+AND(ISNUMBER(L43),L43<='Scoring Settings'!$B$7)) -> 3 | AL43: Retire + Archive | AM43: =IF(B43="","",IF(Z43="N","Easy",IF(OR(AND(ISNUMBER(AB43),AB43>'Scoring Settings'!$B$11),AND(ISNUMBER(W43),W43>'Scoring Settings'!$B$12),AND(ISNUMBER(M43),M43<='Scoring Settings'!$B$13)),"High","Medium"))) -> Medium | AN43: Wave 1 | AO43: 44227 | AP43: Completed | AQ43: Data archived and validated; switched off Jan-21
A44: 111142 | B44: Inventory Control Classic | C44: Inventory | D44: Supply Chain | E44: Partner | I44: 0 | J44: 43932 | K44: =IF(B44="","",IF(AND(I44="",J44=""),"Unknown",IF(OR(AND(ISNUMBER(I44),I44=0),AND(ISNUMBER(J44),J44<=EDATE('Scoring Settings'!$B$4,-'Scoring Settings'!$B$5))),"Not in use",IF(AND(ISNUMBER(I44),I44<'Scoring Settings'!$B$6),"Low use","Active")))) -> Not in use | L44: 3 | M44: 3 | O44: On-prem DC | P44: iccapp01, iccdb01 | Q44: 2 | R44: SUSE Linux 11 | S44: Oracle 11g | T44: EU DC-2 | U44: 43555 | V44: Unstructured | W44: 9 | X44: N | Y44: 3 | Z44: N | AA44: None | AB44: 4 | AC44: N | AD44: Y | AE44: N | AF44: 26000 | AG44: 48791 | AH44: 17500 | AI44: 22000 | AJ44: =IF(AND(ISNUMBER(AH44),ISNUMBER(AI44),N(AI44)>0),AH44/AI44*12,"") -> 9.5454545 | AK44: =IF(B44="","",OR(K44="Not in use",K44="Low use")+AND(N44<>"",N44<>"TBD")+AND(ISNUMBER(U44),U44<=EDATE('Scoring Settings'!$B$4,'Scoring Settings'!$B$8))+AND(ISNUMBER(L44),L44<='Scoring Settings'!$B$7)) -> 2 | AL44: Retire | AM44: =IF(B44="","",IF(Z44="N","Easy",IF(OR(AND(ISNUMBER(AB44),AB44>'Scoring Settings'!$B$11),AND(ISNUMBER(W44),W44>'Scoring Settings'!$B$12),AND(ISNUMBER(M44),M44<='Scoring Settings'!$B$13)),"High","Medium"))) -> Easy | AN44: Wave 1 | AO44: 44408 | AP44: In progress | AQ44: No active users; switch-off confirmed with owner
A45: 104856 | B45: Shared Survey Tool Classic | C45: Market Research | D45: Marketing | E45: Internal | I45: 8 | J45: 44272 | K45: =IF(B45="","",IF(AND(I45="",J45=""),"Unknown",IF(OR(AND(ISNUMBER(I45),I45=0),AND(ISNUMBER(J45),J45<=EDATE('Scoring Settings'!$B$4,-'Scoring Settings'!$B$5))),"Not in use",IF(AND(ISNUMBER(I45),I45<'Scoring Settings'!$B$6),"Low use","Active")))) -> Low use | L45: 4 | M45: 3 | N45: Qualtrics (planned) | O45: On-prem DC | P45: sstapp01, sstdb01 | Q45: 2 | R45: Ubuntu 20.04 | S45: MySQL 8.0 | T45: US DC-1 | U45: 45777 | V45: Structured | W45: 300 | X45: N | Y45: 5 | Z45: Y | AA45: Read-only access | AB45: 3 | AC45: Y | AD45: N | AE45: Y | AF45: 99500 | AG45: 46630 | AH45: 36000 | AI45: 74500 | AJ45: =IF(AND(ISNUMBER(AH45),ISNUMBER(AI45),N(AI45)>0),AH45/AI45*12,"") -> 5.7986577 | AK45: =IF(B45="","",OR(K45="Not in use",K45="Low use")+AND(N45<>"",N45<>"TBD")+AND(ISNUMBER(U45),U45<=EDATE('Scoring Settings'!$B$4,'Scoring Settings'!$B$8))+AND(ISNUMBER(L45),L45<='Scoring Settings'!$B$7)) -> 2 | AL45: Migrate | AM45: =IF(B45="","",IF(Z45="N","Easy",IF(OR(AND(ISNUMBER(AB45),AB45>'Scoring Settings'!$B$11),AND(ISNUMBER(W45),W45>'Scoring Settings'!$B$12),AND(ISNUMBER(M45),M45<='Scoring Settings'!$B$13)),"High","Medium"))) -> Medium | AN45: Wave 1 | AO45: 44408 | AP45: In progress | AQ45: Cut-over planned for Jul-21; parallel run scheduled Blocker: Legal sign-off on retention Q: Who owns the retention decision for archived records?
A46: 51568 | B46: Shared Recruitment Tracker Plus | C46: Recruitment | D46: HR | E46: Internal | I46: 0 | J46: 44267 | K46: =IF(B46="","",IF(AND(I46="",J46=""),"Unknown",IF(OR(AND(ISNUMBER(I46),I46=0),AND(ISNUMBER(J46),J46<=EDATE('Scoring Settings'!$B$4,-'Scoring Settings'!$B$5))),"Not in use",IF(AND(ISNUMBER(I46),I46<'Scoring Settings'!$B$6),"Low use","Active")))) -> Not in use | L46: 2 | M46: 3 | O46: On-prem DC | P46: srtapp01 | Q46: 1 | R46: AIX 6.1 | S46: TBD | T46: US DC-1 | U46: 42855 | V46: Structured | W46: 190 | X46: N | Y46: 3 | Z46: Y | AA46: Read-only access | AB46: 5 | AC46: Partial | AD46: Partial | AE46: Partial | AF46: 39000 | AG46: 48760 | AH46: 37500 | AI46: 28500 | AJ46: =IF(AND(ISNUMBER(AH46),ISNUMBER(AI46),N(AI46)>0),AH46/AI46*12,"") -> 15.789474 | AK46: =IF(B46="","",OR(K46="Not in use",K46="Low use")+AND(N46<>"",N46<>"TBD")+AND(ISNUMBER(U46),U46<=EDATE('Scoring Settings'!$B$4,'Scoring Settings'!$B$8))+AND(ISNUMBER(L46),L46<='Scoring Settings'!$B$7)) -> 3 | AL46: Retire + Archive | AM46: =IF(B46="","",IF(Z46="N","Easy",IF(OR(AND(ISNUMBER(AB46),AB46>'Scoring Settings'!$B$11),AND(ISNUMBER(W46),W46>'Scoring Settings'!$B$12),AND(ISNUMBER(M46),M46<='Scoring Settings'!$B$13)),"High","Medium"))) -> Medium | AN46: Wave 1 | AO46: 44286 | AP46: Completed | AQ46: Data archived and validated; switched off Mar-21
A47: 195565 | B47: Corporate Asset Register Classic | C47: Fixed Assets | D47: Finance | E47: Internal | I47: 149 | J47: 44315 | K47: =IF(B47="","",IF(AND(I47="",J47=""),"Unknown",IF(OR(AND(ISNUMBER(I47),I47=0),AND(ISNUMBER(J47),J47<=EDATE('Scoring Settings'!$B$4,-'Scoring Settings'!$B$5))),"Not in use",IF(AND(ISNUMBER(I47),I47<'Scoring Settings'!$B$6),"Low use","Active")))) -> Active | L47: 3 | M47: 4 | N47: Anaplan (planned) | O47: On-prem DC | P47: carapp01, cardb01, carweb01 | Q47: 3 | R47: Windows Server 2012 R2 | S47: SQL Server 2014 | T47: EU DC-1 | U47: TBD | V47: Both | W47: 170 | X47: Y | Y47: 10 | Z47: N | AA47: None | AB47: 0 | AC47: N | AD47: N | AE47: N | AF47: 48500 | AG47: 46356 | AH47: 38500 | AI47: 43000 | AJ47: =IF(AND(ISNUMBER(AH47),ISNUMBER(AI47),N(AI47)>0),AH47/AI47*12,"") -> 10.744186 | AK47: =IF(B47="","",OR(K47="Not in use",K47="Low use")+AND(N47<>"",N47<>"TBD")+AND(ISNUMBER(U47),U47<=EDATE('Scoring Settings'!$B$4,'Scoring Settings'!$B$8))+AND(ISNUMBER(L47),L47<='Scoring Settings'!$B$7)) -> 1 | AL47: Migrate | AM47: =IF(B47="","",IF(Z47="N","Easy",IF(OR(AND(ISNUMBER(AB47),AB47>'Scoring Settings'!$B$11),AND(ISNUMBER(W47),W47>'Scoring Settings'!$B$12),AND(ISNUMBER(M47),M47<='Scoring Settings'!$B$13)),"High","Medium"))) -> Easy | AN47: Wave 1 | AO47: 44439 | AP47: In progress | AQ47: 3 feeds to re-point to Anaplan
A48: 48049 | B48: Partner Portal Plus | C48: Partner Mgmt | D48: Sales | E48: External | I48: 0 | J48: 44292 | K48: =IF(B48="","",IF(AND(I48="",J48=""),"Unknown",IF(OR(AND(ISNUMBER(I48),I48=0),AND(ISNUMBER(J48),J48<=EDATE('Scoring Settings'!$B$4,-'Scoring Settings'!$B$5))),"Not in use",IF(AND(ISNUMBER(I48),I48<'Scoring Settings'!$B$6),"Low use","Active")))) -> Not in use | L48: 2 | M48: 4 | O48: On-prem DC | P48: pppapp01 | Q48: 1 | R48: Solaris 10 | S48: Oracle 11g | T48: EU DC-1 | U48: 44227 | V48: Structured | W48: 67 | X48: Y | Y48: 7 | Z48: Y | AA48: Reporting extract | AB48: 0 | AC48: Y | AD48: Partial | AE48: N | AF48: 84500 | AG48: 46234 | AH48: 10000 | AI48: 89500 | AJ48: =IF(AND(ISNUMBER(AH48),ISNUMBER(AI48),N(AI48)>0),AH48/AI48*12,"") -> 1.3407821 | AK48: =IF(B48="","",OR(K48="Not in use",K48="Low use")+AND(N48<>"",N48<>"TBD")+AND(ISNUMBER(U48),U48<=EDATE('Scoring Settings'!$B$4,'Scoring Settings'!$B$8))+AND(ISNUMBER(L48),L48<='Scoring Settings'!$B$7)) -> 3 | AL48: Retire + Archive | AM48: =IF(B48="","",IF(Z48="N","Easy",IF(OR(AND(ISNUMBER(AB48),AB48>'Scoring Settings'!$B$11),AND(ISNUMBER(W48),W48>'Scoring Settings'!$B$12),AND(ISNUMBER(M48),M48<='Scoring Settings'!$B$13)),"High","Medium"))) -> Medium | AN48: Wave 1 | AO48: 44316 | AP48: Completed | AQ48: Data archived and validated; switched off Apr-21
A49: 59643 | B49: Regional GL Consolidation Tool | C49: General Ledger | D49: Finance | E49: Partner | I49: 0 | J49: 44233 | K49: =IF(B49="","",IF(AND(I49="",J49=""),"Unknown",IF(OR(AND(ISNUMBER(I49),I49=0),AND(ISNUMBER(J49),J49<=EDATE('Scoring Settings'!$B$4,-'Scoring Settings'!$B$5))),"Not in use",IF(AND(ISNUMBER(I49),I49<'Scoring Settings'!$B$6),"Low use","Active")))) -> Not in use | L49: 1 | M49: 4 | O49: On-prem DC | P49: rgcapp01, rgcdb01 | Q49: 2 | R49: Windows Server 2008 | S49: SQL Server 2008 | T49: US DC-1 | U49: 43655 | V49: Both | W49: 65 | X49: Y | Y49: 7 | Z49: Y | AA49: Archive + read-only | AB49: 0 | AC49: N | AD49: Y | AE49: Y | AF49: 39500 | AG49: 47026 | AH49: 25000 | AI49: 32500 | AJ49: =IF(AND(ISNUMBER(AH49),ISNUMBER(AI49),N(AI49)>0),AH49/AI49*12,"") -> 9.2307692 | AK49: =IF(B49="","",OR(K49="Not in use",K49="Low use")+AND(N49<>"",N49<>"TBD")+AND(ISNUMBER(U49),U49<=EDATE('Scoring Settings'!$B$4,'Scoring Settings'!$B$8))+AND(ISNUMBER(L49),L49<='Scoring Settings'!$B$7)) -> 3 | AL49: Retire + Archive | AM49: =IF(B49="","",IF(Z49="N","Easy",IF(OR(AND(ISNUMBER(AB49),AB49>'Scoring Settings'!$B$11),AND(ISNUMBER(W49),W49>'Scoring Settings'!$B$12),AND(ISNUMBER(M49),M49<='Scoring Settings'!$B$13)),"High","Medium"))) -> Medium | AN49: Wave 1 | AO49: 44255 | AP49: Completed | AQ49: Data archived and validated; switched off Feb-21
A50: 135505 | B50: Legacy CMDB Lite | C50: Config Mgmt | D50: IT | E50: Internal | I50: 3 | J50: 44207 | K50: =IF(B50="","",IF(AND(I50="",J50=""),"Unknown",IF(OR(AND(ISNUMBER(I50),I50=0),AND(ISNUMBER(J50),J50<=EDATE('Scoring Settings'!$B$4,-'Scoring Settings'!$B$5))),"Not in use",IF(AND(ISNUMBER(I50),I50<'Scoring Settings'!$B$6),"Low use","Active")))) -> Low use | L50: 1 | M50: 3 | O50: On-prem DC | P50: lclapp01, lcldb01 | Q50: 2 | R50: Windows Server 2012 R2 | S50: SQL Server 2012 | T50: TBD | U50: 44754 | V50: Structured | W50: 17 | X50: N | Y50: 3 | Z50: N | AA50: None | AB50: 6 | AC50: Partial | AD50: N | AE50: Y | AF50: 47000 | AG50: 46660 | AH50: 64000 | AI50: 50000 | AJ50: =IF(AND(ISNUMBER(AH50),ISNUMBER(AI50),N(AI50)>0),AH50/AI50*12,"") -> 15.36 | AK50: =IF(B50="","",OR(K50="Not in use",K50="Low use")+AND(N50<>"",N50<>"TBD")+AND(ISNUMBER(U50),U50<=EDATE('Scoring Settings'!$B$4,'Scoring Settings'!$B$8))+AND(ISNUMBER(L50),L50<='Scoring Settings'!$B$7)) -> 2 | AL50: Retire | AM50: =IF(B50="","",IF(Z50="N","Easy",IF(OR(AND(ISNUMBER(AB50),AB50>'Scoring Settings'!$B$11),AND(ISNUMBER(W50),W50>'Scoring Settings'!$B$12),AND(ISNUMBER(M50),M50<='Scoring Settings'!$B$13)),"High","Medium"))) -> Easy | AN50: Wave 1 | AO50: 44530 | AP50: In progress | AQ50: No active users; switch-off confirmed with owner
A51: 54551 | B51: Departmental Inventory Control 2012 | C51: Inventory | D51: Supply Chain | E51: Partner | I51: 10 | J51: 44313 | K51: =IF(B51="","",IF(AND(I51="",J51=""),"Unknown",IF(OR(AND(ISNUMBER(I51),I51=0),AND(ISNUMBER(J51),J51<=EDATE('Scoring Settings'!$B$4,-'Scoring Settings'!$B$5))),"Not in use",IF(AND(ISNUMBER(I51),I51<'Scoring Settings'!$B$6),"Low use","Active")))) -> Low use | L51: 2 | M51: 4 | O51: On-prem DC | P51: dicapp01, dicdb01, dicweb01, dicfs01 | Q51: 4 | R51: Ubuntu 16.04 | S51: MySQL 5.7 | T51: US DC-1 | U51: 44316 | V51: Both | W51: 37 | X51: N | Y51: 5 | Z51: N | AA51: None | AB51: 3 | AC51: Partial | AD51: Y | AE51: Partial | AF51: 65000 | AG51: 47726 | AH51: 51500 | AI51: 54000 | AJ51: =IF(AND(ISNUMBER(AH51),ISNUMBER(AI51),N(AI51)>0),AH51/AI51*12,"") -> 11.444444 | AK51: =IF(B51="","",OR(K51="Not in use",K51="Low use")+AND(N51<>"",N51<>"TBD")+AND(ISNUMBER(U51),U51<=EDATE('Scoring Settings'!$B$4,'Scoring Settings'!$B$8))+AND(ISNUMBER(L51),L51<='Scoring Settings'!$B$7)) -> 3 | AL51: Retire | AM51: =IF(B51="","",IF(Z51="N","Easy",IF(OR(AND(ISNUMBER(AB51),AB51>'Scoring Settings'!$B$11),AND(ISNUMBER(W51),W51>'Scoring Settings'!$B$12),AND(ISNUMBER(M51),M51<='Scoring Settings'!$B$13)),"High","Medium"))) -> Easy | AN51: Wave 1 | AO51: 44500 | AP51: In progress | AQ51: Owner sign-off received; switch-off scheduled
A52: 104516 | B52: Regional Order Entry Portal | C52: Order Entry | D52: Sales | E52: Internal | I52: 1 | J52: 43744 | K52: =IF(B52="","",IF(AND(I52="",J52=""),"Unknown",IF(OR(AND(ISNUMBER(I52),I52=0),AND(ISNUMBER(J52),J52<=EDATE('Scoring Settings'!$B$4,-'Scoring Settings'!$B$5))),"Not in use",IF(AND(ISNUMBER(I52),I52<'Scoring Settings'!$B$6),"Low use","Active")))) -> Not in use | L52: 2 | M52: 3 | O52: On-prem DC | P52: roeapp01 | Q52: 1 | R52: RHEL 6 | S52: Oracle 11g | T52: EU DC-1 | U52: 44165 | V52: Structured | W52: 190 | X52: Y | Y52: 10 | Z52: Y | AA52: Data archive | AB52: 4 | AC52: Y | AD52: N | AE52: Y | AF52: 81500 | AG52: 49460 | AH52: 14500 | AI52: 87500 | AJ52: =IF(AND(ISNUMBER(AH52),ISNUMBER(AI52),N(AI52)>0),AH52/AI52*12,"") -> 1.9885714 | AK52: =IF(B52="","",OR(K52="Not in use",K52="Low use")+AND(N52<>"",N52<>"TBD")+AND(ISNUMBER(U52),U52<=EDATE('Scoring Settings'!$B$4,'Scoring Settings'!$B$8))+AND(ISNUMBER(L52),L52<='Scoring Settings'!$B$7)) -> 3 | AL52: Retire + Archive | AM52: =IF(B52="","",IF(Z52="N","Easy",IF(OR(AND(ISNUMBER(AB52),AB52>'Scoring Settings'!$B$11),AND(ISNUMBER(W52),W52>'Scoring Settings'!$B$12),AND(ISNUMBER(M52),M52<='Scoring Settings'!$B$13)),"High","Medium"))) -> Medium | AN52: Wave 1 | AO52: 44347 | AP52: Completed | AQ52: Archive format agreed; load scheduled before switch-off
A53: 32726 | B53: Regional Recruitment Tracker v4 | C53: Recruitment | D53: HR | E53: External | I53: 0 | J53: 44261 | K53: =IF(B53="","",IF(AND(I53="",J53=""),"Unknown",IF(OR(AND(ISNUMBER(I53),I53=0),AND(ISNUMBER(J53),J53<=EDATE('Scoring Settings'!$B$4,-'Scoring Settings'!$B$5))),"Not in use",IF(AND(ISNUMBER(I53),I53<'Scoring Settings'!$B$6),"Low use","Active")))) -> Not in use | L53: 2 | M53: 4 | N53: Cornerstone | O53: IaaS | P53: rrtapp01, rrtdb01, rrtweb01 | Q53: 3 | R53: Ubuntu 16.04 | S53: MySQL 5.7 | T53: Azure West Europe | U53: 44316 | V53: Both | W53: 120 | X53: Y | Y53: 5 | Z53: N | AA53: None | AB53: 3 | AC53: Partial | AD53: Partial | AE53: N | AF53: 130500 | AG53: 47177 | AH53: 17000 | AI53: 109000 | AJ53: =IF(AND(ISNUMBER(AH53),ISNUMBER(AI53),N(AI53)>0),AH53/AI53*12,"") -> 1.8715596 | AK53: =IF(B53="","",OR(K53="Not in use",K53="Low use")+AND(N53<>"",N53<>"TBD")+AND(ISNUMBER(U53),U53<=EDATE('Scoring Settings'!$B$4,'Scoring Settings'!$B$8))+AND(ISNUMBER(L53),L53<='Scoring Settings'!$B$7)) -> 4 | AL53: Retire | AM53: =IF(B53="","",IF(Z53="N","Easy",IF(OR(AND(ISNUMBER(AB53),AB53>'Scoring Settings'!$B$11),AND(ISNUMBER(W53),W53>'Scoring Settings'!$B$12),AND(ISNUMBER(M53),M53<='Scoring Settings'!$B$13)),"High","Medium"))) -> Easy | AN53: Wave 1 | AO53: 44286 | AP53: Completed | AQ53: Switched off Mar-21; licence terminated
A54: 71025 | B54: SAP BW | C54: Enterprise Data Warehouse | D54: Finance | E54: Internal | I54: 140 | J54: 44309 | K54: =IF(B54="","",IF(AND(I54="",J54=""),"Unknown",IF(OR(AND(ISNUMBER(I54),I54=0),AND(ISNUMBER(J54),J54<=EDATE('Scoring Settings'!$B$4,-'Scoring Settings'!$B$5))),"Not in use",IF(AND(ISNUMBER(I54),I54<'Scoring Settings'!$B$6),"Low use","Active")))) -> Active | L54: 3 | M54: 2 | N54: SAP Analytics Cloud | O54: On-prem DC | P54: bw-app01–02, bw-db01–02 | Q54: 4 | R54: SUSE Linux 11 | S54: SAP HANA 1.0 | T54: EU DC-1 | U54: 44196 | V54: Structured | W54: 3200 | X54: N | Y54: 7 | Z54: Y | AA54: Archive + read-only | AB54: 24 | AC54: Y | AD54: Partial | AE54: Y | AF54: 210000 | AG54: 47118 | AH54: 260000 | AI54: 170000 | AJ54: =IF(AND(ISNUMBER(AH54),ISNUMBER(AI54),N(AI54)>0),AH54/AI54*12,"") -> 18.352941 | AK54: =IF(B54="","",OR(K54="Not in use",K54="Low use")+AND(N54<>"",N54<>"TBD")+AND(ISNUMBER(U54),U54<=EDATE('Scoring Settings'!$B$4,'Scoring Settings'!$B$8))+AND(ISNUMBER(L54),L54<='Scoring Settings'!$B$7)) -> 2 | AL54: Retire + Archive | AM54: =IF(B54="","",IF(Z54="N","Easy",IF(OR(AND(ISNUMBER(AB54),AB54>'Scoring Settings'!$B$11),AND(ISNUMBER(W54),W54>'Scoring Settings'!$B$12),AND(ISNUMBER(M54),M54<='Scoring Settings'!$B$13)),"High","Medium"))) -> High | AN54: Wave 1 | AO54: 44377 | AP54: In progress | AQ54: Reports rebuilt in SAP Analytics Cloud; archive load in progress; switch-off May-21
A55: 104583 | B55: Old Commission Calculator | C55: Commissions | D55: Sales | E55: Internal | I55: 0 | J55: 44273 | K55: =IF(B55="","",IF(AND(I55="",J55=""),"Unknown",IF(OR(AND(ISNUMBER(I55),I55=0),AND(ISNUMBER(J55),J55<=EDATE('Scoring Settings'!$B$4,-'Scoring Settings'!$B$5))),"Not in use",IF(AND(ISNUMBER(I55),I55<'Scoring Settings'!$B$6),"Low use","Active")))) -> Not in use | L55: 4 | M55: 1 | N55: Salesforce CPQ | O55: IaaS | P55: occapp01 | Q55: 1 | R55: Solaris 10 | S55: Oracle 11g | T55: AWS us-east-1 | U55: 44227 | V55: Structured | W55: 140 | X55: Y | Y55: 7 | Z55: N | AA55: None | AB55: 41 | AC55: N | AD55: Partial | AE55: N | AF55: 25000 | AG55: 49248 | AH55: 60500 | AI55: 17500 | AJ55: =IF(AND(ISNUMBER(AH55),ISNUMBER(AI55),N(AI55)>0),AH55/AI55*12,"") -> 41.485714 | AK55: =IF(B55="","",OR(K55="Not in use",K55="Low use")+AND(N55<>"",N55<>"TBD")+AND(ISNUMBER(U55),U55<=EDATE('Scoring Settings'!$B$4,'Scoring Settings'!$B$8))+AND(ISNUMBER(L55),L55<='Scoring Settings'!$B$7)) -> 3 | AL55: Migrate | AM55: =IF(B55="","",IF(Z55="N","Easy",IF(OR(AND(ISNUMBER(AB55),AB55>'Scoring Settings'!$B$11),AND(ISNUMBER(W55),W55>'Scoring Settings'!$B$12),AND(ISNUMBER(M55),M55<='Scoring Settings'!$B$13)),"High","Medium"))) -> Easy | AN55: Wave 1 | AO55: 44286 | AP55: Completed | AQ55: Migrated to Salesforce CPQ; legacy switched off Mar-21
A56: 134806 | B56: Regional GL Consolidation Tool Plus | C56: General Ledger | D56: Finance | E56: Internal | I56: 15 | J56: 44283 | K56: =IF(B56="","",IF(AND(I56="",J56=""),"Unknown",IF(OR(AND(ISNUMBER(I56),I56=0),AND(ISNUMBER(J56),J56<=EDATE('Scoring Settings'!$B$4,-'Scoring Settings'!$B$5))),"Not in use",IF(AND(ISNUMBER(I56),I56<'Scoring Settings'!$B$6),"Low use","Active")))) -> Low use | L56: 3 | M56: 4 | O56: On-prem DC | P56: rgcapp01, rgcdb01 | Q56: 2 | R56: RHEL 6 | S56: Oracle 11g | T56: TBD | U56: 44165 | V56: Structured | W56: 640 | X56: Y | Y56: 5 | Z56: Y | AA56: Archive + read-only | AB56: 1 | AC56: Partial | AD56: Y | AE56: N | AF56: 37000 | AG56: 47879 | AH56: 34500 | AI56: 28000 | AJ56: =IF(AND(ISNUMBER(AH56),ISNUMBER(AI56),N(AI56)>0),AH56/AI56*12,"") -> 14.785714 | AK56: =IF(B56="","",OR(K56="Not in use",K56="Low use")+AND(N56<>"",N56<>"TBD")+AND(ISNUMBER(U56),U56<=EDATE('Scoring Settings'!$B$4,'Scoring Settings'!$B$8))+AND(ISNUMBER(L56),L56<='Scoring Settings'!$B$7)) -> 2 | AL56: Retire + Archive | AM56: =IF(B56="","",IF(Z56="N","Easy",IF(OR(AND(ISNUMBER(AB56),AB56>'Scoring Settings'!$B$11),AND(ISNUMBER(W56),W56>'Scoring Settings'!$B$12),AND(ISNUMBER(M56),M56<='Scoring Settings'!$B$13)),"High","Medium"))) -> Medium | AN56: Wave 1 | AO56: 44439 | AP56: In progress | AQ56: Read-only access needed for audit
A57: 154544 | B57: AP Invoice Processor v4 | C57: Accounts Payable | D57: Finance | E57: Internal | I57: 0 | J57: 44301 | K57: =IF(B57="","",IF(AND(I57="",J57=""),"Unknown",IF(OR(AND(ISNUMBER(I57),I57=0),AND(ISNUMBER(J57),J57<=EDATE('Scoring Settings'!$B$4,-'Scoring Settings'!$B$5))),"Not in use",IF(AND(ISNUMBER(I57),I57<'Scoring Settings'!$B$6),"Low use","Active")))) -> Not in use | L57: 1 | M57: 4 | N57: TBD | O57: IaaS | P57: aipapp01 | Q57: 1 | R57: AIX 6.1 | S57: DB2 9.7 | T57: Azure West Europe | U57: 42855 | V57: Both | W57: 9 | X57: Y | Y57: 5 | Z57: N | AA57: None | AB57: 0 | AC57: Partial | AD57: N | AE57: Y | AF57: 15000 | AG57: 46142 | AH57: 14500 | AI57: 13500 | AJ57: =IF(AND(ISNUMBER(AH57),ISNUMBER(AI57),N(AI57)>0),AH57/AI57*12,"") -> 12.888889 | AK57: =IF(B57="","",OR(K57="Not in use",K57="Low use")+AND(N57<>"",N57<>"TBD")+AND(ISNUMBER(U57),U57<=EDATE('Scoring Settings'!$B$4,'Scoring Settings'!$B$8))+AND(ISNUMBER(L57),L57<='Scoring Settings'!$B$7)) -> 3 | AL57: Retire | AM57: =IF(B57="","",IF(Z57="N","Easy",IF(OR(AND(ISNUMBER(AB57),AB57>'Scoring Settings'!$B$11),AND(ISNUMBER(W57),W57>'Scoring Settings'!$B$12),AND(ISNUMBER(M57),M57<='Scoring Settings'!$B$13)),"High","Medium"))) -> Easy | AN57: Wave 1 | AO57: 44316 | AP57: Completed | AQ57: Switched off Apr-21; licence terminated
A58: 31628 | B58: Purchase Order System v4 | C58: Procurement | D58: Supply Chain | E58: Internal | I58: 0 | J58: 44207 | K58: =IF(B58="","",IF(AND(I58="",J58=""),"Unknown",IF(OR(AND(ISNUMBER(I58),I58=0),AND(ISNUMBER(J58),J58<=EDATE('Scoring Settings'!$B$4,-'Scoring Settings'!$B$5))),"Not in use",IF(AND(ISNUMBER(I58),I58<'Scoring Settings'!$B$6),"Low use","Active")))) -> Not in use | L58: 3 | M58: 3 | O58: On-prem DC | P58: posapp01, posdb01, posweb01, posfs01 | Q58: 4 | R58: AIX 6.1 | S58: DB2 9.7 | T58: EU DC-2 | U58: 42855 | V58: Structured | W58: 37 | X58: N | Y58: 1 | Z58: N | AA58: None | AB58: 5 | AC58: Y | AD58: Partial | AE58: Partial | AF58: 35500 | AG58: 45716 | AH58: 29000 | AI58: 32500 | AJ58: =IF(AND(ISNUMBER(AH58),ISNUMBER(AI58),N(AI58)>0),AH58/AI58*12,"") -> 10.707692 | AK58: =IF(B58="","",OR(K58="Not in use",K58="Low use")+AND(N58<>"",N58<>"TBD")+AND(ISNUMBER(U58),U58<=EDATE('Scoring Settings'!$B$4,'Scoring Settings'!$B$8))+AND(ISNUMBER(L58),L58<='Scoring Settings'!$B$7)) -> 2 | AL58: Retire | AM58: =IF(B58="","",IF(Z58="N","Easy",IF(OR(AND(ISNUMBER(AB58),AB58>'Scoring Settings'!$B$11),AND(ISNUMBER(W58),W58>'Scoring Settings'!$B$12),AND(ISNUMBER(M58),M58<='Scoring Settings'!$B$13)),"High","Medium"))) -> Easy | AN58: Wave 1 | AO58: 44377 | AP58: In progress | AQ58: Functionality covered by existing tools
A59: 83626 | B59: Quote Manager (Nordics) | C59: Quoting | D59: Sales | E59: Internal | I59: 0 | J59: 44211 | K59: =IF(B59="","",IF(AND(I59="",J59=""),"Unknown",IF(OR(AND(ISNUMBER(I59),I59=0),AND(ISNUMBER(J59),J59<=EDATE('Scoring Settings'!$B$4,-'Scoring Settings'!$B$5))),"Not in use",IF(AND(ISNUMBER(I59),I59<'Scoring Settings'!$B$6),"Low use","Active")))) -> Not in use | L59: 2 | M59: 3 | O59: On-prem DC | P59: qmnapp01, qmndb01, qmnweb01, qmnfs01 | Q59: 4 | R59: RHEL 6 | S59: Oracle 11g | T59: US DC-1 | U59: 44165 | V59: Unstructured | W59: 160 | X59: Y | Y59: 10 | Z59: Y | AA59: Read-only access | AB59: 8 | AC59: Partial | AD59: Partial | AE59: N | AF59: 55000 | AG59: 45991 | AH59: 59500 | AI59: 37000 | AJ59: =IF(AND(ISNUMBER(AH59),ISNUMBER(AI59),N(AI59)>0),AH59/AI59*12,"") -> 19.297297 | AK59: =IF(B59="","",OR(K59="Not in use",K59="Low use")+AND(N59<>"",N59<>"TBD")+AND(ISNUMBER(U59),U59<=EDATE('Scoring Settings'!$B$4,'Scoring Settings'!$B$8))+AND(ISNUMBER(L59),L59<='Scoring Settings'!$B$7)) -> 3 | AL59: Retire + Archive | AM59: =IF(B59="","",IF(Z59="N","Easy",IF(OR(AND(ISNUMBER(AB59),AB59>'Scoring Settings'!$B$11),AND(ISNUMBER(W59),W59>'Scoring Settings'!$B$12),AND(ISNUMBER(M59),M59<='Scoring Settings'!$B$13)),"High","Medium"))) -> High | AN59: Wave 1 | AO59: 44227 | AP59: Completed | AQ59: Data archived and validated; switched off Jan-21
A60: 56965 | B60: Customer Contact Manager v3 | C60: CRM | D60: Sales | E60: Internal | I60: 10 | J60: 44283 | K60: =IF(B60="","",IF(AND(I60="",J60=""),"Unknown",IF(OR(AND(ISNUMBER(I60),I60=0),AND(ISNUMBER(J60),J60<=EDATE('Scoring Settings'!$B$4,-'Scoring Settings'!$B$5))),"Not in use",IF(AND(ISNUMBER(I60),I60<'Scoring Settings'!$B$6),"Low use","Active")))) -> Low use | L60: 3 | M60: 4 | N60: Salesforce Partner Community | O60: IaaS | P60: ccmapp01, ccmdb01, ccmweb01 | Q60: 3 | R60: AIX 6.1 | S60: DB2 9.7 | T60: AWS us-east-1 | U60: 42855 | V60: Structured | W60: 54 | X60: Y | Y60: 10 | Z60: N | AA60: None | AB60: 3 | AC60: Partial | AD60: Y | AE60: N | AF60: 19500 | AG60: 49613 | AH60: 19500 | AI60: 16000 | AJ60: =IF(AND(ISNUMBER(AH60),ISNUMBER(AI60),N(AI60)>0),AH60/AI60*12,"") -> 14.625 | AK60: =IF(B60="","",OR(K60="Not in use",K60="Low use")+AND(N60<>"",N60<>"TBD")+AND(ISNUMBER(U60),U60<=EDATE('Scoring Settings'!$B$4,'Scoring Settings'!$B$8))+AND(ISNUMBER(L60),L60<='Scoring Settings'!$B$7)) -> 3 | AL60: Migrate | AM60: =IF(B60="","",IF(Z60="N","Easy",IF(OR(AND(ISNUMBER(AB60),AB60>'Scoring Settings'!$B$11),AND(ISNUMBER(W60),W60>'Scoring Settings'!$B$12),AND(ISNUMBER(M60),M60<='Scoring Settings'!$B$13)),"High","Medium"))) -> Easy | AN60: Wave 1 | AO60: 44530 | AP60: In progress | AQ60: Cut-over planned for Nov-21; parallel run scheduled
A61: 59395 | B61: Regional Tax Compliance Tool v4 | C61: Tax | D61: Finance | E61: Internal | I61: 17 | J61: 44181 | K61: =IF(B61="","",IF(AND(I61="",J61=""),"Unknown",IF(OR(AND(ISNUMBER(I61),I61=0),AND(ISNUMBER(J61),J61<=EDATE('Scoring Settings'!$B$4,-'Scoring Settings'!$B$5))),"Not in use",IF(AND(ISNUMBER(I61),I61<'Scoring Settings'!$B$6),"Low use","Active")))) -> Low use | L61: 3 | M61: 2 | N61: BlackLine (planned) | O61: On-prem DC | P61: rtc-app01–04, rtc-db01 | Q61: 5 | R61: Ubuntu 20.04 | S61: MySQL 8.0 | T61: EU DC-2 | U61: 45777 | V61: Structured | W61: 13 | X61: N | Y61: 3 | Z61: N | AA61: None | AB61: 27 | AC61: Partial | AD61: Y | AE61: Partial | AF61: 70000 | AG61: 48273 | AH61: 121000 | AI61: 57000 | AJ61: =IF(AND(ISNUMBER(AH61),ISNUMBER(AI61),N(AI61)>0),AH61/AI61*12,"") -> 25.473684 | AK61: =IF(B61="","",OR(K61="Not in use",K61="Low use")+AND(N61<>"",N61<>"TBD")+AND(ISNUMBER(U61),U61<=EDATE('Scoring Settings'!$B$4,'Scoring Settings'!$B$8))+AND(ISNUMBER(L61),L61<='Scoring Settings'!$B$7)) -> 2 | AL61: Migrate | AM61: =IF(B61="","",IF(Z61="N","Easy",IF(OR(AND(ISNUMBER(AB61),AB61>'Scoring Settings'!$B$11),AND(ISNUMBER(W61),W61>'Scoring Settings'!$B$12),AND(ISNUMBER(M61),M61<='Scoring Settings'!$B$13)),"High","Medium"))) -> Easy | AN61: Wave 1 | AO61: 44377 | AP61: In progress | AQ61: Cut-over planned for Jun-21; parallel run scheduled
A62: 29248 | B62: Corporate Cash Position Reporter (FR) | C62: Treasury | D62: Finance | E62: Internal | I62: 3 | J62: 44198 | K62: =IF(B62="","",IF(AND(I62="",J62=""),"Unknown",IF(OR(AND(ISNUMBER(I62),I62=0),AND(ISNUMBER(J62),J62<=EDATE('Scoring Settings'!$B$4,-'Scoring Settings'!$B$5))),"Not in use",IF(AND(ISNUMBER(I62),I62<'Scoring Settings'!$B$6),"Low use","Active")))) -> Low use | L62: 2 | M62: 3 | O62: On-prem DC | P62: ccpapp01, ccpdb01, ccpweb01, ccpfs01 | Q62: 4 | R62: Solaris 10 | S62: Oracle 11g | T62: Plant DC | U62: 44227 | V62: Structured | W62: 1 | X62: N | Y62: 2 | Z62: N | AA62: None | AB62: 8 | AC62: N | AD62: N | AE62: N | AF62: 55000 | AG62: 46477 | AH62: 78500 | AI62: 48000 | AJ62: =IF(AND(ISNUMBER(AH62),ISNUMBER(AI62),N(AI62)>0),AH62/AI62*12,"") -> 19.625 | AK62: =IF(B62="","",OR(K62="Not in use",K62="Low use")+AND(N62<>"",N62<>"TBD")+AND(ISNUMBER(U62),U62<=EDATE('Scoring Settings'!$B$4,'Scoring Settings'!$B$8))+AND(ISNUMBER(L62),L62<='Scoring Settings'!$B$7)) -> 3 | AL62: Retire | AM62: =IF(B62="","",IF(Z62="N","Easy",IF(OR(AND(ISNUMBER(AB62),AB62>'Scoring Settings'!$B$11),AND(ISNUMBER(W62),W62>'Scoring Settings'!$B$12),AND(ISNUMBER(M62),M62<='Scoring Settings'!$B$13)),"High","Medium"))) -> Easy | AN62: Wave 1 | AO62: 44561 | AP62: Approved | AQ62: No active users; switch-off confirmed with owner
A63: 15356 | B63: Kronos | C63: Time & Attendance | D63: HR | E63: Internal | I63: 5200 | J63: 44315 | K63: =IF(B63="","",IF(AND(I63="",J63=""),"Unknown",IF(OR(AND(ISNUMBER(I63),I63=0),AND(ISNUMBER(J63),J63<=EDATE('Scoring Settings'!$B$4,-'Scoring Settings'!$B$5))),"Not in use",IF(AND(ISNUMBER(I63),I63<'Scoring Settings'!$B$6),"Low use","Active")))) -> Active | L63: 3 | M63: 2 | N63: Workday Time Tracking | O63: IaaS | P63: kronos-app01–02, kronos-db01 | Q63: 3 | R63: Windows Server 2016 | S63: SQL Server 2016 | T63: AWS eu-west-1 | U63: 46217 | V63: Structured | W63: 900 | X63: Y | Y63: 7 | Z63: Y | AA63: Archive + read-only | AB63: 18 | AC63: Y | AD63: Y | AE63: Partial | AF63: 320000 | AG63: 46477 | AH63: 210000 | AI63: 260000 | AJ63: =IF(AND(ISNUMBER(AH63),ISNUMBER(AI63),N(AI63)>0),AH63/AI63*12,"") -> 9.6923077 | AK63: =IF(B63="","",OR(K63="Not in use",K63="Low use")+AND(N63<>"",N63<>"TBD")+AND(ISNUMBER(U63),U63<=EDATE('Scoring Settings'!$B$4,'Scoring Settings'!$B$8))+AND(ISNUMBER(L63),L63<='Scoring Settings'!$B$7)) -> 1 | AL63: Migrate | AM63: =IF(B63="","",IF(Z63="N","Easy",IF(OR(AND(ISNUMBER(AB63),AB63>'Scoring Settings'!$B$11),AND(ISNUMBER(W63),W63>'Scoring Settings'!$B$12),AND(ISNUMBER(M63),M63<='Scoring Settings'!$B$13)),"High","Medium"))) -> High | AN63: Wave 1 | AO63: 44316 | AP63: Completed | AQ63: Payroll interface re-pointed to Workday; timecard history archived before switch-off (May-21)
A64: 16966 | B64: Custom Licence Manager 2010 | C64: Licence Mgmt | D64: IT | E64: Internal | I64: 10 | J64: 44224 | K64: =IF(B64="","",IF(AND(I64="",J64=""),"Unknown",IF(OR(AND(ISNUMBER(I64),I64=0),AND(ISNUMBER(J64),J64<=EDATE('Scoring Settings'!$B$4,-'Scoring Settings'!$B$5))),"Not in use",IF(AND(ISNUMBER(I64),I64<'Scoring Settings'!$B$6),"Low use","Active")))) -> Low use | L64: 2 | M64: 4 | N64: Azure Monitor (planned) | O64: On-prem DC | P64: clmapp01, clmdb01, clmweb01, clmfs01 | Q64: 4 | R64: Windows Server 2016 | S64: SQL Server 2017 | T64: Plant DC | U64: 46399 | V64: Unstructured | W64: 350 | X64: N | Y64: 2 | Z64: N | AA64: None | AB64: 3 | AC64: N | AD64: Y | AE64: Partial | AF64: 31500 | AG64: 46568 | AH64: 40000 | AI64: 26500 | AJ64: =IF(AND(ISNUMBER(AH64),ISNUMBER(AI64),N(AI64)>0),AH64/AI64*12,"") -> 18.113208 | AK64: =IF(B64="","",OR(K64="Not in use",K64="Low use")+AND(N64<>"",N64<>"TBD")+AND(ISNUMBER(U64),U64<=EDATE('Scoring Settings'!$B$4,'Scoring Settings'!$B$8))+AND(ISNUMBER(L64),L64<='Scoring Settings'!$B$7)) -> 3 | AL64: Retire | AM64: =IF(B64="","",IF(Z64="N","Easy",IF(OR(AND(ISNUMBER(AB64),AB64>'Scoring Settings'!$B$11),AND(ISNUMBER(W64),W64>'Scoring Settings'!$B$12),AND(ISNUMBER(M64),M64<='Scoring Settings'!$B$13)),"High","Medium"))) -> Easy | AN64: Wave 1 | AO64: 44439 | AP64: In progress | AQ64: Owner sign-off received; switch-off scheduled
A65: 64942 | B65: Sales Forecast Tool (UK) | C65: Sales Planning | D65: Sales | E65: Internal | I65: 187 | J65: 44297 | K65: =IF(B65="","",IF(AND(I65="",J65=""),"Unknown",IF(OR(AND(ISNUMBER(I65),I65=0),AND(ISNUMBER(J65),J65<=EDATE('Scoring Settings'!$B$4,-'Scoring Settings'!$B$5))),"Not in use",IF(AND(ISNUMBER(I65),I65<'Scoring Settings'!$B$6),"Low use","Active")))) -> Active | L65: 2 | M65: 4 | N65: Salesforce CPQ | O65: On-prem DC | P65: sftapp01, sftdb01, sftweb01, sftfs01 | Q65: 4 | R65: Windows Server 2008 R2 | S65: SQL Server 2008 R2 | T65: US DC-1 | U65: 43844 | V65: Unstructured | W65: 16 | X65: N | Y65: 7 | Z65: N | AA65: None | AB65: 3 | AC65: Y | AD65: N | AE65: N | AF65: 40500 | AG65: 47664 | AH65: 19500 | AI65: 35500 | AJ65: =IF(AND(ISNUMBER(AH65),ISNUMBER(AI65),N(AI65)>0),AH65/AI65*12,"") -> 6.5915493 | AK65: =IF(B65="","",OR(K65="Not in use",K65="Low use")+AND(N65<>"",N65<>"TBD")+AND(ISNUMBER(U65),U65<=EDATE('Scoring Settings'!$B$4,'Scoring Settings'!$B$8))+AND(ISNUMBER(L65),L65<='Scoring Settings'!$B$7)) -> 3 | AL65: Migrate | AM65: =IF(B65="","",IF(Z65="N","Easy",IF(OR(AND(ISNUMBER(AB65),AB65>'Scoring Settings'!$B$11),AND(ISNUMBER(W65),W65>'Scoring Settings'!$B$12),AND(ISNUMBER(M65),M65<='Scoring Settings'!$B$13)),"High","Medium"))) -> Easy | AN65: Wave 1 | AO65: 44500 | AP65: In progress | AQ65: Funding approved; migration to Salesforce CPQ scheduled
A66: 123642 | B66: Custom Batch Scheduler Lite | C66: Batch Scheduling | D66: IT | E66: External | I66: 25 | J66: 44312 | K66: =IF(B66="","",IF(AND(I66="",J66=""),"Unknown",IF(OR(AND(ISNUMBER(I66),I66=0),AND(ISNUMBER(J66),J66<=EDATE('Scoring Settings'!$B$4,-'Scoring Settings'!$B$5))),"Not in use",IF(AND(ISNUMBER(I66),I66<'Scoring Settings'!$B$6),"Low use","Active")))) -> Active | L66: 2 | M66: 4 | O66: PaaS | P66: Azure App Service (PaaS) | Q66: 0 | R66: N/A (PaaS) | S66: Cosmos DB | T66: Azure West Europe | V66: Structured | W66: 91 | X66: Y | Y66: 7 | Z66: Y | AA66: Data archive | AB66: 3 | AC66: Y | AD66: N | AE66: Partial | AF66: 22000 | AG66: 47452 | AH66: 31000 | AI66: 13500 | AJ66: =IF(AND(ISNUMBER(AH66),ISNUMBER(AI66),N(AI66)>0),AH66/AI66*12,"") -> 27.555556 | AK66: =IF(B66="","",OR(K66="Not in use",K66="Low use")+AND(N66<>"",N66<>"TBD")+AND(ISNUMBER(U66),U66<=EDATE('Scoring Settings'!$B$4,'Scoring Settings'!$B$8))+AND(ISNUMBER(L66),L66<='Scoring Settings'!$B$7)) -> 1 | AL66: Retire + Archive | AM66: =IF(B66="","",IF(Z66="N","Easy",IF(OR(AND(ISNUMBER(AB66),AB66>'Scoring Settings'!$B$11),AND(ISNUMBER(W66),W66>'Scoring Settings'!$B$12),AND(ISNUMBER(M66),M66<='Scoring Settings'!$B$13)),"High","Medium"))) -> Medium | AN66: Wave 1 | AO66: 44316 | AP66: Completed | AQ66: Archive load in progress; validation with data owner
A67: 81239 | B67: Departmental Supplier Portal v4 | C67: Supplier Mgmt | D67: Supply Chain | E67: Internal | I67: 6 | J67: 43782 | K67: =IF(B67="","",IF(AND(I67="",J67=""),"Unknown",IF(OR(AND(ISNUMBER(I67),I67=0),AND(ISNUMBER(J67),J67<=EDATE('Scoring Settings'!$B$4,-'Scoring Settings'!$B$5))),"Not in use",IF(AND(ISNUMBER(I67),I67<'Scoring Settings'!$B$6),"Low use","Active")))) -> Not in use | L67: 3 | M67: 3 | N67: TBD | O67: On-prem DC | P67: dspapp01 | Q67: 1 | R67: Solaris 10 | S67: Oracle 11g | T67: US DC-1 | U67: 44227 | V67: Structured | W67: 27 | X67: Y | Y67: 7 | Z67: Y | AA67: Read-only access | AB67: 6 | AC67: Partial | AD67: Partial | AE67: Y | AF67: 22000 | AG67: 46507 | AH67: 11500 | AI67: 16000 | AJ67: =IF(AND(ISNUMBER(AH67),ISNUMBER(AI67),N(AI67)>0),AH67/AI67*12,"") -> 8.625 | AK67: =IF(B67="","",OR(K67="Not in use",K67="Low use")+AND(N67<>"",N67<>"TBD")+AND(ISNUMBER(U67),U67<=EDATE('Scoring Settings'!$B$4,'Scoring Settings'!$B$8))+AND(ISNUMBER(L67),L67<='Scoring Settings'!$B$7)) -> 2 | AL67: Retire + Archive | AM67: =IF(B67="","",IF(Z67="N","Easy",IF(OR(AND(ISNUMBER(AB67),AB67>'Scoring Settings'!$B$11),AND(ISNUMBER(W67),W67>'Scoring Settings'!$B$12),AND(ISNUMBER(M67),M67<='Scoring Settings'!$B$13)),"High","Medium"))) -> High | AN67: Wave 1 | AO67: 44377 | AP67: In progress | AQ67: Archive format agreed; load scheduled before switch-off
A68: 178002 | B68: Budget Planner v3 | C68: Budgeting | D68: Finance | E68: Internal | I68: 10 | J68: 44260 | K68: =IF(B68="","",IF(AND(I68="",J68=""),"Unknown",IF(OR(AND(ISNUMBER(I68),I68=0),AND(ISNUMBER(J68),J68<=EDATE('Scoring Settings'!$B$4,-'Scoring Settings'!$B$5))),"Not in use",IF(AND(ISNUMBER(I68),I68<'Scoring Settings'!$B$6),"Low use","Active")))) -> Low use | L68: 1 | M68: 4 | O68: On-prem DC | P68: bpvapp01, bpvdb01, bpvweb01 | Q68: 3 | R68: Windows Server 2012 R2 | S68: SQL Server 2014 | T68: EU DC-2 | U68: 45482 | V68: Structured | W68: 5 | X68: Y | Y68: 10 | Z68: N | AA68: None | AB68: 1 | AC68: N | AD68: Y | AE68: Partial | AF68: 65000 | AG68: 48579 | AH68: 41000 | AI68: 59000 | AJ68: =IF(AND(ISNUMBER(AH68),ISNUMBER(AI68),N(AI68)>0),AH68/AI68*12,"") -> 8.3389831 | AK68: =IF(B68="","",OR(K68="Not in use",K68="Low use")+AND(N68<>"",N68<>"TBD")+AND(ISNUMBER(U68),U68<=EDATE('Scoring Settings'!$B$4,'Scoring Settings'!$B$8))+AND(ISNUMBER(L68),L68<='Scoring Settings'!$B$7)) -> 2 | AL68: Retire | AM68: =IF(B68="","",IF(Z68="N","Easy",IF(OR(AND(ISNUMBER(AB68),AB68>'Scoring Settings'!$B$11),AND(ISNUMBER(W68),W68>'Scoring Settings'!$B$12),AND(ISNUMBER(M68),M68<='Scoring Settings'!$B$13)),"High","Medium"))) -> Easy | AN68: Wave 1 | AO68: 44439 | AP68: In progress | AQ68: Owner sign-off received; switch-off scheduled
A69: 94745 | B69: Old Ticket Desk | C69: Service Desk | D69: IT | E69: Internal | I69: 25 | J69: 44271 | K69: =IF(B69="","",IF(AND(I69="",J69=""),"Unknown",IF(OR(AND(ISNUMBER(I69),I69=0),AND(ISNUMBER(J69),J69<=EDATE('Scoring Settings'!$B$4,-'Scoring Settings'!$B$5))),"Not in use",IF(AND(ISNUMBER(I69),I69<'Scoring Settings'!$B$6),"Low use","Active")))) -> Active | L69: 5 | M69: 2 | N69: Azure Monitor | O69: On-prem DC | P69: otdapp01, otddb01, otdweb01 | Q69: 3 | R69: Ubuntu 16.04 | S69: MySQL 5.7 | T69: Plant DC | U69: 44316 | V69: Both | W69: 10570 | X69: N | Y69: 5 | Z69: N | AA69: None | AB69: 13 | AC69: N | AD69: Partial | AE69: N | AF69: 60000 | AG69: 47603 | AH69: 103500 | AI69: 47500 | AJ69: =IF(AND(ISNUMBER(AH69),ISNUMBER(AI69),N(AI69)>0),AH69/AI69*12,"") -> 26.147368 | AK69: =IF(B69="","",OR(K69="Not in use",K69="Low use")+AND(N69<>"",N69<>"TBD")+AND(ISNUMBER(U69),U69<=EDATE('Scoring Settings'!$B$4,'Scoring Settings'!$B$8))+AND(ISNUMBER(L69),L69<='Scoring Settings'!$B$7)) -> 2 | AL69: Migrate | AM69: =IF(B69="","",IF(Z69="N","Easy",IF(OR(AND(ISNUMBER(AB69),AB69>'Scoring Settings'!$B$11),AND(ISNUMBER(W69),W69>'Scoring Settings'!$B$12),AND(ISNUMBER(M69),M69<='Scoring Settings'!$B$13)),"High","Medium"))) -> Easy | AN69: Wave 1 | AO69: 44469 | AP69: In progress | AQ69: Cut-over planned for Sep-21; parallel run scheduled
A70: 70067 | B70: Shared Travel Booking Tool v2 | C70: Travel | D70: HR | E70: Internal | I70: 20 | J70: 44198 | K70: =IF(B70="","",IF(AND(I70="",J70=""),"Unknown",IF(OR(AND(ISNUMBER(I70),I70=0),AND(ISNUMBER(J70),J70<=EDATE('Scoring Settings'!$B$4,-'Scoring Settings'!$B$5))),"Not in use",IF(AND(ISNUMBER(I70),I70<'Scoring Settings'!$B$6),"Low use","Active")))) -> Low use | L70: 3 | M70: 4 | O70: On-prem DC | P70: stbapp01, stbdb01 | Q70: 2 | R70: Windows Server 2012 R2 | S70: SQL Server 2012 | T70: Plant DC | U70: 44754 | V70: Structured | W70: 570 | X70: Y | Y70: 7 | Z70: N | AA70: None | AB70: 3 | AC70: Partial | AD70: Partial | AE70: Y | AF70: 33000 | AG70: 49125 | AH70: 44000 | AI70: 30500 | AJ70: =IF(AND(ISNUMBER(AH70),ISNUMBER(AI70),N(AI70)>0),AH70/AI70*12,"") -> 17.311475 | AK70: =IF(B70="","",OR(K70="Not in use",K70="Low use")+AND(N70<>"",N70<>"TBD")+AND(ISNUMBER(U70),U70<=EDATE('Scoring Settings'!$B$4,'Scoring Settings'!$B$8))+AND(ISNUMBER(L70),L70<='Scoring Settings'!$B$7)) -> 1 | AL70: Retire | AM70: =IF(B70="","",IF(Z70="N","Easy",IF(OR(AND(ISNUMBER(AB70),AB70>'Scoring Settings'!$B$11),AND(ISNUMBER(W70),W70>'Scoring Settings'!$B$12),AND(ISNUMBER(M70),M70<='Scoring Settings'!$B$13)),"High","Medium"))) -> Easy | AN70: Wave 1 | AO70: 44408 | AP70: In progress | AQ70: No active users; switch-off confirmed with owner
A71: 195793 | B71: Old Intranet (SharePoint) Lite | C71: Collaboration | D71: IT | E71: Internal | I71: 0 | J71: 44233 | K71: =IF(B71="","",IF(AND(I71="",J71=""),"Unknown",IF(OR(AND(ISNUMBER(I71),I71=0),AND(ISNUMBER(J71),J71<=EDATE('Scoring Settings'!$B$4,-'Scoring Settings'!$B$5))),"Not in use",IF(AND(ISNUMBER(I71),I71<'Scoring Settings'!$B$6),"Low use","Active")))) -> Not in use | L71: 2 | M71: 4 | N71: Azure Monitor | O71: On-prem DC | P71: oisapp01 | Q71: 1 | R71: HP-UX 11i v3 | S71: Sybase ASE 15.7 | T71: EU DC-1 | U71: 44561 | V71: Structured | W71: 1470 | X71: N | Y71: 3 | Z71: Y | AA71: Archive + read-only | AB71: 1 | AC71: N | AD71: Partial | AE71: Partial | AF71: 34500 | AG71: 49095 | AH71: 51000 | AI71: 19000 | AJ71: =IF(AND(ISNUMBER(AH71),ISNUMBER(AI71),N(AI71)>0),AH71/AI71*12,"") -> 32.210526 | AK71: =IF(B71="","",OR(K71="Not in use",K71="Low use")+AND(N71<>"",N71<>"TBD")+AND(ISNUMBER(U71),U71<=EDATE('Scoring Settings'!$B$4,'Scoring Settings'!$B$8))+AND(ISNUMBER(L71),L71<='Scoring Settings'!$B$7)) -> 4 | AL71: Retire + Archive | AM71: =IF(B71="","",IF(Z71="N","Easy",IF(OR(AND(ISNUMBER(AB71),AB71>'Scoring Settings'!$B$11),AND(ISNUMBER(W71),W71>'Scoring Settings'!$B$12),AND(ISNUMBER(M71),M71<='Scoring Settings'!$B$13)),"High","Medium"))) -> High | AN71: Wave 1 | AO71: 44255 | AP71: Completed | AQ71: Data archived and validated; switched off Feb-21
A72: 140270 | B72: Old Brand Asset Library Plus | C72: Digital Assets | D72: Marketing | E72: Internal | I72: 377 | J72: 44307 | K72: =IF(B72="","",IF(AND(I72="",J72=""),"Unknown",IF(OR(AND(ISNUMBER(I72),I72=0),AND(ISNUMBER(J72),J72<=EDATE('Scoring Settings'!$B$4,-'Scoring Settings'!$B$5))),"Not in use",IF(AND(ISNUMBER(I72),I72<'Scoring Settings'!$B$6),"Low use","Active")))) -> Active | L72: 3 | M72: 4 | N72: Marketo | O72: On-prem DC | P72: obaapp01, obadb01 | Q72: 2 | R72: TBD | S72: Oracle 19c | T72: US DC-1 | U72: 47269 | V72: Unstructured | W72: 65 | X72: Y | Y72: 10 | Z72: Y | AA72: Data archive | AB72: 1 | AC72: N | AD72: Partial | AE72: Y | AF72: 25000 | AG72: 47330 | AH72: 22500 | AI72: 15500 | AJ72: =IF(AND(ISNUMBER(AH72),ISNUMBER(AI72),N(AI72)>0),AH72/AI72*12,"") -> 17.419355 | AK72: =IF(B72="","",OR(K72="Not in use",K72="Low use")+AND(N72<>"",N72<>"TBD")+AND(ISNUMBER(U72),U72<=EDATE('Scoring Settings'!$B$4,'Scoring Settings'!$B$8))+AND(ISNUMBER(L72),L72<='Scoring Settings'!$B$7)) -> 1 | AL72: Migrate | AM72: =IF(B72="","",IF(Z72="N","Easy",IF(OR(AND(ISNUMBER(AB72),AB72>'Scoring Settings'!$B$11),AND(ISNUMBER(W72),W72>'Scoring Settings'!$B$12),AND(ISNUMBER(M72),M72<='Scoring Settings'!$B$13)),"High","Medium"))) -> Medium | AN72: Wave 1 | AO72: 44347 | AP72: On hold | AQ72: On hold - waiting for interface owner sign-off
A73: 16909 | B73: Custom Corporate Website CMS | C73: Web | D73: Marketing | E73: Partner | I73: 0 | J73: 44205 | K73: =IF(B73="","",IF(AND(I73="",J73=""),"Unknown",IF(OR(AND(ISNUMBER(I73),I73=0),AND(ISNUMBER(J73),J73<=EDATE('Scoring Settings'!$B$4,-'Scoring Settings'!$B$5))),"Not in use",IF(AND(ISNUMBER(I73),I73<'Scoring Settings'!$B$6),"Low use","Active")))) -> Not in use | L73: 2 | M73: 4 | O73: On-prem DC | P73: ccwapp01, ccwdb01, ccwweb01, ccwfs01 | Q73: 4 | R73: RHEL 7 | S73: Oracle 12c | T73: EU DC-1 | U73: 45473 | V73: Structured | W73: 320 | X73: Y | Y73: 5 | Z73: Y | AA73: Legal hold | AB73: 2 | AC73: Y | AD73: N | AE73: N | AF73: 55000 | AG73: 45961 | AH73: 27500 | AI73: 38500 | AJ73: =IF(AND(ISNUMBER(AH73),ISNUMBER(AI73),N(AI73)>0),AH73/AI73*12,"") -> 8.5714286 | AK73: =IF(B73="","",OR(K73="Not in use",K73="Low use")+AND(N73<>"",N73<>"TBD")+AND(ISNUMBER(U73),U73<=EDATE('Scoring Settings'!$B$4,'Scoring Settings'!$B$8))+AND(ISNUMBER(L73),L73<='Scoring Settings'!$B$7)) -> 2 | AL73: Retire + Archive | AM73: =IF(B73="","",IF(Z73="N","Easy",IF(OR(AND(ISNUMBER(AB73),AB73>'Scoring Settings'!$B$11),AND(ISNUMBER(W73),W73>'Scoring Settings'!$B$12),AND(ISNUMBER(M73),M73<='Scoring Settings'!$B$13)),"High","Medium"))) -> Medium | AN73: Wave 1 | AO73: 44227 | AP73: Completed | AQ73: Data archived and validated; switched off Jan-21
A74: 98914 | B74: Event Registration Tool v4 | C74: Events | D74: Marketing | E74: Internal | I74: 8 | J74: 44243 | K74: =IF(B74="","",IF(AND(I74="",J74=""),"Unknown",IF(OR(AND(ISNUMBER(I74),I74=0),AND(ISNUMBER(J74),J74<=EDATE('Scoring Settings'!$B$4,-'Scoring Settings'!$B$5))),"Not in use",IF(AND(ISNUMBER(I74),I74<'Scoring Settings'!$B$6),"Low use","Active")))) -> Low use | L74: 3 | M74: 3 | N74: HubSpot | O74: On-prem DC | P74: ertapp01, ertdb01, ertweb01 | Q74: 3 | R74: Windows Server 2008 R2 | S74: SQL Server 2008 R2 | T74: EU DC-1 | U74: 43844 | V74: Structured | W74: 38 | X74: N | Y74: 7 | Z74: N | AA74: None | AB74: 3 | AC74: N | AD74: Partial | AE74: Partial | AF74: 60000 | AG74: 48304 | AH74: 67500 | AI74: 55500 | AJ74: =IF(AND(ISNUMBER(AH74),ISNUMBER(AI74),N(AI74)>0),AH74/AI74*12,"") -> 14.594595 | AK74: =IF(B74="","",OR(K74="Not in use",K74="Low use")+AND(N74<>"",N74<>"TBD")+AND(ISNUMBER(U74),U74<=EDATE('Scoring Settings'!$B$4,'Scoring Settings'!$B$8))+AND(ISNUMBER(L74),L74<='Scoring Settings'!$B$7)) -> 3 | AL74: Retire | AM74: =IF(B74="","",IF(Z74="N","Easy",IF(OR(AND(ISNUMBER(AB74),AB74>'Scoring Settings'!$B$11),AND(ISNUMBER(W74),W74>'Scoring Settings'!$B$12),AND(ISNUMBER(M74),M74<='Scoring Settings'!$B$13)),"High","Medium"))) -> Easy | AN74: Wave 1 | AO74: 44500 | AP74: In progress | AQ74: No active users; switch-off confirmed with owner
A75: 31080 | B75: Custom Appraisal Tool (APAC) | C75: Performance | D75: HR | E75: Partner | I75: 0 | J75: 44239 | K75: =IF(B75="","",IF(AND(I75="",J75=""),"Unknown",IF(OR(AND(ISNUMBER(I75),I75=0),AND(ISNUMBER(J75),J75<=EDATE('Scoring Settings'!$B$4,-'Scoring Settings'!$B$5))),"Not in use",IF(AND(ISNUMBER(I75),I75<'Scoring Settings'!$B$6),"Low use","Active")))) -> Not in use | L75: 2 | M75: 3 | O75: On-prem DC | P75: catapp01, catdb01 | Q75: 2 | R75: Solaris 10 | S75: Oracle 11g | T75: EU DC-1 | U75: 44227 | V75: Structured | W75: 22 | X75: Y | Y75: 10 | Z75: Y | AA75: Archive + read-only | AB75: 8 | AC75: Partial | AD75: Partial | AE75: Partial | AF75: 21500 | AG75: 48548 | AH75: 13000 | AI75: 13500 | AJ75: =IF(AND(ISNUMBER(AH75),ISNUMBER(AI75),N(AI75)>0),AH75/AI75*12,"") -> 11.555556 | AK75: =IF(B75="","",OR(K75="Not in use",K75="Low use")+AND(N75<>"",N75<>"TBD")+AND(ISNUMBER(U75),U75<=EDATE('Scoring Settings'!$B$4,'Scoring Settings'!$B$8))+AND(ISNUMBER(L75),L75<='Scoring Settings'!$B$7)) -> 3 | AL75: Retire + Archive | AM75: =IF(B75="","",IF(Z75="N","Easy",IF(OR(AND(ISNUMBER(AB75),AB75>'Scoring Settings'!$B$11),AND(ISNUMBER(W75),W75>'Scoring Settings'!$B$12),AND(ISNUMBER(M75),M75<='Scoring Settings'!$B$13)),"High","Medium"))) -> High | AN75: Wave 1 | AO75: 44255 | AP75: Completed | AQ75: Data archived and validated; switched off Feb-21
A76: 182350 | B76: Legacy Price List Manager 2008 | C76: Pricing | D76: Sales | E76: Internal | I76: 20 | J76: 44295 | K76: =IF(B76="","",IF(AND(I76="",J76=""),"Unknown",IF(OR(AND(ISNUMBER(I76),I76=0),AND(ISNUMBER(J76),J76<=EDATE('Scoring Settings'!$B$4,-'Scoring Settings'!$B$5))),"Not in use",IF(AND(ISNUMBER(I76),I76<'Scoring Settings'!$B$6),"Low use","Active")))) -> Low use | L76: 4 | M76: 3 | O76: PaaS | P76: Azure App Service (PaaS) | Q76: 0 | R76: N/A (PaaS) | S76: Azure SQL | T76: Azure West Europe | V76: Structured | W76: 13 | X76: N | Y76: 3 | Z76: N | AA76: None | AB76: 6 | AC76: Partial | AD76: Partial | AE76: N | AF76: 12000 | AG76: 47422 | AH76: 8500 | AI76: 11000 | AJ76: =IF(AND(ISNUMBER(AH76),ISNUMBER(AI76),N(AI76)>0),AH76/AI76*12,"") -> 9.2727273 | AK76: =IF(B76="","",OR(K76="Not in use",K76="Low use")+AND(N76<>"",N76<>"TBD")+AND(ISNUMBER(U76),U76<=EDATE('Scoring Settings'!$B$4,'Scoring Settings'!$B$8))+AND(ISNUMBER(L76),L76<='Scoring Settings'!$B$7)) -> 1 | AL76: Retire | AM76: =IF(B76="","",IF(Z76="N","Easy",IF(OR(AND(ISNUMBER(AB76),AB76>'Scoring Settings'!$B$11),AND(ISNUMBER(W76),W76>'Scoring Settings'!$B$12),AND(ISNUMBER(M76),M76<='Scoring Settings'!$B$13)),"High","Medium"))) -> Easy | AN76: Wave 1 | AO76: 44408 | AP76: In progress | AQ76: Owner sign-off received; switch-off scheduled
A77: 196046 | B77: Travel Booking Tool (Nordics) | C77: Travel | D77: HR | E77: Internal | I77: 2 | J77: 43781 | K77: =IF(B77="","",IF(AND(I77="",J77=""),"Unknown",IF(OR(AND(ISNUMBER(I77),I77=0),AND(ISNUMBER(J77),J77<=EDATE('Scoring Settings'!$B$4,-'Scoring Settings'!$B$5))),"Not in use",IF(AND(ISNUMBER(I77),I77<'Scoring Settings'!$B$6),"Low use","Active")))) -> Not in use | L77: 1 | M77: 3 | O77: SaaS | P77: N/A (SaaS) | Q77: 0 | R77: N/A | S77: N/A | T77: Vendor cloud (EU) | V77: Unstructured | W77: 200 | X77: N | Y77: 3 | Z77: Y | AA77: Archive + read-only | AB77: 3 | AC77: Y | AD77: Partial | AE77: Partial | AF77: 115000 | AG77: 48487 | AH77: 79500 | AI77: 49500 | AJ77: =IF(AND(ISNUMBER(AH77),ISNUMBER(AI77),N(AI77)>0),AH77/AI77*12,"") -> 19.272727 | AK77: =IF(B77="","",OR(K77="Not in use",K77="Low use")+AND(N77<>"",N77<>"TBD")+AND(ISNUMBER(U77),U77<=EDATE('Scoring Settings'!$B$4,'Scoring Settings'!$B$8))+AND(ISNUMBER(L77),L77<='Scoring Settings'!$B$7)) -> 2 | AL77: Retire + Archive | AM77: =IF(B77="","",IF(Z77="N","Easy",IF(OR(AND(ISNUMBER(AB77),AB77>'Scoring Settings'!$B$11),AND(ISNUMBER(W77),W77>'Scoring Settings'!$B$12),AND(ISNUMBER(M77),M77<='Scoring Settings'!$B$13)),"High","Medium"))) -> Medium | AN77: Wave 1 | AO77: 44408 | AP77: In progress | AQ77: Retention 3 yrs - archive slot booked
A78: 192364 | B78: Corporate Newsletter Mailer | C78: Email | D78: Marketing | E78: Internal | I78: 0 | J78: 43642 | K78: =IF(B78="","",IF(AND(I78="",J78=""),"Unknown",IF(OR(AND(ISNUMBER(I78),I78=0),AND(ISNUMBER(J78),J78<=EDATE('Scoring Settings'!$B$4,-'Scoring Settings'!$B$5))),"Not in use",IF(AND(ISNUMBER(I78),I78<'Scoring Settings'!$B$6),"Low use","Active")))) -> Not in use | L78: 1 | M78: 4 | O78: IaaS | P78: cnmapp01, cnmdb01, cnmweb01 | Q78: 3 | R78: RHEL 8 | S78: TBD | T78: Azure West Europe | U78: 47269 | V78: Structured | W78: 12 | X78: Y | Y78: 10 | Z78: N | AA78: None | AB78: 2 | AC78: Y | AD78: Y | AE78: Y | AF78: 14500 | AG78: 49643 | AH78: 10500 | AI78: 13500 | AJ78: =IF(AND(ISNUMBER(AH78),ISNUMBER(AI78),N(AI78)>0),AH78/AI78*12,"") -> 9.3333333 | AK78: =IF(B78="","",OR(K78="Not in use",K78="Low use")+AND(N78<>"",N78<>"TBD")+AND(ISNUMBER(U78),U78<=EDATE('Scoring Settings'!$B$4,'Scoring Settings'!$B$8))+AND(ISNUMBER(L78),L78<='Scoring Settings'!$B$7)) -> 2 | AL78: Retire | AM78: =IF(B78="","",IF(Z78="N","Easy",IF(OR(AND(ISNUMBER(AB78),AB78>'Scoring Settings'!$B$11),AND(ISNUMBER(W78),W78>'Scoring Settings'!$B$12),AND(ISNUMBER(M78),M78<='Scoring Settings'!$B$13)),"High","Medium"))) -> Easy | AN78: Wave 1 | AO78: 44469 | AP78: In progress | AQ78: No active users; switch-off confirmed with owner
A79: 149711 | B79: Shared Sales Forecast Tool | C79: Sales Planning | D79: Sales | E79: Partner | I79: 0 | J79: 44227 | K79: =IF(B79="","",IF(AND(I79="",J79=""),"Unknown",IF(OR(AND(ISNUMBER(I79),I79=0),AND(ISNUMBER(J79),J79<=EDATE('Scoring Settings'!$B$4,-'Scoring Settings'!$B$5))),"Not in use",IF(AND(ISNUMBER(I79),I79<'Scoring Settings'!$B$6),"Low use","Active")))) -> Not in use | L79: 3 | M79: 3 | N79: Salesforce (planned) | O79: SaaS | P79: N/A (SaaS) | Q79: 0 | R79: N/A | S79: N/A | T79: Vendor cloud (EU) | V79: Structured | W79: 100 | X79: Y | Y79: 10 | Z79: Y | AA79: Archive + read-only | AB79: 4 | AC79: Y | AD79: Y | AE79: Partial | AF79: 48000 | AG79: 46356 | AH79: 48000 | AI79: 25000 | AJ79: =IF(AND(ISNUMBER(AH79),ISNUMBER(AI79),N(AI79)>0),AH79/AI79*12,"") -> 23.04 | AK79: =IF(B79="","",OR(K79="Not in use",K79="Low use")+AND(N79<>"",N79<>"TBD")+AND(ISNUMBER(U79),U79<=EDATE('Scoring Settings'!$B$4,'Scoring Settings'!$B$8))+AND(ISNUMBER(L79),L79<='Scoring Settings'!$B$7)) -> 2 | AL79: Retire + Archive | AM79: =IF(B79="","",IF(Z79="N","Easy",IF(OR(AND(ISNUMBER(AB79),AB79>'Scoring Settings'!$B$11),AND(ISNUMBER(W79),W79>'Scoring Settings'!$B$12),AND(ISNUMBER(M79),M79<='Scoring Settings'!$B$13)),"High","Medium"))) -> Medium | AN79: Wave 1 | AO79: 44439 | AP79: In progress | AQ79: Read-only access needed for audit
A80: 154871 | B80: Corporate Corporate Website CMS (DE) | C80: Web | D80: Marketing | E80: Internal | I80: 1103 | J80: 44283 | K80: =IF(B80="","",IF(AND(I80="",J80=""),"Unknown",IF(OR(AND(ISNUMBER(I80),I80=0),AND(ISNUMBER(J80),J80<=EDATE('Scoring Settings'!$B$4,-'Scoring Settings'!$B$5))),"Not in use",IF(AND(ISNUMBER(I80),I80<'Scoring Settings'!$B$6),"Low use","Active")))) -> Active | L80: 3 | M80: 2 | N80: Adobe Campaign | O80: On-prem DC | P80: ccw-app01–05, ccw-db01 | Q80: 6 | R80: Windows Server 2019 | S80: SQL Server 2019 | T80: EU DC-1 | U80: 47127 | V80: Structured | W80: 1490 | X80: Y | Y80: 7 | Z80: N | AA80: None | AB80: 18 | AC80: N | AD80: N | AE80: Y | AF80: 135000 | AG80: 47634 | AH80: 188000 | AI80: 112000 | AJ80: =IF(AND(ISNUMBER(AH80),ISNUMBER(AI80),N(AI80)>0),AH80/AI80*12,"") -> 20.142857 | AK80: =IF(B80="","",OR(K80="Not in use",K80="Low use")+AND(N80<>"",N80<>"TBD")+AND(ISNUMBER(U80),U80<=EDATE('Scoring Settings'!$B$4,'Scoring Settings'!$B$8))+AND(ISNUMBER(L80),L80<='Scoring Settings'!$B$7)) -> 1 | AL80: Retire | AM80: =IF(B80="","",IF(Z80="N","Easy",IF(OR(AND(ISNUMBER(AB80),AB80>'Scoring Settings'!$B$11),AND(ISNUMBER(W80),W80>'Scoring Settings'!$B$12),AND(ISNUMBER(M80),M80<='Scoring Settings'!$B$13)),"High","Medium"))) -> Easy | AN80: Wave 1 | AO80: 44316 | AP80: Completed | AQ80: Functionality covered by existing tools
A81: 141151 | B81: Global Leave Manager v2 | C81: Leave Mgmt | D81: HR | E81: Internal | I81: 0 | J81: 43709 | K81: =IF(B81="","",IF(AND(I81="",J81=""),"Unknown",IF(OR(AND(ISNUMBER(I81),I81=0),AND(ISNUMBER(J81),J81<=EDATE('Scoring Settings'!$B$4,-'Scoring Settings'!$B$5))),"Not in use",IF(AND(ISNUMBER(I81),I81<'Scoring Settings'!$B$6),"Low use","Active")))) -> Not in use | L81: 3 | M81: 3 | O81: On-prem DC | P81: glmapp01, glmdb01 | Q81: 2 | R81: SUSE Linux 11 | S81: Oracle 11g | T81: EU DC-2 | U81: 43555 | V81: Structured | W81: 220 | X81: Y | Y81: 10 | Z81: N | AA81: None | AB81: 7 | AC81: N | AD81: N | AE81: N | AF81: 48000 | AG81: 46203 | AH81: 28500 | AI81: 45000 | AJ81: =IF(AND(ISNUMBER(AH81),ISNUMBER(AI81),N(AI81)>0),AH81/AI81*12,"") -> 7.6 | AK81: =IF(B81="","",OR(K81="Not in use",K81="Low use")+AND(N81<>"",N81<>"TBD")+AND(ISNUMBER(U81),U81<=EDATE('Scoring Settings'!$B$4,'Scoring Settings'!$B$8))+AND(ISNUMBER(L81),L81<='Scoring Settings'!$B$7)) -> 2 | AL81: Retire | AM81: =IF(B81="","",IF(Z81="N","Easy",IF(OR(AND(ISNUMBER(AB81),AB81>'Scoring Settings'!$B$11),AND(ISNUMBER(W81),W81>'Scoring Settings'!$B$12),AND(ISNUMBER(M81),M81<='Scoring Settings'!$B$13)),"High","Medium"))) -> Easy | AN81: Wave 1 | AO81: 44500 | AP81: In progress | AQ81: Owner sign-off received; switch-off scheduled
A82: 63796 | B82: Global Licence Manager v2 | C82: Licence Mgmt | D82: IT | E82: Internal | I82: 13 | J82: 44204 | K82: =IF(B82="","",IF(AND(I82="",J82=""),"Unknown",IF(OR(AND(ISNUMBER(I82),I82=0),AND(ISNUMBER(J82),J82<=EDATE('Scoring Settings'!$B$4,-'Scoring Settings'!$B$5))),"Not in use",IF(AND(ISNUMBER(I82),I82<'Scoring Settings'!$B$6),"Low use","Active")))) -> Low use | L82: 1 | M82: 4 | O82: SaaS | P82: N/A (SaaS) | Q82: 0 | R82: N/A | S82: N/A | T82: Vendor cloud (EU) | U82: 46053 | V82: Unstructured | W82: 14 | X82: N | Y82: 5 | Z82: N | AA82: None | AB82: 2 | AC82: Partial | AD82: N | AE82: Y | AF82: 100000 | AG82: 47999 | AH82: 118500 | AI82: 58500 | AJ82: =IF(AND(ISNUMBER(AH82),ISNUMBER(AI82),N(AI82)>0),AH82/AI82*12,"") -> 24.307692 | AK82: =IF(B82="","",OR(K82="Not in use",K82="Low use")+AND(N82<>"",N82<>"TBD")+AND(ISNUMBER(U82),U82<=EDATE('Scoring Settings'!$B$4,'Scoring Settings'!$B$8))+AND(ISNUMBER(L82),L82<='Scoring Settings'!$B$7)) -> 2 | AL82: Retire | AM82: =IF(B82="","",IF(Z82="N","Easy",IF(OR(AND(ISNUMBER(AB82),AB82>'Scoring Settings'!$B$11),AND(ISNUMBER(W82),W82>'Scoring Settings'!$B$12),AND(ISNUMBER(M82),M82<='Scoring Settings'!$B$13)),"High","Medium"))) -> Easy | AN82: Wave 1 | AO82: 44469 | AP82: In progress | AQ82: Functionality covered by existing tools
A83: 185493 | B83: Access Request Tool 2012 | C83: Identity | D83: IT | E83: Internal | I83: 62 | J83: 44297 | K83: =IF(B83="","",IF(AND(I83="",J83=""),"Unknown",IF(OR(AND(ISNUMBER(I83),I83=0),AND(ISNUMBER(J83),J83<=EDATE('Scoring Settings'!$B$4,-'Scoring Settings'!$B$5))),"Not in use",IF(AND(ISNUMBER(I83),I83<'Scoring Settings'!$B$6),"Low use","Active")))) -> Active | L83: 5 | M83: 1 | N83: SharePoint Online | O83: On-prem DC | P83: artapp01, artdb01, artweb01, artfs01 | Q83: 4 | R83: Windows Server 2016 | S83: SQL Server 2017 | T83: Plant DC | U83: 46399 | V83: Both | W83: 62 | X83: N | Y83: 3 | Z83: N | AA83: None | AB83: 76 | AC83: Y | AD83: N | AE83: Partial | AF83: 125000 | AG83: 47118 | AH83: 208500 | AI83: 108000 | AJ83: =IF(AND(ISNUMBER(AH83),ISNUMBER(AI83),N(AI83)>0),AH83/AI83*12,"") -> 23.166667 | AK83: =IF(B83="","",OR(K83="Not in use",K83="Low use")+AND(N83<>"",N83<>"TBD")+AND(ISNUMBER(U83),U83<=EDATE('Scoring Settings'!$B$4,'Scoring Settings'!$B$8))+AND(ISNUMBER(L83),L83<='Scoring Settings'!$B$7)) -> 1 | AL83: Migrate | AM83: =IF(B83="","",IF(Z83="N","Easy",IF(OR(AND(ISNUMBER(AB83),AB83>'Scoring Settings'!$B$11),AND(ISNUMBER(W83),W83>'Scoring Settings'!$B$12),AND(ISNUMBER(M83),M83<='Scoring Settings'!$B$13)),"High","Medium"))) -> Easy | AN83: Wave 1 | AO83: 44439 | AP83: In progress | AQ83: 4 feeds to re-point to SharePoint Online
A84: 16283 | B84: Departmental Access Request Tool Classic | C84: Identity | D84: IT | E84: Partner | I84: 7 | J84: 44181 | K84: =IF(B84="","",IF(AND(I84="",J84=""),"Unknown",IF(OR(AND(ISNUMBER(I84),I84=0),AND(ISNUMBER(J84),J84<=EDATE('Scoring Settings'!$B$4,-'Scoring Settings'!$B$5))),"Not in use",IF(AND(ISNUMBER(I84),I84<'Scoring Settings'!$B$6),"Low use","Active")))) -> Low use | L84: 1 | M84: 3 | O84: On-prem DC | P84: darapp01, dardb01, darweb01, darfs01 | Q84: 4 | R84: RHEL 8 | S84: PostgreSQL 12 | T84: Plant DC | U84: 47269 | V84: Structured | W84: 340 | X84: Y | Y84: 10 | Z84: Y | AA84: Archive + read-only | AB84: 2 | AC84: Partial | AD84: Partial | AE84: Partial | AF84: 47000 | AG84: 46418 | AH84: 28500 | AI84: 34000 | AJ84: =IF(AND(ISNUMBER(AH84),ISNUMBER(AI84),N(AI84)>0),AH84/AI84*12,"") -> 10.058824 | AK84: =IF(B84="","",OR(K84="Not in use",K84="Low use")+AND(N84<>"",N84<>"TBD")+AND(ISNUMBER(U84),U84<=EDATE('Scoring Settings'!$B$4,'Scoring Settings'!$B$8))+AND(ISNUMBER(L84),L84<='Scoring Settings'!$B$7)) -> 2 | AL84: Retire + Archive | AM84: =IF(B84="","",IF(Z84="N","Easy",IF(OR(AND(ISNUMBER(AB84),AB84>'Scoring Settings'!$B$11),AND(ISNUMBER(W84),W84>'Scoring Settings'!$B$12),AND(ISNUMBER(M84),M84<='Scoring Settings'!$B$13)),"High","Medium"))) -> Medium | AN84: Wave 1 | AO84: 44500 | AP84: In progress | AQ84: Read-only access needed for audit
A85: 32809 | B85: Departmental Production Scheduler Plus | C85: Production Planning | D85: Operations | E85: Internal | I85: 0 | J85: 43749 | K85: =IF(B85="","",IF(AND(I85="",J85=""),"Unknown",IF(OR(AND(ISNUMBER(I85),I85=0),AND(ISNUMBER(J85),J85<=EDATE('Scoring Settings'!$B$4,-'Scoring Settings'!$B$5))),"Not in use",IF(AND(ISNUMBER(I85),I85<'Scoring Settings'!$B$6),"Low use","Active")))) -> Not in use | L85: 1 | M85: 3 | N85: ServiceMax | O85: On-prem DC | P85: dpsapp01, dpsdb01, dpsweb01 | Q85: 3 | R85: RHEL 6 | S85: Oracle 11g | T85: EU DC-2 | U85: 44165 | V85: Structured | W85: 74 | X85: N | Y85: 7 | Z85: N | AA85: None | AB85: 4 | AC85: Y | AD85: Partial | AE85: Partial | AF85: 44000 | AG85: 49125 | AH85: 21000 | AI85: 38500 | AJ85: =IF(AND(ISNUMBER(AH85),ISNUMBER(AI85),N(AI85)>0),AH85/AI85*12,"") -> 6.5454545 | AK85: =IF(B85="","",OR(K85="Not in use",K85="Low use")+AND(N85<>"",N85<>"TBD")+AND(ISNUMBER(U85),U85<=EDATE('Scoring Settings'!$B$4,'Scoring Settings'!$B$8))+AND(ISNUMBER(L85),L85<='Scoring Settings'!$B$7)) -> 4 | AL85: Retire | AM85: =IF(B85="","",IF(Z85="N","Easy",IF(OR(AND(ISNUMBER(AB85),AB85>'Scoring Settings'!$B$11),AND(ISNUMBER(W85),W85>'Scoring Settings'!$B$12),AND(ISNUMBER(M85),M85<='Scoring Settings'!$B$13)),"High","Medium"))) -> Easy | AN85: Wave 1 | AO85: 44316 | AP85: Completed | AQ85: User comms sent; switch-off scheduled for end of May
A86: 111703 | B86: Maintenance Scheduler v2 | C86: Asset Maintenance | D86: Operations | E86: Internal | I86: 496 | J86: 44276 | K86: =IF(B86="","",IF(AND(I86="",J86=""),"Unknown",IF(OR(AND(ISNUMBER(I86),I86=0),AND(ISNUMBER(J86),J86<=EDATE('Scoring Settings'!$B$4,-'Scoring Settings'!$B$5))),"Not in use",IF(AND(ISNUMBER(I86),I86<'Scoring Settings'!$B$6),"Low use","Active")))) -> Active | L86: 1 | M86: 3 | N86: ServiceMax | O86: On-prem DC | P86: msvapp01, msvdb01, msvweb01 | Q86: 3 | R86: Windows Server 2012 R2 | S86: SQL Server 2014 | T86: TBD | U86: 45482 | V86: Structured | W86: 31 | X86: Y | Y86: 7 | Z86: N | AA86: None | AB86: 4 | AC86: N | AD86: Partial | AE86: Partial | AF86: 60000 | AG86: 47330 | AH86: 67000 | AI86: 53000 | AJ86: =IF(AND(ISNUMBER(AH86),ISNUMBER(AI86),N(AI86)>0),AH86/AI86*12,"") -> 15.169811 | AK86: =IF(B86="","",OR(K86="Not in use",K86="Low use")+AND(N86<>"",N86<>"TBD")+AND(ISNUMBER(U86),U86<=EDATE('Scoring Settings'!$B$4,'Scoring Settings'!$B$8))+AND(ISNUMBER(L86),L86<='Scoring Settings'!$B$7)) -> 2 | AL86: Migrate | AM86: =IF(B86="","",IF(Z86="N","Easy",IF(OR(AND(ISNUMBER(AB86),AB86>'Scoring Settings'!$B$11),AND(ISNUMBER(W86),W86>'Scoring Settings'!$B$12),AND(ISNUMBER(M86),M86<='Scoring Settings'!$B$13)),"High","Medium"))) -> Easy | AN86: Wave 1 | AO86: 44561 | AP86: Approved | AQ86: Cut-over planned for Dec-21; parallel run scheduled
A87: 55298 | B87: Regional Supplier Portal Classic | C87: Supplier Mgmt | D87: Supply Chain | E87: Internal | I87: 213 | J87: 44302 | K87: =IF(B87="","",IF(AND(I87="",J87=""),"Unknown",IF(OR(AND(ISNUMBER(I87),I87=0),AND(ISNUMBER(J87),J87<=EDATE('Scoring Settings'!$B$4,-'Scoring Settings'!$B$5))),"Not in use",IF(AND(ISNUMBER(I87),I87<'Scoring Settings'!$B$6),"Low use","Active")))) -> Active | L87: 3 | M87: 4 | N87: Ariba | O87: SaaS | P87: N/A (SaaS) | Q87: 0 | R87: N/A | S87: N/A | T87: Vendor cloud (EU) | V87: Structured | W87: 460 | X87: Y | Y87: 10 | Z87: Y | AA87: Read-only access | AB87: 1 | AC87: Partial | AD87: N | AE87: Y | AF87: 80000 | AG87: 48487 | AH87: 126500 | AI87: 33000 | AJ87: =IF(AND(ISNUMBER(AH87),ISNUMBER(AI87),N(AI87)>0),AH87/AI87*12,"") -> 46 | AK87: =IF(B87="","",OR(K87="Not in use",K87="Low use")+AND(N87<>"",N87<>"TBD")+AND(ISNUMBER(U87),U87<=EDATE('Scoring Settings'!$B$4,'Scoring Settings'!$B$8))+AND(ISNUMBER(L87),L87<='Scoring Settings'!$B$7)) -> 1 | AL87: Migrate | AM87: =IF(B87="","",IF(Z87="N","Easy",IF(OR(AND(ISNUMBER(AB87),AB87>'Scoring Settings'!$B$11),AND(ISNUMBER(W87),W87>'Scoring Settings'!$B$12),AND(ISNUMBER(M87),M87<='Scoring Settings'!$B$13)),"High","Medium"))) -> Medium | AN87: Wave 1 | AO87: 44347 | AP87: Completed | AQ87: Migration to Ariba 55% complete; cut-over by end of May
A88: 195665 | B88: Fleet Manager 2008 | C88: Fleet | D88: Operations | E88: Internal | I88: 0 | J88: 44298 | K88: =IF(B88="","",IF(AND(I88="",J88=""),"Unknown",IF(OR(AND(ISNUMBER(I88),I88=0),AND(ISNUMBER(J88),J88<=EDATE('Scoring Settings'!$B$4,-'Scoring Settings'!$B$5))),"Not in use",IF(AND(ISNUMBER(I88),I88<'Scoring Settings'!$B$6),"Low use","Active")))) -> Not in use | L88: 2 | M88: 4 | N88: IBM Maximo | O88: On-prem DC | P88: fmxapp01, fmxdb01 | Q88: 2 | R88: Windows Server 2012 R2 | S88: SQL Server 2014 | T88: EU DC-1 | U88: 45482 | V88: Structured | W88: 13 | X88: N | Y88: 1 | Z88: N | AA88: None | AB88: 2 | AC88: Partial | AD88: N | AE88: N | AF88: 41500 | AG88: 49613 | AH88: 31500 | AI88: 34000 | AJ88: =IF(AND(ISNUMBER(AH88),ISNUMBER(AI88),N(AI88)>0),AH88/AI88*12,"") -> 11.117647 | AK88: =IF(B88="","",OR(K88="Not in use",K88="Low use")+AND(N88<>"",N88<>"TBD")+AND(ISNUMBER(U88),U88<=EDATE('Scoring Settings'!$B$4,'Scoring Settings'!$B$8))+AND(ISNUMBER(L88),L88<='Scoring Settings'!$B$7)) -> 3 | AL88: Retire | AM88: =IF(B88="","",IF(Z88="N","Easy",IF(OR(AND(ISNUMBER(AB88),AB88>'Scoring Settings'!$B$11),AND(ISNUMBER(W88),W88>'Scoring Settings'!$B$12),AND(ISNUMBER(M88),M88<='Scoring Settings'!$B$13)),"High","Medium"))) -> Easy | AN88: Wave 1 | AO88: 44316 | AP88: Completed | AQ88: Switched off Apr-21; licence terminated
A89: 54573 | B89: Legacy Cash Position Reporter | C89: Treasury | D89: Finance | E89: External | I89: 1 | J89: 43819 | K89: =IF(B89="","",IF(AND(I89="",J89=""),"Unknown",IF(OR(AND(ISNUMBER(I89),I89=0),AND(ISNUMBER(J89),J89<=EDATE('Scoring Settings'!$B$4,-'Scoring Settings'!$B$5))),"Not in use",IF(AND(ISNUMBER(I89),I89<'Scoring Settings'!$B$6),"Low use","Active")))) -> Not in use | L89: 1 | M89: 4 | O89: On-prem DC | P89: lcpapp01, lcpdb01 | Q89: 2 | R89: RHEL 6 | S89: Oracle 11g | T89: TBD | U89: 44165 | V89: Structured | W89: 170 | X89: Y | Y89: 7 | Z89: Y | AA89: Read-only access | AB89: 3 | AC89: N | AD89: Y | AE89: N | AF89: 25500 | AG89: 49187 | AH89: 36000 | AI89: 17000 | AJ89: =IF(AND(ISNUMBER(AH89),ISNUMBER(AI89),N(AI89)>0),AH89/AI89*12,"") -> 25.411765 | AK89: =IF(B89="","",OR(K89="Not in use",K89="Low use")+AND(N89<>"",N89<>"TBD")+AND(ISNUMBER(U89),U89<=EDATE('Scoring Settings'!$B$4,'Scoring Settings'!$B$8))+AND(ISNUMBER(L89),L89<='Scoring Settings'!$B$7)) -> 3 | AL89: Retire + Archive | AM89: =IF(B89="","",IF(Z89="N","Easy",IF(OR(AND(ISNUMBER(AB89),AB89>'Scoring Settings'!$B$11),AND(ISNUMBER(W89),W89>'Scoring Settings'!$B$12),AND(ISNUMBER(M89),M89<='Scoring Settings'!$B$13)),"High","Medium"))) -> Medium | AN89: Wave 1 | AO89: 44347 | AP89: Completed | AQ89: Archive load in progress; validation with data owner
A90: 92127 | B90: Old Monitoring Console (DE) | C90: Monitoring | D90: IT | E90: External | I90: 0 | J90: 44275 | K90: =IF(B90="","",IF(AND(I90="",J90=""),"Unknown",IF(OR(AND(ISNUMBER(I90),I90=0),AND(ISNUMBER(J90),J90<=EDATE('Scoring Settings'!$B$4,-'Scoring Settings'!$B$5))),"Not in use",IF(AND(ISNUMBER(I90),I90<'Scoring Settings'!$B$6),"Low use","Active")))) -> Not in use | L90: 3 | M90: 2 | O90: On-prem DC | P90: omc-app01–04, omc-db01 | Q90: 5 | R90: Windows Server 2016 | S90: SQL Server 2016 | T90: TBD | U90: 46217 | V90: Structured | W90: 310 | X90: N | Y90: 5 | Z90: N | AA90: None | AB90: 5 | AC90: N | AD90: Partial | AE90: N | AF90: 85000 | AG90: 47848 | AH90: 113500 | AI90: 70000 | AJ90: =IF(AND(ISNUMBER(AH90),ISNUMBER(AI90),N(AI90)>0),AH90/AI90*12,"") -> 19.457143 | AK90: =IF(B90="","",OR(K90="Not in use",K90="Low use")+AND(N90<>"",N90<>"TBD")+AND(ISNUMBER(U90),U90<=EDATE('Scoring Settings'!$B$4,'Scoring Settings'!$B$8))+AND(ISNUMBER(L90),L90<='Scoring Settings'!$B$7)) -> 1 | AL90: Retire | AM90: =IF(B90="","",IF(Z90="N","Easy",IF(OR(AND(ISNUMBER(AB90),AB90>'Scoring Settings'!$B$11),AND(ISNUMBER(W90),W90>'Scoring Settings'!$B$12),AND(ISNUMBER(M90),M90<='Scoring Settings'!$B$13)),"High","Medium"))) -> Easy | AN90: Wave 1 | AO90: 44286 | AP90: Completed | AQ90: Switched off Mar-21; licence terminated
A91: 91481 | B91: Global Newsletter Mailer (Nordics) | C91: Email | D91: Marketing | E91: Internal | I91: 139 | J91: 44315 | K91: =IF(B91="","",IF(AND(I91="",J91=""),"Unknown",IF(OR(AND(ISNUMBER(I91),I91=0),AND(ISNUMBER(J91),J91<=EDATE('Scoring Settings'!$B$4,-'Scoring Settings'!$B$5))),"Not in use",IF(AND(ISNUMBER(I91),I91<'Scoring Settings'!$B$6),"Low use","Active")))) -> Active | L91: 2 | M91: 3 | N91: HubSpot | O91: On-prem DC | P91: gnmapp01, gnmdb01, gnmweb01, gnmfs01 | Q91: 4 | R91: Ubuntu 16.04 | S91: MySQL 5.7 | T91: EU DC-1 | U91: 44316 | V91: Structured | W91: 2370 | X91: Y | Y91: 7 | Z91: N | AA91: None | AB91: 2 | AC91: Partial | AD91: N | AE91: N | AF91: 55000 | AG91: 45900 | AH91: 51500 | AI91: 44500 | AJ91: =IF(AND(ISNUMBER(AH91),ISNUMBER(AI91),N(AI91)>0),AH91/AI91*12,"") -> 13.88764 | AK91: =IF(B91="","",OR(K91="Not in use",K91="Low use")+AND(N91<>"",N91<>"TBD")+AND(ISNUMBER(U91),U91<=EDATE('Scoring Settings'!$B$4,'Scoring Settings'!$B$8))+AND(ISNUMBER(L91),L91<='Scoring Settings'!$B$7)) -> 3 | AL91: Migrate | AM91: =IF(B91="","",IF(Z91="N","Easy",IF(OR(AND(ISNUMBER(AB91),AB91>'Scoring Settings'!$B$11),AND(ISNUMBER(W91),W91>'Scoring Settings'!$B$12),AND(ISNUMBER(M91),M91<='Scoring Settings'!$B$13)),"High","Medium"))) -> Easy | AN91: Wave 1 | AO91: 44347 | AP91: Completed | AQ91: Migration to HubSpot 85% complete; cut-over by end of May
A92: 117522 | B92: Regional Web Analytics Mart 2008 | C92: Analytics | D92: Marketing | E92: Internal | I92: 0 | J92: 44304 | K92: =IF(B92="","",IF(AND(I92="",J92=""),"Unknown",IF(OR(AND(ISNUMBER(I92),I92=0),AND(ISNUMBER(J92),J92<=EDATE('Scoring Settings'!$B$4,-'Scoring Settings'!$B$5))),"Not in use",IF(AND(ISNUMBER(I92),I92<'Scoring Settings'!$B$6),"Low use","Active")))) -> Not in use | L92: 1 | M92: 3 | O92: On-prem DC | P92: rwaapp01, rwadb01 | Q92: 2 | R92: RHEL 6 | S92: Oracle 11g | T92: TBD | U92: 44165 | V92: Structured | W92: 54 | X92: N | Y92: 3 | Z92: N | AA92: None | AB92: 5 | AC92: Partial | AD92: Y | AE92: Partial | AF92: 37500 | AG92: 46812 | AH92: 42000 | AI92: 36000 | AJ92: =IF(AND(ISNUMBER(AH92),ISNUMBER(AI92),N(AI92)>0),AH92/AI92*12,"") -> 14 | AK92: =IF(B92="","",OR(K92="Not in use",K92="Low use")+AND(N92<>"",N92<>"TBD")+AND(ISNUMBER(U92),U92<=EDATE('Scoring Settings'!$B$4,'Scoring Settings'!$B$8))+AND(ISNUMBER(L92),L92<='Scoring Settings'!$B$7)) -> 3 | AL92: Retire | AM92: =IF(B92="","",IF(Z92="N","Easy",IF(OR(AND(ISNUMBER(AB92),AB92>'Scoring Settings'!$B$11),AND(ISNUMBER(W92),W92>'Scoring Settings'!$B$12),AND(ISNUMBER(M92),M92<='Scoring Settings'!$B$13)),"High","Medium"))) -> Easy | AN92: Wave 1 | AO92: 44316 | AP92: Completed | AQ92: Switched off Apr-21; licence terminated
A93: 64349 | B93: Custom Fleet Manager 2012 | C93: Fleet | D93: Operations | E93: Internal | I93: 234 | J93: 44307 | K93: =IF(B93="","",IF(AND(I93="",J93=""),"Unknown",IF(OR(AND(ISNUMBER(I93),I93=0),AND(ISNUMBER(J93),J93<=EDATE('Scoring Settings'!$B$4,-'Scoring Settings'!$B$5))),"Not in use",IF(AND(ISNUMBER(I93),I93<'Scoring Settings'!$B$6),"Low use","Active")))) -> Active | L93: 1 | M93: 3 | N93: Fiix | O93: On-prem DC | P93: cfmapp01 | Q93: 1 | R93: Windows Server 2016 | S93: SQL Server 2017 | T93: US DC-1 | U93: 46399 | V93: Structured | W93: 66 | X93: N | Y93: 2 | Z93: N | AA93: None | AB93: 2 | AC93: Partial | AD93: N | AE93: Y | AF93: 20000 | AG93: 47483 | AH93: 16500 | AI93: 16500 | AJ93: =IF(AND(ISNUMBER(AH93),ISNUMBER(AI93),N(AI93)>0),AH93/AI93*12,"") -> 12 | AK93: =IF(B93="","",OR(K93="Not in use",K93="Low use")+AND(N93<>"",N93<>"TBD")+AND(ISNUMBER(U93),U93<=EDATE('Scoring Settings'!$B$4,'Scoring Settings'!$B$8))+AND(ISNUMBER(L93),L93<='Scoring Settings'!$B$7)) -> 2 | AL93: Retire | AM93: =IF(B93="","",IF(Z93="N","Easy",IF(OR(AND(ISNUMBER(AB93),AB93>'Scoring Settings'!$B$11),AND(ISNUMBER(W93),W93>'Scoring Settings'!$B$12),AND(ISNUMBER(M93),M93<='Scoring Settings'!$B$13)),"High","Medium"))) -> Easy | AN93: Wave 1 | AO93: 44561 | AP93: Approved | AQ93: Owner sign-off received; switch-off scheduled
A94: 143983 | B94: Contract Repository | C94: Contract Mgmt | D94: Finance | E94: Internal | I94: 0 | J94: 44302 | K94: =IF(B94="","",IF(AND(I94="",J94=""),"Unknown",IF(OR(AND(ISNUMBER(I94),I94=0),AND(ISNUMBER(J94),J94<=EDATE('Scoring Settings'!$B$4,-'Scoring Settings'!$B$5))),"Not in use",IF(AND(ISNUMBER(I94),I94<'Scoring Settings'!$B$6),"Low use","Active")))) -> Not in use | L94: 2 | M94: 4 | N94: SAP Concur | O94: On-prem DC | P94: crxapp01, crxdb01, crxweb01, crxfs01 | Q94: 4 | R94: RHEL 6 | S94: Oracle 11g | T94: TBD | U94: 44165 | V94: Structured | W94: 160 | X94: Y | Y94: 10 | Z94: Y | AA94: Reporting extract | AB94: 2 | AC94: N | AD94: Partial | AE94: Partial | AF94: 46000 | AG94: 49278 | AH94: 30000 | AI94: 36500 | AJ94: =IF(AND(ISNUMBER(AH94),ISNUMBER(AI94),N(AI94)>0),AH94/AI94*12,"") -> 9.8630137 | AK94: =IF(B94="","",OR(K94="Not in use",K94="Low use")+AND(N94<>"",N94<>"TBD")+AND(ISNUMBER(U94),U94<=EDATE('Scoring Settings'!$B$4,'Scoring Settings'!$B$8))+AND(ISNUMBER(L94),L94<='Scoring Settings'!$B$7)) -> 4 | AL94: Migrate | AM94: =IF(B94="","",IF(Z94="N","Easy",IF(OR(AND(ISNUMBER(AB94),AB94>'Scoring Settings'!$B$11),AND(ISNUMBER(W94),W94>'Scoring Settings'!$B$12),AND(ISNUMBER(M94),M94<='Scoring Settings'!$B$13)),"High","Medium"))) -> Medium | AN94: Wave 1 | AO94: 44316 | AP94: Completed | AQ94: Migrated to SAP Concur; legacy switched off Apr-21
A95: 148488 | B95: Custom Leave Manager (FR) | C95: Leave Mgmt | D95: HR | E95: Internal | I95: 0 | J95: 43795 | K95: =IF(B95="","",IF(AND(I95="",J95=""),"Unknown",IF(OR(AND(ISNUMBER(I95),I95=0),AND(ISNUMBER(J95),J95<=EDATE('Scoring Settings'!$B$4,-'Scoring Settings'!$B$5))),"Not in use",IF(AND(ISNUMBER(I95),I95<'Scoring Settings'!$B$6),"Low use","Active")))) -> Not in use | L95: 2 | M95: 3 | O95: On-prem DC | P95: clmapp01, clmdb01, clmweb01 | Q95: 3 | R95: Windows Server 2016 | S95: SQL Server 2016 | T95: Plant DC | U95: 46217 | V95: Structured | W95: 1440 | X95: Y | Y95: 10 | Z95: Y | AA95: Legal hold | AB95: 1 | AC95: Y | AD95: N | AE95: Partial | AF95: 40500 | AG95: 47514 | AH95: 46500 | AI95: 21000 | AJ95: =IF(AND(ISNUMBER(AH95),ISNUMBER(AI95),N(AI95)>0),AH95/AI95*12,"") -> 26.571429 | AK95: =IF(B95="","",OR(K95="Not in use",K95="Low use")+AND(N95<>"",N95<>"TBD")+AND(ISNUMBER(U95),U95<=EDATE('Scoring Settings'!$B$4,'Scoring Settings'!$B$8))+AND(ISNUMBER(L95),L95<='Scoring Settings'!$B$7)) -> 2 | AL95: Retire + Archive | AM95: =IF(B95="","",IF(Z95="N","Easy",IF(OR(AND(ISNUMBER(AB95),AB95>'Scoring Settings'!$B$11),AND(ISNUMBER(W95),W95>'Scoring Settings'!$B$12),AND(ISNUMBER(M95),M95<='Scoring Settings'!$B$13)),"High","Medium"))) -> High | AN95: Wave 1 | AO95: 44316 | AP95: Completed | AQ95: Archive format agreed; load scheduled before switch-off
A96: 108871 | B96: Regional Customer Contact Manager | C96: CRM | D96: Sales | E96: Internal | I96: 0 | J96: 44100 | K96: =IF(B96="","",IF(AND(I96="",J96=""),"Unknown",IF(OR(AND(ISNUMBER(I96),I96=0),AND(ISNUMBER(J96),J96<=EDATE('Scoring Settings'!$B$4,-'Scoring Settings'!$B$5))),"Not in use",IF(AND(ISNUMBER(I96),I96<'Scoring Settings'!$B$6),"Low use","Active")))) -> Not in use | L96: 1 | M96: 3 | O96: IaaS | P96: rccapp01, rccdb01, rccweb01, rccfs01 | Q96: 4 | R96: AIX 6.1 | S96: DB2 9.7 | T96: AWS us-east-1 | U96: 42855 | V96: Unstructured | W96: 40 | X96: N | Y96: 2 | Z96: N | AA96: None | AB96: 1 | AC96: Partial | AD96: Partial | AE96: Partial | AF96: 30000 | AG96: 45930 | AH96: 15500 | AI96: 26500 | AJ96: =IF(AND(ISNUMBER(AH96),ISNUMBER(AI96),N(AI96)>0),AH96/AI96*12,"") -> 7.0188679 | AK96: =IF(B96="","",OR(K96="Not in use",K96="Low use")+AND(N96<>"",N96<>"TBD")+AND(ISNUMBER(U96),U96<=EDATE('Scoring Settings'!$B$4,'Scoring Settings'!$B$8))+AND(ISNUMBER(L96),L96<='Scoring Settings'!$B$7)) -> 3 | AL96: Retire | AM96: =IF(B96="","",IF(Z96="N","Easy",IF(OR(AND(ISNUMBER(AB96),AB96>'Scoring Settings'!$B$11),AND(ISNUMBER(W96),W96>'Scoring Settings'!$B$12),AND(ISNUMBER(M96),M96<='Scoring Settings'!$B$13)),"High","Medium"))) -> Easy | AN96: Wave 1 | AO96: 44469 | AP96: In progress | AQ96: No active users; switch-off confirmed with owner Blocker: Replacement not yet funded Q: Is budget confirmed in the next planning cycle?
A97: 176641 | B97: Old Licence Manager Classic | C97: Licence Mgmt | D97: IT | E97: Internal | I97: 25 | J97: 44312 | K97: =IF(B97="","",IF(AND(I97="",J97=""),"Unknown",IF(OR(AND(ISNUMBER(I97),I97=0),AND(ISNUMBER(J97),J97<=EDATE('Scoring Settings'!$B$4,-'Scoring Settings'!$B$5))),"Not in use",IF(AND(ISNUMBER(I97),I97<'Scoring Settings'!$B$6),"Low use","Active")))) -> Active | L97: 3 | M97: 2 | N97: Splunk | O97: IaaS | P97: olmapp01, olmdb01, olmweb01 | Q97: 3 | R97: Windows Server 2008 | S97: SQL Server 2008 | T97: AWS eu-west-1 | U97: 43655 | V97: Structured | W97: 400 | X97: N | Y97: 7 | Z97: N | AA97: None | AB97: 23 | AC97: Y | AD97: Partial | AE97: Partial | AF97: 55000 | AG97: 47118 | AH97: 87500 | AI97: 35000 | AJ97: =IF(AND(ISNUMBER(AH97),ISNUMBER(AI97),N(AI97)>0),AH97/AI97*12,"") -> 30 | AK97: =IF(B97="","",OR(K97="Not in use",K97="Low use")+AND(N97<>"",N97<>"TBD")+AND(ISNUMBER(U97),U97<=EDATE('Scoring Settings'!$B$4,'Scoring Settings'!$B$8))+AND(ISNUMBER(L97),L97<='Scoring Settings'!$B$7)) -> 2 | AL97: Migrate | AM97: =IF(B97="","",IF(Z97="N","Easy",IF(OR(AND(ISNUMBER(AB97),AB97>'Scoring Settings'!$B$11),AND(ISNUMBER(W97),W97>'Scoring Settings'!$B$12),AND(ISNUMBER(M97),M97<='Scoring Settings'!$B$13)),"High","Medium"))) -> Easy | AN97: Wave 1 | AO97: 44530 | AP97: In progress | AQ97: 5 feeds to re-point to Splunk
A98: 187839 | B98: Departmental Commission Calculator (DE) | C98: Commissions | D98: Sales | E98: Internal | I98: 15 | J98: 44307 | K98: =IF(B98="","",IF(AND(I98="",J98=""),"Unknown",IF(OR(AND(ISNUMBER(I98),I98=0),AND(ISNUMBER(J98),J98<=EDATE('Scoring Settings'!$B$4,-'Scoring Settings'!$B$5))),"Not in use",IF(AND(ISNUMBER(I98),I98<'Scoring Settings'!$B$6),"Low use","Active")))) -> Low use | L98: 1 | M98: 4 | N98: Salesforce CPQ | O98: SaaS | P98: N/A (SaaS) | Q98: 0 | R98: N/A | S98: N/A | T98: Vendor cloud (EU) | U98: 45626 | V98: Structured | W98: 130 | X98: Y | Y98: 7 | Z98: N | AA98: None | AB98: 1 | AC98: Y | AD98: N | AE98: Partial | AF98: 60000 | AG98: 46599 | AH98: 58000 | AI98: 36500 | AJ98: =IF(AND(ISNUMBER(AH98),ISNUMBER(AI98),N(AI98)>0),AH98/AI98*12,"") -> 19.068493 | AK98: =IF(B98="","",OR(K98="Not in use",K98="Low use")+AND(N98<>"",N98<>"TBD")+AND(ISNUMBER(U98),U98<=EDATE('Scoring Settings'!$B$4,'Scoring Settings'!$B$8))+AND(ISNUMBER(L98),L98<='Scoring Settings'!$B$7)) -> 3 | AL98: Retire | AM98: =IF(B98="","",IF(Z98="N","Easy",IF(OR(AND(ISNUMBER(AB98),AB98>'Scoring Settings'!$B$11),AND(ISNUMBER(W98),W98>'Scoring Settings'!$B$12),AND(ISNUMBER(M98),M98<='Scoring Settings'!$B$13)),"High","Medium"))) -> Easy | AN98: Wave 1 | AO98: 44469 | AP98: In progress | AQ98: No active users; switch-off confirmed with owner
A99: 40283 | B99: Custom Corporate Website CMS v2 | C99: Web | D99: Marketing | E99: Internal | I99: 6 | J99: 44198 | K99: =IF(B99="","",IF(AND(I99="",J99=""),"Unknown",IF(OR(AND(ISNUMBER(I99),I99=0),AND(ISNUMBER(J99),J99<=EDATE('Scoring Settings'!$B$4,-'Scoring Settings'!$B$5))),"Not in use",IF(AND(ISNUMBER(I99),I99<'Scoring Settings'!$B$6),"Low use","Active")))) -> Low use | L99: 1 | M99: 4 | N99: TBD | O99: On-prem DC | P99: ccwapp01, ccwdb01 | Q99: 2 | R99: SUSE Linux 11 | S99: Oracle 11g | T99: EU DC-2 | U99: 43555 | V99: Structured | W99: 5 | X99: Y | Y99: 5 | Z99: N | AA99: None | AB99: 3 | AC99: N | AD99: Partial | AE99: N | AF99: 29500 | AG99: 47422 | AH99: 22000 | AI99: 25500 | AJ99: =IF(AND(ISNUMBER(AH99),ISNUMBER(AI99),N(AI99)>0),AH99/AI99*12,"") -> 10.352941 | AK99: =IF(B99="","",OR(K99="Not in use",K99="Low use")+AND(N99<>"",N99<>"TBD")+AND(ISNUMBER(U99),U99<=EDATE('Scoring Settings'!$B$4,'Scoring Settings'!$B$8))+AND(ISNUMBER(L99),L99<='Scoring Settings'!$B$7)) -> 3 | AL99: Retire | AM99: =IF(B99="","",IF(Z99="N","Easy",IF(OR(AND(ISNUMBER(AB99),AB99>'Scoring Settings'!$B$11),AND(ISNUMBER(W99),W99>'Scoring Settings'!$B$12),AND(ISNUMBER(M99),M99<='Scoring Settings'!$B$13)),"High","Medium"))) -> Easy | AN99: Wave 1 | AO99: 44347 | AP99: On hold | AQ99: On hold - audit request needs system access until Q3
A100: 82887 | B100: Shared Event Registration Tool (DE) | C100: Events | D100: Marketing | E100: Internal | I100: 1484 | J100: 44272 | K100: =IF(B100="","",IF(AND(I100="",J100=""),"Unknown",IF(OR(AND(ISNUMBER(I100),I100=0),AND(ISNUMBER(J100),J100<=EDATE('Scoring Settings'!$B$4,-'Scoring Settings'!$B$5))),"Not in use",IF(AND(ISNUMBER(I100),I100<'Scoring Settings'!$B$6),"Low use","Active")))) -> Active | L100: 3 | M100: 4 | N100: HubSpot (planned) | O100: On-prem DC | P100: serapp01, serdb01 | Q100: 2 | R100: RHEL 6 | S100: Oracle 11g | T100: Plant DC | U100: 44165 | V100: Structured | W100: 160 | X100: N | Y100: 3 | Z100: N | AA100: None | AB100: 3 | AC100: N | AD100: Partial | AE100: Partial | AF100: 20000 | AG100: 49643 | AH100: 12000 | AI100: 15000 | AJ100: =IF(AND(ISNUMBER(AH100),ISNUMBER(AI100),N(AI100)>0),AH100/AI100*12,"") -> 9.6 | AK100: =IF(B100="","",OR(K100="Not in use",K100="Low use")+AND(N100<>"",N100<>"TBD")+AND(ISNUMBER(U100),U100<=EDATE('Scoring Settings'!$B$4,'Scoring Settings'!$B$8))+AND(ISNUMBER(L100),L100<='Scoring Settings'!$B$7)) -> 2 | AL100: Migrate | AM100: =IF(B100="","",IF(Z100="N","Easy",IF(OR(AND(ISNUMBER(AB100),AB100>'Scoring Settings'!$B$11),AND(ISNUMBER(W100),W100>'Scoring Settings'!$B$12),AND(ISNUMBER(M100),M100<='Scoring Settings'!$B$13)),"High","Medium"))) -> Easy | AN100: Wave 1 | AO100: 44408 | AP100: In progress | AQ100: Funding approved; migration to HubSpot scheduled
...

Sheet Summary
A1: Decommissioning Summary
A2: All figures formula-driven from the Application Inventory tab.
A3: Current Wave | B3: Wave 1
A4: Status As On | B4: 44317
A5: Total applications | B5: =COUNTA('Application Inventory'!$B$5:$B$1004) -> 1000
A6: Applications with a decision (in plan) | B6: =COUNTIF('Application Inventory'!$AL$5:$AL$1004,"Decommission")+COUNTIF('Application Inventory'!$AL$5:$AL$1004,"Retire")+COUNTIF('Application Inventory'!$AL$5:$AL$1004,"Retire + Archive")+COUNTIF('Application Inventory'!$AL$5:$AL$1004,"Retain") -> 549
A7: Change candidates (Decommission / Retire / Retire + Archive) | B7: =COUNTIF('Application Inventory'!$AL$5:$AL$1004,"Decommission")+COUNTIF('Application Inventory'!$AL$5:$AL$1004,"Retire")+COUNTIF('Application Inventory'!$AL$5:$AL$1004,"Retire + Archive") -> 349
A8: Retain | B8: =COUNTIF('Application Inventory'!$AL$5:$AL$1004,"Retain") -> 200
A9: Pending decision | B9: =COUNTIF('Application Inventory'!$AL$5:$AL$1004,"Pending") -> 300
A10: Annual savings from change candidates ($) | B10: =SUMIF('Application Inventory'!$AL$5:$AL$1004,"Decommission",'Application Inventory'!$AI$5:$AI$1004)+SUMIF('Application Inventory'!$AL$5:$AL$1004,"Retire",'Application Inventory'!$AI$5:$AI$1004)+SUMIF('Application Inventory'!$AL$5:$AL$1004,"Retire + Archive",'Application Inventory'!$AI$5:$AI$1004) -> 12956000
A11: Completed to date (target retirement before May 2021) | B11: =COUNTIF('Application Inventory'!$AP$5:$AP$1004,"Completed") -> 58
A12: Decision | B12: Easy | C12: Medium | D12: High | E12: Total | F12: Annual Run Cost ($) | G12: Annual Savings ($) | H12: Est. Decom Cost ($) | I12: Data Volume (GB)
A13: Decommission | B13: =COUNTIFS('Application Inventory'!$AL$5:$AL$1004,$A13,'Application Inventory'!$AM$5:$AM$1004,"Easy") -> 0 | C13: =COUNTIFS('Application Inventory'!$AL$5:$AL$1004,$A13,'Application Inventory'!$AM$5:$AM$1004,"Medium") -> 0 | D13: =COUNTIFS('Application Inventory'!$AL$5:$AL$1004,$A13,'Application Inventory'!$AM$5:$AM$1004,"High") -> 0 | E13: =SUM(B13:D13) -> 0 | F13: =SUMIF('Application Inventory'!$AL$5:$AL$1004,$A13,'Application Inventory'!$AF$5:$AF$1004) -> 0 | G13: =SUMIF('Application Inventory'!$AL$5:$AL$1004,$A13,'Application Inventory'!$AI$5:$AI$1004) -> 0 | H13: =SUMIF('Application Inventory'!$AL$5:$AL$1004,$A13,'Application Inventory'!$AH$5:$AH$1004) -> 0 | I13: =SUMIF('Application Inventory'!$AL$5:$AL$1004,$A13,'Application Inventory'!$W$5:$W$1004) -> 0
A14: Retire | B14: =COUNTIFS('Application Inventory'!$AL$5:$AL$1004,$A14,'Application Inventory'!$AM$5:$AM$1004,"Easy") -> 161 | C14: =COUNTIFS('Application Inventory'!$AL$5:$AL$1004,$A14,'Application Inventory'!$AM$5:$AM$1004,"Medium") -> 0 | D14: =COUNTIFS('Application Inventory'!$AL$5:$AL$1004,$A14,'Application Inventory'!$AM$5:$AM$1004,"High") -> 0 | E14: =SUM(B14:D14) -> 161 | F14: =SUMIF('Application Inventory'!$AL$5:$AL$1004,$A14,'Application Inventory'!$AF$5:$AF$1004) -> 7969500 | G14: =SUMIF('Application Inventory'!$AL$5:$AL$1004,$A14,'Application Inventory'!$AI$5:$AI$1004) -> 6950000 | H14: =SUMIF('Application Inventory'!$AL$5:$AL$1004,$A14,'Application Inventory'!$AH$5:$AH$1004) -> 39038000 | I14: =SUMIF('Application Inventory'!$AL$5:$AL$1004,$A14,'Application Inventory'!$W$5:$W$1004) -> 53027
A15: Retire + Archive | B15: =COUNTIFS('Application Inventory'!$AL$5:$AL$1004,$A15,'Application Inventory'!$AM$5:$AM$1004,"Easy") -> 0 | C15: =COUNTIFS('Application Inventory'!$AL$5:$AL$1004,$A15,'Application Inventory'!$AM$5:$AM$1004,"Medium") -> 105 | D15: =COUNTIFS('Application Inventory'!$AL$5:$AL$1004,$A15,'Application Inventory'!$AM$5:$AM$1004,"High") -> 83 | E15: =SUM(B15:D15) -> 188 | F15: =SUMIF('Application Inventory'!$AL$5:$AL$1004,$A15,'Application Inventory'!$AF$5:$AF$1004) -> 9228000 | G15: =SUMIF('Application Inventory'!$AL$5:$AL$1004,$A15,'Application Inventory'!$AI$5:$AI$1004) -> 6006000 | H15: =SUMIF('Application Inventory'!$AL$5:$AL$1004,$A15,'Application Inventory'!$AH$5:$AH$1004) -> 13290500 | I15: =SUMIF('Application Inventory'!$AL$5:$AL$1004,$A15,'Application Inventory'!$W$5:$W$1004) -> 184467
A16: Retain | B16: =COUNTIFS('Application Inventory'!$AL$5:$AL$1004,$A16,'Application Inventory'!$AM$5:$AM$1004,"Easy") -> 83 | C16: =COUNTIFS('Application Inventory'!$AL$5:$AL$1004,$A16,'Application Inventory'!$AM$5:$AM$1004,"Medium") -> 18 | D16: =COUNTIFS('Application Inventory'!$AL$5:$AL$1004,$A16,'Application Inventory'!$AM$5:$AM$1004,"High") -> 99 | E16: =SUM(B16:D16) -> 200 | F16: =SUMIF('Application Inventory'!$AL$5:$AL$1004,$A16,'Application Inventory'!$AF$5:$AF$1004) -> 19221500 | G16: =SUMIF('Application Inventory'!$AL$5:$AL$1004,$A16,'Application Inventory'!$AI$5:$AI$1004) -> 0 | H16: =SUMIF('Application Inventory'!$AL$5:$AL$1004,$A16,'Application Inventory'!$AH$5:$AH$1004) -> 0 | I16: =SUMIF('Application Inventory'!$AL$5:$AL$1004,$A16,'Application Inventory'!$W$5:$W$1004) -> 104569
A17: Total | B17: =SUM(B13:B16) -> 244 | C17: =SUM(C13:C16) -> 123 | D17: =SUM(D13:D16) -> 182 | E17: =SUM(E13:E16) -> 549 | F17: =SUM(F13:F16) -> 36419000 | G17: =SUM(G13:G16) -> 12956000 | H17: =SUM(H13:H16) -> 52328500 | I17: =SUM(I13:I16) -> 342063
A19: Wave | B19: # Apps | C19: Annual Savings ($) | D19: Est. Decom Cost ($)
A20: Wave 1 | B20: =COUNTIF('Application Inventory'!$AN$5:$AN$1004,A20) -> 145 | C20: =SUMIF('Application Inventory'!$AN$5:$AN$1004,A20,'Application Inventory'!$AI$5:$AI$1004) -> 7647500 | D20: =SUMIF('Application Inventory'!$AN$5:$AN$1004,A20,'Application Inventory'!$AH$5:$AH$1004) -> 40835500
A21: Wave 2 | B21: =COUNTIF('Application Inventory'!$AN$5:$AN$1004,A21) -> 190 | C21: =SUMIF('Application Inventory'!$AN$5:$AN$1004,A21,'Application Inventory'!$AI$5:$AI$1004) -> 6919000 | D21: =SUMIF('Application Inventory'!$AN$5:$AN$1004,A21,'Application Inventory'!$AH$5:$AH$1004) -> 14090000
A22: Wave 3 | B22: =COUNTIF('Application Inventory'!$AN$5:$AN$1004,A22) -> 165 | C22: =SUMIF('Application Inventory'!$AN$5:$AN$1004,A22,'Application Inventory'!$AI$5:$AI$1004) -> 7503500 | D22: =SUMIF('Application Inventory'!$AN$5:$AN$1004,A22,'Application Inventory'!$AH$5:$AH$1004) -> 18336000
A23: Backlog | B23: =COUNTIF('Application Inventory'!$AN$5:$AN$1004,A23) -> 0 | C23: =SUMIF('Application Inventory'!$AN$5:$AN$1004,A23,'Application Inventory'!$AI$5:$AI$1004) -> 0 | D23: =SUMIF('Application Inventory'!$AN$5:$AN$1004,A23,'Application Inventory'!$AH$5:$AH$1004) -> 0
A25: Status | B25: # Apps
A26: Under Review | B26: =COUNTIF('Application Inventory'!$AP$5:$AP$1004,A26) -> 547
A27: Approved | B27: =COUNTIF('Application Inventory'!$AP$5:$AP$1004,A27) -> 152
A28: In progress | B28: =COUNTIF('Application Inventory'!$AP$5:$AP$1004,A28) -> 65
A29: On hold | B29: =COUNTIF('Application Inventory'!$AP$5:$AP$1004,A29) -> 4
A30: Completed | B30: =COUNTIF('Application Inventory'!$AP$5:$AP$1004,A30) -> 58
A31: Rejected | B31: =COUNTIF('Application Inventory'!$AP$5:$AP$1004,A31) -> 174
I32: Select Wave | J32: Wave 1
I33: Complexity | J33: (All)
A34: Planned retirements by month (formula-driven from Target Retirement Date and Decision)
A35: Target retirement period | B35: Migrate | C35: Retire | D35: Retire + Archive | E35: Total | F35: From | G35: To | I35: Count of App ID | J35: Column Labels
A36: Jan 2021 | B36: =COUNTIFS('Application Inventory'!$AL$5:$AL$1004,"Migrate",'Application Inventory'!$AO$5:$AO$1004,">="&$F36,'Application Inventory'!$AO$5:$AO$1004,"<="&$G36) -> 1 | C36: =COUNTIFS('Application Inventory'!$AL$5:$AL$1004,"Retire",'Application Inventory'!$AO$5:$AO$1004,">="&$F36,'Application Inventory'!$AO$5:$AO$1004,"<="&$G36) -> 4 | D36: =COUNTIFS('Application Inventory'!$AL$5:$AL$1004,"Retire + Archive",'Application Inventory'!$AO$5:$AO$1004,">="&$F36,'Application Inventory'!$AO$5:$AO$1004,"<="&$G36) -> 3 | E36: =SUM(B36:D36) -> 8 | F36: 44197 | G36: 44227 | I36: Row Labels | J36: 44227 | K36: 44255 | L36: 44286 | M36: 44316 | N36: 44347 | O36: 44377 | P36: 44408 | Q36: 44439 | R36: 44469 | S36: 44500 | T36: 44530 | U36: 44561 | V36: Grand Total
A37: Feb 2021 | B37: =COUNTIFS('Application Inventory'!$AL$5:$AL$1004,"Migrate",'Application Inventory'!$AO$5:$AO$1004,">="&$F37,'Application Inventory'!$AO$5:$AO$1004,"<="&$G37) -> 2 | C37: =COUNTIFS('Application Inventory'!$AL$5:$AL$1004,"Retire",'Application Inventory'!$AO$5:$AO$1004,">="&$F37,'Application Inventory'!$AO$5:$AO$1004,"<="&$G37) -> 3 | D37: =COUNTIFS('Application Inventory'!$AL$5:$AL$1004,"Retire + Archive",'Application Inventory'!$AO$5:$AO$1004,">="&$F37,'Application Inventory'!$AO$5:$AO$1004,"<="&$G37) -> 5 | E37: =SUM(B37:D37) -> 10 | F37: 44228 | G37: 44255 | I37: Approved | Q37: 2 | R37: 1 | S37: 2 | T37: 2 | U37: 11 | V37: 18
A38: Mar 2021 | B38: =COUNTIFS('Application Inventory'!$AL$5:$AL$1004,"Migrate",'Application Inventory'!$AO$5:$AO$1004,">="&$F38,'Application Inventory'!$AO$5:$AO$1004,"<="&$G38) -> 1 | C38: =COUNTIFS('Application Inventory'!$AL$5:$AL$1004,"Retire",'Application Inventory'!$AO$5:$AO$1004,">="&$F38,'Application Inventory'!$AO$5:$AO$1004,"<="&$G38) -> 7 | D38: =COUNTIFS('Application Inventory'!$AL$5:$AL$1004,"Retire + Archive",'Application Inventory'!$AO$5:$AO$1004,">="&$F38,'Application Inventory'!$AO$5:$AO$1004,"<="&$G38) -> 3 | E38: =SUM(B38:D38) -> 11 | F38: 44256 | G38: 44286 | I38: Completed | J38: 8 | K38: 10 | L38: 11 | M38: 17 | N38: 12 | V38: 58
A39: Apr 2021 | B39: =COUNTIFS('Application Inventory'!$AL$5:$AL$1004,"Migrate",'Application Inventory'!$AO$5:$AO$1004,">="&$F39,'Application Inventory'!$AO$5:$AO$1004,"<="&$G39) -> 6 | C39: =COUNTIFS('Application Inventory'!$AL$5:$AL$1004,"Retire",'Application Inventory'!$AO$5:$AO$1004,">="&$F39,'Application Inventory'!$AO$5:$AO$1004,"<="&$G39) -> 7 | D39: =COUNTIFS('Application Inventory'!$AL$5:$AL$1004,"Retire + Archive",'Application Inventory'!$AO$5:$AO$1004,">="&$F39,'Application Inventory'!$AO$5:$AO$1004,"<="&$G39) -> 4 | E39: =SUM(B39:D39) -> 17 | F39: 44287 | G39: 44316 | I39: Migrate | J39: 1 | K39: 2 | L39: 1 | M39: 6 | N39: 3 | V39: 13
A40: May 2021 | B40: =COUNTIFS('Application Inventory'!$AL$5:$AL$1004,"Migrate",'Application Inventory'!$AO$5:$AO$1004,">="&$F40,'Application Inventory'!$AO$5:$AO$1004,"<="&$G40) -> 4 | C40: =COUNTIFS('Application Inventory'!$AL$5:$AL$1004,"Retire",'Application Inventory'!$AO$5:$AO$1004,">="&$F40,'Application Inventory'!$AO$5:$AO$1004,"<="&$G40) -> 6 | D40: =COUNTIFS('Application Inventory'!$AL$5:$AL$1004,"Retire + Archive",'Application Inventory'!$AO$5:$AO$1004,">="&$F40,'Application Inventory'!$AO$5:$AO$1004,"<="&$G40) -> 6 | E40: =SUM(B40:D40) -> 16 | F40: 44317 | G40: 44347 | I40: Retire | J40: 4 | K40: 3 | L40: 7 | M40: 7 | N40: 3 | V40: 24
A41: Jun 2021 | B41: =COUNTIFS('Application Inventory'!$AL$5:$AL$1004,"Migrate",'Application Inventory'!$AO$5:$AO$1004,">="&$F41,'Application Inventory'!$AO$5:$AO$1004,"<="&$G41) -> 4 | C41: =COUNTIFS('Application Inventory'!$AL$5:$AL$1004,"Retire",'Application Inventory'!$AO$5:$AO$1004,">="&$F41,'Application Inventory'!$AO$5:$AO$1004,"<="&$G41) -> 3 | D41: =COUNTIFS('Application Inventory'!$AL$5:$AL$1004,"Retire + Archive",'Application Inventory'!$AO$5:$AO$1004,">="&$F41,'Application Inventory'!$AO$5:$AO$1004,"<="&$G41) -> 6 | E41: =SUM(B41:D41) -> 13 | F41: 44348 | G41: 44377 | I41: Retire + Archive | J41: 3 | K41: 5 | L41: 3 | M41: 4 | N41: 6 | V41: 21
A42: Jul 2021 | B42: =COUNTIFS('Application Inventory'!$AL$5:$AL$1004,"Migrate",'Application Inventory'!$AO$5:$AO$1004,">="&$F42,'Application Inventory'!$AO$5:$AO$1004,"<="&$G42) -> 5 | C42: =COUNTIFS('Application Inventory'!$AL$5:$AL$1004,"Retire",'Application Inventory'!$AO$5:$AO$1004,">="&$F42,'Application Inventory'!$AO$5:$AO$1004,"<="&$G42) -> 3 | D42: =COUNTIFS('Application Inventory'!$AL$5:$AL$1004,"Retire + Archive",'Application Inventory'!$AO$5:$AO$1004,">="&$F42,'Application Inventory'!$AO$5:$AO$1004,"<="&$G42) -> 4 | E42: =SUM(B42:D42) -> 12 | F42: 44378 | G42: 44408 | I42: In progress | O42: 9 | P42: 12 | Q42: 10 | R42: 12 | S42: 12 | T42: 10 | V42: 65
A43: Aug 2021 | B43: =COUNTIFS('Application Inventory'!$AL$5:$AL$1004,"Migrate",'Application Inventory'!$AO$5:$AO$1004,">="&$F43,'Application Inventory'!$AO$5:$AO$1004,"<="&$G43) -> 4 | C43: =COUNTIFS('Application Inventory'!$AL$5:$AL$1004,"Retire",'Application Inventory'!$AO$5:$AO$1004,">="&$F43,'Application Inventory'!$AO$5:$AO$1004,"<="&$G43) -> 4 | D43: =COUNTIFS('Application Inventory'!$AL$5:$AL$1004,"Retire + Archive",'Application Inventory'!$AO$5:$AO$1004,">="&$F43,'Application Inventory'!$AO$5:$AO$1004,"<="&$G43) -> 4 | E43: =SUM(B43:D43) -> 12 | F43: 44409 | G43: 44439 | I43: On hold | N43: 4 | V43: 4
A44: Sep 2021 | B44: =COUNTIFS('Application Inventory'!$AL$5:$AL$1004,"Migrate",'Application Inventory'!$AO$5:$AO$1004,">="&$F44,'Application Inventory'!$AO$5:$AO$1004,"<="&$G44) -> 5 | C44: =COUNTIFS('Application Inventory'!$AL$5:$AL$1004,"Retire",'Application Inventory'!$AO$5:$AO$1004,">="&$F44,'Application Inventory'!$AO$5:$AO$1004,"<="&$G44) -> 7 | D44: =COUNTIFS('Application Inventory'!$AL$5:$AL$1004,"Retire + Archive",'Application Inventory'!$AO$5:$AO$1004,">="&$F44,'Application Inventory'!$AO$5:$AO$1004,"<="&$G44) -> 1 | E44: =SUM(B44:D44) -> 13 | F44: 44440 | G44: 44469 | I44: Grand Total | J44: 8 | K44: 10 | L44: 11 | M44: 17 | N44: 16 | O44: 9 | P44: 12 | Q44: 12 | R44: 13 | S44: 14 | T44: 12 | U44: 11 | V44: 145
A45: Oct 2021 | B45: =COUNTIFS('Application Inventory'!$AL$5:$AL$1004,"Migrate",'Application Inventory'!$AO$5:$AO$1004,">="&$F45,'Application Inventory'!$AO$5:$AO$1004,"<="&$G45) -> 5 | C45: =COUNTIFS('Application Inventory'!$AL$5:$AL$1004,"Retire",'Application Inventory'!$AO$5:$AO$1004,">="&$F45,'Application Inventory'!$AO$5:$AO$1004,"<="&$G45) -> 6 | D45: =COUNTIFS('Application Inventory'!$AL$5:$AL$1004,"Retire + Archive",'Application Inventory'!$AO$5:$AO$1004,">="&$F45,'Application Inventory'!$AO$5:$AO$1004,"<="&$G45) -> 3 | E45: =SUM(B45:D45) -> 14 | F45: 44470 | G45: 44500
A46: Nov 2021 | B46: =COUNTIFS('Application Inventory'!$AL$5:$AL$1004,"Migrate",'Application Inventory'!$AO$5:$AO$1004,">="&$F46,'Application Inventory'!$AO$5:$AO$1004,"<="&$G46) -> 5 | C46: =COUNTIFS('Application Inventory'!$AL$5:$AL$1004,"Retire",'Application Inventory'!$AO$5:$AO$1004,">="&$F46,'Application Inventory'!$AO$5:$AO$1004,"<="&$G46) -> 2 | D46: =COUNTIFS('Application Inventory'!$AL$5:$AL$1004,"Retire + Archive",'Application Inventory'!$AO$5:$AO$1004,">="&$F46,'Application Inventory'!$AO$5:$AO$1004,"<="&$G46) -> 5 | E46: =SUM(B46:D46) -> 12 | F46: 44501 | G46: 44530
A47: Dec 2021 | B47: =COUNTIFS('Application Inventory'!$AL$5:$AL$1004,"Migrate",'Application Inventory'!$AO$5:$AO$1004,">="&$F47,'Application Inventory'!$AO$5:$AO$1004,"<="&$G47) -> 2 | C47: =COUNTIFS('Application Inventory'!$AL$5:$AL$1004,"Retire",'Application Inventory'!$AO$5:$AO$1004,">="&$F47,'Application Inventory'!$AO$5:$AO$1004,"<="&$G47) -> 3 | D47: =COUNTIFS('Application Inventory'!$AL$5:$AL$1004,"Retire + Archive",'Application Inventory'!$AO$5:$AO$1004,">="&$F47,'Application Inventory'!$AO$5:$AO$1004,"<="&$G47) -> 6 | E47: =SUM(B47:D47) -> 11 | F47: 44531 | G47: 44561
A48: Jan 2022 | B48: =COUNTIFS('Application Inventory'!$AL$5:$AL$1004,"Migrate",'Application Inventory'!$AO$5:$AO$1004,">="&$F48,'Application Inventory'!$AO$5:$AO$1004,"<="&$G48) -> 2 | C48: =COUNTIFS('Application Inventory'!$AL$5:$AL$1004,"Retire",'Application Inventory'!$AO$5:$AO$1004,">="&$F48,'Application Inventory'!$AO$5:$AO$1004,"<="&$G48) -> 6 | D48: =COUNTIFS('Application Inventory'!$AL$5:$AL$1004,"Retire + Archive",'Application Inventory'!$AO$5:$AO$1004,">="&$F48,'Application Inventory'!$AO$5:$AO$1004,"<="&$G48) -> 6 | E48: =SUM(B48:D48) -> 14 | F48: 44562 | G48: 44592
A49: Feb 2022 | B49: =COUNTIFS('Application Inventory'!$AL$5:$AL$1004,"Migrate",'Application Inventory'!$AO$5:$AO$1004,">="&$F49,'Application Inventory'!$AO$5:$AO$1004,"<="&$G49) -> 3 | C49: =COUNTIFS('Application Inventory'!$AL$5:$AL$1004,"Retire",'Application Inventory'!$AO$5:$AO$1004,">="&$F49,'Application Inventory'!$AO$5:$AO$1004,"<="&$G49) -> 5 | D49: =COUNTIFS('Application Inventory'!$AL$5:$AL$1004,"Retire + Archive",'Application Inventory'!$AO$5:$AO$1004,">="&$F49,'Application Inventory'!$AO$5:$AO$1004,"<="&$G49) -> 7 | E49: =SUM(B49:D49) -> 15 | F49: 44593 | G49: 44620
A50: Mar 2022 | B50: =COUNTIFS('Application Inventory'!$AL$5:$AL$1004,"Migrate",'Application Inventory'!$AO$5:$AO$1004,">="&$F50,'Application Inventory'!$AO$5:$AO$1004,"<="&$G50) -> 3 | C50: =COUNTIFS('Application Inventory'!$AL$5:$AL$1004,"Retire",'Application Inventory'!$AO$5:$AO$1004,">="&$F50,'Application Inventory'!$AO$5:$AO$1004,"<="&$G50) -> 5 | D50: =COUNTIFS('Application Inventory'!$AL$5:$AL$1004,"Retire + Archive",'Application Inventory'!$AO$5:$AO$1004,">="&$F50,'Application Inventory'!$AO$5:$AO$1004,"<="&$G50) -> 8 | E50: =SUM(B50:D50) -> 16 | F50: 44621 | G50: 44651
A51: Apr 2022 | B51: =COUNTIFS('Application Inventory'!$AL$5:$AL$1004,"Migrate",'Application Inventory'!$AO$5:$AO$1004,">="&$F51,'Application Inventory'!$AO$5:$AO$1004,"<="&$G51) -> 4 | C51: =COUNTIFS('Application Inventory'!$AL$5:$AL$1004,"Retire",'Application Inventory'!$AO$5:$AO$1004,">="&$F51,'Application Inventory'!$AO$5:$AO$1004,"<="&$G51) -> 3 | D51: =COUNTIFS('Application Inventory'!$AL$5:$AL$1004,"Retire + Archive",'Application Inventory'!$AO$5:$AO$1004,">="&$F51,'Application Inventory'!$AO$5:$AO$1004,"<="&$G51) -> 9 | E51: =SUM(B51:D51) -> 16 | F51: 44652 | G51: 44681 | I51: Select Wave | J51: Sum of Annual Savings ($)
A52: May 2022 | B52: =COUNTIFS('Application Inventory'!$AL$5:$AL$1004,"Migrate",'Application Inventory'!$AO$5:$AO$1004,">="&$F52,'Application Inventory'!$AO$5:$AO$1004,"<="&$G52) -> 3 | C52: =COUNTIFS('Application Inventory'!$AL$5:$AL$1004,"Retire",'Application Inventory'!$AO$5:$AO$1004,">="&$F52,'Application Inventory'!$AO$5:$AO$1004,"<="&$G52) -> 8 | D52: =COUNTIFS('Application Inventory'!$AL$5:$AL$1004,"Retire + Archive",'Application Inventory'!$AO$5:$AO$1004,">="&$F52,'Application Inventory'!$AO$5:$AO$1004,"<="&$G52) -> 6 | E52: =SUM(B52:D52) -> 17 | F52: 44682 | G52: 44712 | I52: Wave 1 | J52: 7647500
A53: Jun 2022 | B53: =COUNTIFS('Application Inventory'!$AL$5:$AL$1004,"Migrate",'Application Inventory'!$AO$5:$AO$1004,">="&$F53,'Application Inventory'!$AO$5:$AO$1004,"<="&$G53) -> 4 | C53: =COUNTIFS('Application Inventory'!$AL$5:$AL$1004,"Retire",'Application Inventory'!$AO$5:$AO$1004,">="&$F53,'Application Inventory'!$AO$5:$AO$1004,"<="&$G53) -> 1 | D53: =COUNTIFS('Application Inventory'!$AL$5:$AL$1004,"Retire + Archive",'Application Inventory'!$AO$5:$AO$1004,">="&$F53,'Application Inventory'!$AO$5:$AO$1004,"<="&$G53) -> 8 | E53: =SUM(B53:D53) -> 13 | F53: 44713 | G53: 44742 | I53: 44227 | J53: 246500
A54: Jul 2022 | B54: =COUNTIFS('Application Inventory'!$AL$5:$AL$1004,"Migrate",'Application Inventory'!$AO$5:$AO$1004,">="&$F54,'Application Inventory'!$AO$5:$AO$1004,"<="&$G54) -> 2 | C54: =COUNTIFS('Application Inventory'!$AL$5:$AL$1004,"Retire",'Application Inventory'!$AO$5:$AO$1004,">="&$F54,'Application Inventory'!$AO$5:$AO$1004,"<="&$G54) -> 8 | D54: =COUNTIFS('Application Inventory'!$AL$5:$AL$1004,"Retire + Archive",'Application Inventory'!$AO$5:$AO$1004,">="&$F54,'Application Inventory'!$AO$5:$AO$1004,"<="&$G54) -> 6 | E54: =SUM(B54:D54) -> 16 | F54: 44743 | G54: 44773 | I54: 44255 | J54: 545000
A55: Aug 2022 | B55: =COUNTIFS('Application Inventory'!$AL$5:$AL$1004,"Migrate",'Application Inventory'!$AO$5:$AO$1004,">="&$F55,'Application Inventory'!$AO$5:$AO$1004,"<="&$G55) -> 7 | C55: =COUNTIFS('Application Inventory'!$AL$5:$AL$1004,"Retire",'Application Inventory'!$AO$5:$AO$1004,">="&$F55,'Application Inventory'!$AO$5:$AO$1004,"<="&$G55) -> 4 | D55: =COUNTIFS('Application Inventory'!$AL$5:$AL$1004,"Retire + Archive",'Application Inventory'!$AO$5:$AO$1004,">="&$F55,'Application Inventory'!$AO$5:$AO$1004,"<="&$G55) -> 5 | E55: =SUM(B55:D55) -> 16 | F55: 44774 | G55: 44804 | I55: 44286 | J55: 527500
A56: Sep 2022 | B56: =COUNTIFS('Application Inventory'!$AL$5:$AL$1004,"Migrate",'Application Inventory'!$AO$5:$AO$1004,">="&$F56,'Application Inventory'!$AO$5:$AO$1004,"<="&$G56) -> 5 | C56: =COUNTIFS('Application Inventory'!$AL$5:$AL$1004,"Retire",'Application Inventory'!$AO$5:$AO$1004,">="&$F56,'Application Inventory'!$AO$5:$AO$1004,"<="&$G56) -> 1 | D56: =COUNTIFS('Application Inventory'!$AL$5:$AL$1004,"Retire + Archive",'Application Inventory'!$AO$5:$AO$1004,">="&$F56,'Application Inventory'!$AO$5:$AO$1004,"<="&$G56) -> 11 | E56: =SUM(B56:D56) -> 17 | F56: 44805 | G56: 44834 | I56: 44316 | J56: 967000
A57: Oct 2022 | B57: =COUNTIFS('Application Inventory'!$AL$5:$AL$1004,"Migrate",'Application Inventory'!$AO$5:$AO$1004,">="&$F57,'Application Inventory'!$AO$5:$AO$1004,"<="&$G57) -> 6 | C57: =COUNTIFS('Application Inventory'!$AL$5:$AL$1004,"Retire",'Application Inventory'!$AO$5:$AO$1004,">="&$F57,'Application Inventory'!$AO$5:$AO$1004,"<="&$G57) -> 7 | D57: =COUNTIFS('Application Inventory'!$AL$5:$AL$1004,"Retire + Archive",'Application Inventory'!$AO$5:$AO$1004,">="&$F57,'Application Inventory'!$AO$5:$AO$1004,"<="&$G57) -> 3 | E57: =SUM(B57:D57) -> 16 | F57: 44835 | G57: 44865 | I57: 44347 | J57: 1082500
A58: Nov 2022 | B58: =COUNTIFS('Application Inventory'!$AL$5:$AL$1004,"Migrate",'Application Inventory'!$AO$5:$AO$1004,">="&$F58,'Application Inventory'!$AO$5:$AO$1004,"<="&$G58) -> 5 | C58: =COUNTIFS('Application Inventory'!$AL$5:$AL$1004,"Retire",'Application Inventory'!$AO$5:$AO$1004,">="&$F58,'Application Inventory'!$AO$5:$AO$1004,"<="&$G58) -> 4 | D58: =COUNTIFS('Application Inventory'!$AL$5:$AL$1004,"Retire + Archive",'Application Inventory'!$AO$5:$AO$1004,">="&$F58,'Application Inventory'!$AO$5:$AO$1004,"<="&$G58) -> 6 | E58: =SUM(B58:D58) -> 15 | F58: 44866 | G58: 44895 | I58: 44377 | J58: 500500
A59: Dec 2022 | B59: =COUNTIFS('Application Inventory'!$AL$5:$AL$1004,"Migrate",'Application Inventory'!$AO$5:$AO$1004,">="&$F59,'Application Inventory'!$AO$5:$AO$1004,"<="&$G59) -> 6 | C59: =COUNTIFS('Application Inventory'!$AL$5:$AL$1004,"Retire",'Application Inventory'!$AO$5:$AO$1004,">="&$F59,'Application Inventory'!$AO$5:$AO$1004,"<="&$G59) -> 4 | D59: =COUNTIFS('Application Inventory'!$AL$5:$AL$1004,"Retire + Archive",'Application Inventory'!$AO$5:$AO$1004,">="&$F59,'Application Inventory'!$AO$5:$AO$1004,"<="&$G59) -> 5 | E59: =SUM(B59:D59) -> 15 | F59: 44896 | G59: 44926 | I59: 44408 | J59: 535500
A60: Jan 2023 | B60: =COUNTIFS('Application Inventory'!$AL$5:$AL$1004,"Migrate",'Application Inventory'!$AO$5:$AO$1004,">="&$F60,'Application Inventory'!$AO$5:$AO$1004,"<="&$G60) -> 9 | C60: =COUNTIFS('Application Inventory'!$AL$5:$AL$1004,"Retire",'Application Inventory'!$AO$5:$AO$1004,">="&$F60,'Application Inventory'!$AO$5:$AO$1004,"<="&$G60) -> 4 | D60: =COUNTIFS('Application Inventory'!$AL$5:$AL$1004,"Retire + Archive",'Application Inventory'!$AO$5:$AO$1004,">="&$F60,'Application Inventory'!$AO$5:$AO$1004,"<="&$G60) -> 2 | E60: =SUM(B60:D60) -> 15 | F60: 44927 | G60: 44957 | I60: 44439 | J60: 539000
A61: Feb 2023 | B61: =COUNTIFS('Application Inventory'!$AL$5:$AL$1004,"Migrate",'Application Inventory'!$AO$5:$AO$1004,">="&$F61,'Application Inventory'!$AO$5:$AO$1004,"<="&$G61) -> 5 | C61: =COUNTIFS('Application Inventory'!$AL$5:$AL$1004,"Retire",'Application Inventory'!$AO$5:$AO$1004,">="&$F61,'Application Inventory'!$AO$5:$AO$1004,"<="&$G61) -> 3 | D61: =COUNTIFS('Application Inventory'!$AL$5:$AL$1004,"Retire + Archive",'Application Inventory'!$AO$5:$AO$1004,">="&$F61,'Application Inventory'!$AO$5:$AO$1004,"<="&$G61) -> 7 | E61: =SUM(B61:D61) -> 15 | F61: 44958 | G61: 44985 | I61: 44469 | J61: 745500
A62: Mar 2023 | B62: =COUNTIFS('Application Inventory'!$AL$5:$AL$1004,"Migrate",'Application Inventory'!$AO$5:$AO$1004,">="&$F62,'Application Inventory'!$AO$5:$AO$1004,"<="&$G62) -> 4 | C62: =COUNTIFS('Application Inventory'!$AL$5:$AL$1004,"Retire",'Application Inventory'!$AO$5:$AO$1004,">="&$F62,'Application Inventory'!$AO$5:$AO$1004,"<="&$G62) -> 6 | D62: =COUNTIFS('Application Inventory'!$AL$5:$AL$1004,"Retire + Archive",'Application Inventory'!$AO$5:$AO$1004,">="&$F62,'Application Inventory'!$AO$5:$AO$1004,"<="&$G62) -> 6 | E62: =SUM(B62:D62) -> 16 | F62: 44986 | G62: 45016 | I62: 44500 | J62: 1099000
A63: Apr 2023 | B63: =COUNTIFS('Application Inventory'!$AL$5:$AL$1004,"Migrate",'Application Inventory'!$AO$5:$AO$1004,">="&$F63,'Application Inventory'!$AO$5:$AO$1004,"<="&$G63) -> 3 | C63: =COUNTIFS('Application Inventory'!$AL$5:$AL$1004,"Retire",'Application Inventory'!$AO$5:$AO$1004,">="&$F63,'Application Inventory'!$AO$5:$AO$1004,"<="&$G63) -> 9 | D63: =COUNTIFS('Application Inventory'!$AL$5:$AL$1004,"Retire + Archive",'Application Inventory'!$AO$5:$AO$1004,">="&$F63,'Application Inventory'!$AO$5:$AO$1004,"<="&$G63) -> 4 | E63: =SUM(B63:D63) -> 16 | F63: 45017 | G63: 45046 | I63: 44530 | J63: 423000
A64: May 2023 | B64: =COUNTIFS('Application Inventory'!$AL$5:$AL$1004,"Migrate",'Application Inventory'!$AO$5:$AO$1004,">="&$F64,'Application Inventory'!$AO$5:$AO$1004,"<="&$G64) -> 7 | C64: =COUNTIFS('Application Inventory'!$AL$5:$AL$1004,"Retire",'Application Inventory'!$AO$5:$AO$1004,">="&$F64,'Application Inventory'!$AO$5:$AO$1004,"<="&$G64) -> 4 | D64: =COUNTIFS('Application Inventory'!$AL$5:$AL$1004,"Retire + Archive",'Application Inventory'!$AO$5:$AO$1004,">="&$F64,'Application Inventory'!$AO$5:$AO$1004,"<="&$G64) -> 4 | E64: =SUM(B64:D64) -> 15 | F64: 45047 | G64: 45077 | I64: 44561 | J64: 436500
A65: Jun 2023 | B65: =COUNTIFS('Application Inventory'!$AL$5:$AL$1004,"Migrate",'Application Inventory'!$AO$5:$AO$1004,">="&$F65,'Application Inventory'!$AO$5:$AO$1004,"<="&$G65) -> 5 | C65: =COUNTIFS('Application Inventory'!$AL$5:$AL$1004,"Retire",'Application Inventory'!$AO$5:$AO$1004,">="&$F65,'Application Inventory'!$AO$5:$AO$1004,"<="&$G65) -> 4 | D65: =COUNTIFS('Application Inventory'!$AL$5:$AL$1004,"Retire + Archive",'Application Inventory'!$AO$5:$AO$1004,">="&$F65,'Application Inventory'!$AO$5:$AO$1004,"<="&$G65) -> 5 | E65: =SUM(B65:D65) -> 14 | F65: 45078 | G65: 45107 | I65: Wave 2 | J65: 6919000
A66: Jul 2023 | B66: =COUNTIFS('Application Inventory'!$AL$5:$AL$1004,"Migrate",'Application Inventory'!$AO$5:$AO$1004,">="&$F66,'Application Inventory'!$AO$5:$AO$1004,"<="&$G66) -> 9 | C66: =COUNTIFS('Application Inventory'!$AL$5:$AL$1004,"Retire",'Application Inventory'!$AO$5:$AO$1004,">="&$F66,'Application Inventory'!$AO$5:$AO$1004,"<="&$G66) -> 2 | D66: =COUNTIFS('Application Inventory'!$AL$5:$AL$1004,"Retire + Archive",'Application Inventory'!$AO$5:$AO$1004,">="&$F66,'Application Inventory'!$AO$5:$AO$1004,"<="&$G66) -> 3 | E66: =SUM(B66:D66) -> 14 | F66: 45108 | G66: 45138 | I66: Wave 3 | J66: 7503500
A67: Aug 2023 | B67: =COUNTIFS('Application Inventory'!$AL$5:$AL$1004,"Migrate",'Application Inventory'!$AO$5:$AO$1004,">="&$F67,'Application Inventory'!$AO$5:$AO$1004,"<="&$G67) -> 6 | C67: =COUNTIFS('Application Inventory'!$AL$5:$AL$1004,"Retire",'Application Inventory'!$AO$5:$AO$1004,">="&$F67,'Application Inventory'!$AO$5:$AO$1004,"<="&$G67) -> 3 | D67: =COUNTIFS('Application Inventory'!$AL$5:$AL$1004,"Retire + Archive",'Application Inventory'!$AO$5:$AO$1004,">="&$F67,'Application Inventory'!$AO$5:$AO$1004,"<="&$G67) -> 5 | E67: =SUM(B67:D67) -> 14 | F67: 45139 | G67: 45169 | I67: (blank) | J67: 9631000
A68: Sep 2023 | B68: =COUNTIFS('Application Inventory'!$AL$5:$AL$1004,"Migrate",'Application Inventory'!$AO$5:$AO$1004,">="&$F68,'Application Inventory'!$AO$5:$AO$1004,"<="&$G68) -> 4 | C68: =COUNTIFS('Application Inventory'!$AL$5:$AL$1004,"Retire",'Application Inventory'!$AO$5:$AO$1004,">="&$F68,'Application Inventory'!$AO$5:$AO$1004,"<="&$G68) -> 2 | D68: =COUNTIFS('Application Inventory'!$AL$5:$AL$1004,"Retire + Archive",'Application Inventory'!$AO$5:$AO$1004,">="&$F68,'Application Inventory'!$AO$5:$AO$1004,"<="&$G68) -> 7 | E68: =SUM(B68:D68) -> 13 | F68: 45170 | G68: 45199 | I68: Grand Total | J68: 31701000
A69: Oct 2023 | B69: =COUNTIFS('Application Inventory'!$AL$5:$AL$1004,"Migrate",'Application Inventory'!$AO$5:$AO$1004,">="&$F69,'Application Inventory'!$AO$5:$AO$1004,"<="&$G69) -> 4 | C69: =COUNTIFS('Application Inventory'!$AL$5:$AL$1004,"Retire",'Application Inventory'!$AO$5:$AO$1004,">="&$F69,'Application Inventory'!$AO$5:$AO$1004,"<="&$G69) -> 2 | D69: =COUNTIFS('Application Inventory'!$AL$5:$AL$1004,"Retire + Archive",'Application Inventory'!$AO$5:$AO$1004,">="&$F69,'Application Inventory'!$AO$5:$AO$1004,"<="&$G69) -> 6 | E69: =SUM(B69:D69) -> 12 | F69: 45200 | G69: 45230
A70: Nov 2023 | B70: =COUNTIFS('Application Inventory'!$AL$5:$AL$1004,"Migrate",'Application Inventory'!$AO$5:$AO$1004,">="&$F70,'Application Inventory'!$AO$5:$AO$1004,"<="&$G70) -> 1 | C70: =COUNTIFS('Application Inventory'!$AL$5:$AL$1004,"Retire",'Application Inventory'!$AO$5:$AO$1004,">="&$F70,'Application Inventory'!$AO$5:$AO$1004,"<="&$G70) -> 6 | D70: =COUNTIFS('Application Inventory'!$AL$5:$AL$1004,"Retire + Archive",'Application Inventory'!$AO$5:$AO$1004,">="&$F70,'Application Inventory'!$AO$5:$AO$1004,"<="&$G70) -> 4 | E70: =SUM(B70:D70) -> 11 | F70: 45231 | G70: 45260
A71: Dec 2023 | B71: =COUNTIFS('Application Inventory'!$AL$5:$AL$1004,"Migrate",'Application Inventory'!$AO$5:$AO$1004,">="&$F71,'Application Inventory'!$AO$5:$AO$1004,"<="&$G71) -> 0 | C71: =COUNTIFS('Application Inventory'!$AL$5:$AL$1004,"Retire",'Application Inventory'!$AO$5:$AO$1004,">="&$F71,'Application Inventory'!$AO$5:$AO$1004,"<="&$G71) -> 5 | D71: =COUNTIFS('Application Inventory'!$AL$5:$AL$1004,"Retire + Archive",'Application Inventory'!$AO$5:$AO$1004,">="&$F71,'Application Inventory'!$AO$5:$AO$1004,"<="&$G71) -> 5 | E71: =SUM(B71:D71) -> 10 | F71: 45261 | G71: 45291
A72: Total | B72: =SUM(B36:B71) -> 151 | C72: =SUM(C36:C71) -> 161 | D72: =SUM(D36:D71) -> 188 | E72: =SUM(E36:E71) -> 500

Sheet Dashboard
A1: Decommissioning Dashboard
A2: Excel charts linked to Summary formulas – they update as the Application Inventory changes.

Sheet Scoring Settings
A1: Scoring Settings
A2: Values used by the Application Inventory formulas. Edit blue cells only.
A3: DECISION
A4: As-of date (assessment date) | B4: 44317 | C4: All date checks are measured from this date
A5: Not in use if last used more than (months) ago | B5: 6 | C5: Or Active Users = 0 → 'Not in use' → Priority
A6: Low use if active users below | B6: 25 | C6: Counts as a retirement driver
A7: Low business value if score ≤ | B7: 2 | C7: Counts as a retirement driver
A8: Out of support if EOS within (months) | B8: 12 | C8: EOS already passed or due within window → driver
A9: Decommission if drivers ≥ | B9: 2 | C9: Indicative only - the Decision is set in the plan (see rules below)
A10: COMPLEXITY
A11: High if interfaces more than | B11: 5 | C11: Only applies when Data Archival Required = Y
A12: High if data volume (GB) more than | B12: 1000 | C12: Only applies when Data Archival Required = Y
A13: High if criticality tier ≤ | B13: 2 | C13: Tier 1–2 = business critical
A15: RULES
A16: Retirement drivers (0–4): Low / no use · Replacement named · Out of support · Low business value
A17: Decision (set in plan): Decommission = migrate to a named replacement then switch off · Retire = switch off, no archive · Retire + Archive = switch off and archive data · Retain = keep · Pending = not yet decided
A18: Complexity: Data Archival Required = N → Easy · else any High trigger → High · else Medium
